Workbook
Name OwnerName: Settings!$C$6
Name Age: Settings!$C$7
Name HeightCm: Settings!$C$8
Name StartWeight: Settings!$C$9
Name StartBF: Settings!$C$10
Name GoalBF: Settings!$C$11
Name LeanMass: Settings!$C$12
Name GoalWeight: Settings!$C$13
Name TrackStart: Settings!$C$15
Name WakeTime: Settings!$C$16
Name TrainTime: Settings!$C$17
Name WorkHours: Settings!$C$18
Name LightsOut: Settings!$C$19
Name WorkDays: Settings!$C$20
Name StrDays: Settings!$C$21
Name ProtTarget: Settings!$C$23
Name ProtHit: Settings!$C$24
Name ProtDinner: Settings!$C$25
Name ProtMVD: Settings!$C$26
Name KcalMin: Settings!$C$27
Name KcalMax: Settings!$C$28
Name FatRange: Settings!$C$29
Name WaterHit: Settings!$C$30
Name WaterMVD: Settings!$C$31
Name SleepTarget: Settings!$C$33
Name SleepMin: Settings!$C$34
Name SleepLow: Settings!$C$35
Name Steps1: Settings!$C$37
Name Steps2: Settings!$C$38
Name Steps3: Settings!$C$39
Name StepsAlert: Settings!$C$40
Name LossMin: Settings!$C$42
Name LossMax: Settings!$C$43
Name LossMaxPct: Settings!$C$44
Name Band1: Settings!$C$46
Name Band2: Settings!$C$47
Name Band3: Settings!$C$48
Name RecoveryLow: Settings!$C$49
Name PlanTraining: Settings!$H$7:$H$13
Name PlanRest: Settings!$I$7:$I$13
Name k_Mode: Calc!$B$4
Name k_Wd: Calc!$B$5
Name k_PlanT: Calc!$B$6
Name k_PlanR: Calc!$B$7
Name k_T_wake: Calc!$B$8
Name k_T_pray: Calc!$B$9
Name k_T_mob: Calc!$B$10
Name k_T_move: Calc!$B$11
Name k_T_top3: Calc!$B$12
Name k_T_love: Calc!$B$13
Name k_T_read: Calc!$B$14
Name k_T_shut: Calc!$B$15
Name k_T_sleep: Calc!$B$16
Name k_T_str: Calc!$B$17
Name k_T_prog: Calc!$B$18
Name k_T_core: Calc!$B$19
Name k_T_calf: Calc!$B$20
Name k_T_cardio: Calc!$B$21
Name k_T_deep: Calc!$B$22
Name k_T_brk: Calc!$B$23

Sheet Start Here
B2: LIFE OS · START HERE
B3: Lucas's personal operating system. Consistency > Intensity · Progress > Perfection · Systems > Motivation · Health > Extreme results
B5: THE 60-SECOND DAILY CHECK-IN | E5: THE TABS
B6: 1 | C6: Open this month's tab (Oct 2026, Nov 2026…). Today's date is highlighted in yellow. | E6: Dashboard | F6: Today · this week · this month · coach · system check · pillars · charts. Change the yellow date to look back.
B7: 2 | C7: Tick the habits you did. Level 3 is bonus only. | E7: Week Plan | F7: Top 3 and tasks for each day, daily donuts and check-ins (task-tracker layout).
B8: 3 | C8: Type the numbers you have in BODY & MIND: weight, steps, protein, water, sleep, energy, stress, mood. Blank is fine. | E8: Month tabs | F8: The habit grid, scores, body & mind numbers, charts. This is where you log.
B9: 4 | C9: Hard day? Type M in the Day mode row. Sick? Type S. Planned rest? R. | E9: Body | F9: Profile, goal estimate, measurements every 2 weeks, monthly photos, trend charts.
B10: 5 | C10: Glance at the Dashboard: Foundation score, rolling 7-day, Smart Coach. | E10: Weekly Review | F10: Sunday, 15–30 min. Numbers fill themselves; write wins, problems and ONE change.
E11: Monthly Review | F11: Once a month: body, health, mind, spirit, relationships, business, stop/start/continue.
E12: Habit Library | F12: Every habit with level, pillar, target, what counts, and 7/30-day scores.
E13: Plan & Routines | F13: The playbook: routines, training, nutrition, MVD, sick days, eye and jaw notes.
E14: Settings | F14: Targets and thresholds. Change them here and everything follows.
E15: Calc · Data | F15: The engine. Don't type there.
B17: THREE LEVELS | E17: HOW SCORING WORKS
B18: Level 1 | C18: Non-negotiables. The small daily foundation: morning reset, prayer, mobility, movement, Top 3, fiancée, read/learn, shutdown, lights out (+ protein, water, steps, sleep from your numbers). | E18: Foundation | F18: Each day gets one score from 9 things: sleep, movement, protein, water, steps, prayer, Top 3 (work days only), fiancée, read/learn.
B19: Level 2 | C19: High value, scored against weekly targets: strength 4×, progression, core 3×, calves 3×, cardio 2×, deep work, breaks, home reset, son, couple time, family, church, meal prep. | E19: Rolling | F19: The headline numbers are rolling 7-day and 30-day averages, not streaks. One missed day can't wipe anything out.
B20: Level 3 | C20: Optional. Never counts against you. | E20: Bands | F20: Green ≥ 85% · Good 70–84% · Needs attention 50–69% · Reset < 50%
E21: Modes | F21: M days are scored on the Minimum Viable Day list. S days are paused.
E22: Missed vs failed | F22: The System Check separates 'one off day', 'missed a few habits' and 'the system is too complicated'. It never says 'failed'. When adherence drops, it tells you to simplify, not to try harder.
B24: PRINCIPLES | E24: GOOGLE SHEETS SETUP · once
B25: 1 | C25: Consistency > intensity | E25: 1 | F25: Google Drive → New → File upload → Lucas-Life-OS.xlsx → open it → File → Save as Google Sheets.
B26: 2 | C26: Progress > perfection | E26: 2 | F26: In the Google Sheet: Extensions → Apps Script. Paste the contents of life_os_setup.gs, save, click Run on finishSetup and allow access.
B27: 3 | C27: Systems > motivation | E27: 3 | F27: That converts the grids to real checkboxes, applies Montserrat, dark-styles the charts and adds a 'Life OS' menu (Go to today · New week).
B28: 4 | C28: Health > extreme results | E28: No script? | F28: Everything still works: type x in a cell instead of ticking. Or select a grid and use Insert → Checkbox.
B29: Note | C29: This is a personal planning tool, not medical advice. For eyes, jaw or anything persistent, see a professional.

Sheet Dashboard
B2: LIFE OS | N2: SHOWING | P2: =TODAY()
N3: DAY MODE | P3: =IF(k_Mode="M","Minimum Viable Day",IF(k_Mode="S","Sick day · score paused",IF(k_Mode="R","Rest / recovery day","Normal day")))
B4: Lucas · personal operating system · Consistency > Intensity · Progress > Perfection · Systems > Motivation · Health > Extreme results | N4: type any date in the yellow cell to look back · =TODAY() for live
B6: FOUNDATION · TODAY | E6: ROLLING 7-DAY | H6: ROLLING 30-DAY | K6: STATUS · 7 DAY | N6: WEIGHT · 7-DAY AVG | Q6: WEEKLY RATE
B7: =k_T_score | E7: =k_T_r7 | H7: =k_T_r30 | K7: =k_Status7 | N7: =IF(ISNUMBER(k_T_w7),k_T_w7,"—") | Q7: =IF(ISNUMBER(k_Rate),k_Rate,"—")
B9: =IF(NOT(ISNUMBER(k_T_score)),IF(k_Mode="S","sick day · paused","not logged yet"),k_T_l1done&" of "&k_T_l1app&" non-negotiables") | E9: =k_Status7 | H9: =k_Status30 | K9: ="Green ≥85 · Good 70–84 · Attention 50–69 · Reset <50" | N9: =IF(ISNUMBER(k_T_weight),"today "&TEXT(k_T_weight,"0.0")&" kg","no weigh-in today") | Q9: =k_RateFlag
B11: ="TODAY · "&UPPER(TEXT(AsOf,"dddd"))&" · 06:00 wake + reset · 06:30 "&k_PlanT&" · 10:00–20:00 work · "&k_PlanR&" · 22:00 lights out"
B13: TODAY
B14: BODY | F14: MIND | I14: SPIRIT | L14: LIFE | P14: RECOVERY
B15: Weight | D15: =IF(ISNUMBER(k_T_weight),TEXT(k_T_weight,"0.0")&" kg","—") | F15: Read / learn | H15: =IF(k_T_read=1,"✓ done",IF(k_T_read="","—","○ open")) | I15: Prayer + Word | K15: =IF(k_T_pray=1,"✓ done",IF(k_T_pray="","—","○ open")) | L15: Top 3 set | N15: =IF(k_T_top3=1,"✓ done",IF(k_T_top3="","—","○ open")) | P15: Sleep | R15: =IF(ISNUMBER(k_T_sleeph),TEXT(k_T_sleeph,"0.0")&" h","—")
B16: Steps | D16: =IF(ISNUMBER(k_T_steps),TEXT(k_T_steps,"#,##0")&" / "&TEXT(k_T_stepT,"#,##0"),"— / "&TEXT(k_T_stepT,"#,##0")) | F16: Deep work | H16: =IF(k_T_deep=1,"✓ done",IF(k_T_deep="","—","○ open")) | I16: Church · wk | K16: =IF(k_Church7>0,"✓ "&k_Church7,"○ 0") | L16: Fiancée time | N16: =IF(k_T_love=1,"✓ done",IF(k_T_love="","—","○ open")) | P16: Lights out | R16: =IF(k_T_sleep=1,"✓ done",IF(k_T_sleep="","—","○ open"))
B17: Workout | D17: =IF(k_T_move=1,"✓ done",IF(k_T_move="","—","○ open")) | F17: Med / journal | H17: =IF(k_T_med=1,"✓ done",IF(k_T_med="","—","○ open")) | I17: Prayer · 7d | K17: =k_Pray7&" / 7" | L17: Son · this week | N17: =IF(k_Son7>0,"✓ "&k_Son7,"○ 0") | P17: Energy | R17: =IF(ISNUMBER(k_T_energy),TEXT(k_T_energy,"0")&"/10","—")
B18: Protein | D18: =IF(ISNUMBER(k_T_protein),TEXT(k_T_protein,"0")&" / "&ProtTarget&" g","— / "&ProtTarget&" g") | F18: Mood | H18: =IF(ISNUMBER(k_T_mood),TEXT(k_T_mood,"0")&"/10","—") | L18: Family · this week | N18: =IF(k_Family7>0,"✓ "&k_Family7,"○ 0") | P18: Stress | R18: =IF(ISNUMBER(k_T_stress),TEXT(k_T_stress,"0")&"/10","—")
B19: Water | D19: =IF(ISNUMBER(k_T_water),TEXT(k_T_water,"0.0")&" / "&TEXT(WaterHit,"0.0")&" L","— / "&TEXT(WaterHit,"0.0")&" L") | L19: Home reset | N19: =IF(k_T_home=1,"✓ done",IF(k_T_home="","—","○ open")) | P19: Recovery · 7d | R19: =IF(ISNUMBER(k_Recovery),k_Recovery&" / 100","—")
B20: Calories | D20: =IF(ISNUMBER(k_T_kcal),TEXT(k_T_kcal,"#,##0"),"—") | L20: Shutdown | N20: =IF(k_T_shut=1,"✓ done",IF(k_T_shut="","—","○ open"))
B22: SMART COACH · adaptive recommendations | N22: SYSTEM CHECK
B23: =IF(k_Mode="S","🤒 Sick-day rule: rest, fluids, protein-conscious food, sleep. No hard training, no deficit, no forced cardio. Resume gradually.","✓ Not a sick day.") | N23: =IF(NOT(ISNUMBER(k_T_r7)),"Start logging",IF(k_L1low>=3,"The system is too complicated",IF(k_T_r7<Band3,"Reset week, not a failure",IF(k_T_r7<Band2,"Missed a few habits",IF(AND(ISNUMBER(k_Y_score),k_Y_score<0.5),"One off day","System working")))))
B24: =IF(NOT(ISNUMBER(k_T_sleeph)),"· Log sleep hours to unlock recovery advice.",IF(k_T_sleeph<SleepLow,"⚠ Under "&SleepLow&" h sleep → make today a recovery day: walk + mobility, or cut the session to 2 easy sets per move.","✓ Sleep "&TEXT(k_T_sleeph,"0.0")&" h, train as planned."))
B25: =IF(NOT(ISNUMBER(k_T_protein)),"· Log protein to get a dinner nudge.",IF(k_T_protein<ProtDinner,"⚠ Protein at "&k_T_protein&" g → make dinner high-protein: chicken, eggs, lean beef, dholl + a whey shake (+25 g).","✓ Protein on track ("&k_T_protein&" g)."))
B26: =IF(AND(AsOf=TODAY(),HOUR(NOW())>=18,ISNUMBER(k_T_steps),k_T_steps<StepsAlert),"⚠ Under "&TEXT(StepsAlert,"#,##0")&" steps after 18:00 → 20–30 min walk (with your fiancée or son counts twice).",IF(ISNUMBER(k_T_steps),"✓ Steps "&TEXT(k_T_steps,"#,##0")&" of "&TEXT(k_T_stepT,"#,##0")&" target.","· Steps target today: "&TEXT(k_T_stepT,"#,##0")&".")) | N26: =IF(NOT(ISNUMBER(k_T_r7)),"Tick today's habits on the month tab. The scores appear from the first logged day.",IF(k_L1low>=3,"3+ non-negotiables under 50% this week. That's a design problem, not a character problem. Run Minimum Viable Days for 7 days and drop one high-value habit.",IF(k_T_r7<Band3,"Rolling 7-day under 50%. Don't add motivation tactics. Shrink to the Minimum Viable Day until it's back above 70%.",IF(k_T_r7<Band2,"You missed some habits. That's data, not failure. Pick the one that matters most and protect it tomorrow.",IF(AND(ISNUMBER(k_Y_score),k_Y_score<0.5),"Yesterday was low, the rolling average is still healthy. Restart today. No make-up work, no punishment.","Consistency > intensity. Keep the system the same size; don't add habits just because it's going well.")))))
B27: =IF(AND(k_Y_strday=1,k_Y_active=1,k_Y_mode<>"S",k_Y_str=0),"⚠ Yesterday's session was missed → don't reshuffle the week. Do the 20-minute minimum workout today (Plan & Routines).","✓ Training on plan. Today: "&k_PlanT&".")
B28: =IF(AND(ISNUMBER(k_T_w7),ISNUMBER(k_W7_m14)),IF(k_T_w7>=k_W7_m14,"⚠ 7-day average hasn't dropped in 14 days → trim 150–200 kcal or add ~2,000 steps a day. One change only.","✓ Weight trend moving the right way."),"· The weight rules switch on after 2 weeks of weigh-ins.")
B29: =IF(k_LossTooFast=1,"⚠ Losing more than 1% bodyweight a week, twice in a row → add 150–200 kcal and check recovery. Fat loss, not muscle loss.",IF(ISNUMBER(k_Rate),"✓ Rate of loss is sustainable (target 0.4–0.8 kg/week).","· The pace check starts after 2 weeks of weigh-ins."))
B30: =IF(NOT(ISNUMBER(k_Prot7)),"· Protein average appears after a few logged days.",IF(k_Prot7<ProtHit,"⚠ Protein averaging "&TEXT(k_Prot7,"0")&" g this week → muscle-preservation risk. Add one whey serving or an extra egg/chicken portion.","✓ Protein averaging "&TEXT(k_Prot7,"0")&" g.")) | N30: Non-negotiables · 7d | R30: =k_L1avg7
B31: =IF(NOT(ISNUMBER(k_Sleep7)),"· Sleep average appears after a few logged nights.",IF(k_Sleep7<SleepMin,"⚠ Sleep averaging "&TEXT(k_Sleep7,"0.0")&" h → protect 22:00 lights out before adding anything else.","✓ Sleep averaging "&TEXT(k_Sleep7,"0.0")&" h.")) | N31: High-value vs targets · 7d | R31: =k_L2avg7
B32: =IF(AND(k_Str14>=3,ISNUMBER(k_ProgRate14),k_ProgRate14<0.25),"⚠ Strength is stalling (progress in "&TEXT(k_ProgRate14,"0%")&" of sessions) → check sleep, protein and calories before pushing harder.",IF(ISNUMBER(k_ProgRate14),"✓ Progressive overload: "&TEXT(k_ProgRate14,"0%")&" of sessions improved something.","· Tick Progression achieved after each session to track overload.")) | N32: Non-negotiables under 50% | R32: =k_L1low
B33: =IF(AND(ISNUMBER(k_Recovery),k_Recovery<RecoveryLow),"⚠ Recovery score "&k_Recovery&" → lighter training this week: one set fewer, stop 2–3 reps before failure.",IF(ISNUMBER(k_Recovery),"✓ Recovery score "&k_Recovery&" / 100.","· Recovery score appears once you log sleep, energy and stress.")) | N33: Recovery score · 7d | R33: =IF(ISNUMBER(k_Recovery),k_Recovery,"—")
B34: =IF(k_Cardio7>4,"⚠ "&k_Cardio7&" cardio sessions this week → too much cardio eats into recovery and muscle. Keep it to 2–3.","✓ Cardio "&k_Cardio7&" / 2–3 this week.") | N34: Days logged · 7d | R34: =k_Logged7&" / 7"
B35: =IF(AND(ISNUMBER(k_Energy7),k_Energy7<=4),"⚠ Energy low all week → treat it as a recovery week. If it keeps happening, talk to a doctor.",IF(ISNUMBER(k_Energy7),"✓ Energy "&TEXT(k_Energy7,"0.0")&" / 10 this week.","· Log energy 1–10 to track fatigue.")) | N35: MINIMUM VIABLE DAY · water · 10-min walk · protein as close as possible · 5-min mobility · prayer · 10 min with your fiancée · lights out on time
B36: =IF(k_L1low>=3,"⚠ "&k_L1low&" non-negotiables slipped this week → SIMPLIFY THIS WEEK: run Minimum Viable Days, skip the optional list, add nothing new.","✓ No need to simplify. Keep the system the same size.")
B38: THIS WEEK · last 7 days | K38: THIS MONTH · last 30 days
B39: Weight trend (7-day avg vs last week) | G39: =IF(ISNUMBER(k_Rate),TEXT(k_Rate,"+0.00;-0.00")&" kg · "&k_RateFlag,"—") | K39: Weight change (7-day avg) | P39: =IF(ISNUMBER(k_Change30),TEXT(k_Change30,"+0.0;-0.0")&" kg","—")
B40: Strength sessions | G40: =k_Str7&" / 4" | K40: Waist (latest) | P40: =IF(ISNUMBER(k_Waist),TEXT(k_Waist,"0.0")&" cm"&IF(ISNUMBER(k_WaistPrev)," ("&TEXT(k_Waist-k_WaistPrev,"+0.0;-0.0")&")",""),"measure every 2 weeks")
B41: Progression rate (14 days) | G41: =IF(ISNUMBER(k_ProgRate14),TEXT(k_ProgRate14,"0%"),"—") | K41: Progress photos | P41: =IF(k_Photo30>0,"✓ taken","○ due this month")
B42: Core · calves · cardio | G42: =k_Core7&"/3 · "&k_Calf7&"/3 · "&k_Cardio7&"/2" | K42: Strength sessions | P42: =k_Str30&" (target ~17)"
B43: Protein average | G43: =IF(ISNUMBER(k_Prot7),TEXT(k_Prot7,"0")&" g / "&ProtTarget,"—") | K43: Reading / learning days | P43: =k_Read30&" / 30"
B44: Steps average | G44: =IF(ISNUMBER(k_Steps7),TEXT(k_Steps7,"#,##0")&" / "&TEXT(k_T_stepT,"#,##0"),"—") | K44: Prayer days | P44: =k_Pray30&" / 30"
B45: Sleep average | G45: =IF(ISNUMBER(k_Sleep7),TEXT(k_Sleep7,"0.0")&" h","—") | K45: Goal weight (if muscle kept) | P45: =TEXT(GoalWeight,"0.0")&" kg"
B46: Couple time · son · church · meal prep | G46: =k_Date7&" · "&k_Son7&" · "&k_Church7&" · "&k_Prep7 | K46: Weeks to goal at this pace | P46: =IF(ISNUMBER(k_WeeksToGoal),TEXT(k_WeeksToGoal,"0")&" weeks","needs a downward trend")
B48: PILLARS · 30-day consistency (high-value habits are scored against their weekly targets)
B49: BODY | E49: =IF(ISNUMBER(I49),REPT("█",ROUND(MAX(0,MIN(1,I49))*16,0))&REPT("░",16-ROUND(MAX(0,MIN(1,I49))*16,0)),"") | I49: =IFERROR(AVERAGEIFS('Habit Library'!$M$6:$M$40,'Habit Library'!$D$6:$D$40,"Body"),"") | K49: SPIRIT | N49: =IF(ISNUMBER(R49),REPT("█",ROUND(MAX(0,MIN(1,R49))*16,0))&REPT("░",16-ROUND(MAX(0,MIN(1,R49))*16,0)),"") | R49: =IFERROR(AVERAGEIFS('Habit Library'!$M$6:$M$40,'Habit Library'!$D$6:$D$40,"Spirit"),"")
B50: HEALTH | E50: =IF(ISNUMBER(I50),REPT("█",ROUND(MAX(0,MIN(1,I50))*16,0))&REPT("░",16-ROUND(MAX(0,MIN(1,I50))*16,0)),"") | I50: =IFERROR(AVERAGEIFS('Habit Library'!$M$6:$M$40,'Habit Library'!$D$6:$D$40,"Health"),"") | K50: WORK | N50: =IF(ISNUMBER(R50),REPT("█",ROUND(MAX(0,MIN(1,R50))*16,0))&REPT("░",16-ROUND(MAX(0,MIN(1,R50))*16,0)),"") | R50: =IFERROR(AVERAGEIFS('Habit Library'!$M$6:$M$40,'Habit Library'!$D$6:$D$40,"Work"),"")
B51: POSTURE | E51: =IF(ISNUMBER(I51),REPT("█",ROUND(MAX(0,MIN(1,I51))*16,0))&REPT("░",16-ROUND(MAX(0,MIN(1,I51))*16,0)),"") | I51: =IFERROR(AVERAGEIFS('Habit Library'!$M$6:$M$40,'Habit Library'!$D$6:$D$40,"Posture"),"") | K51: RELATIONSHIPS | N51: =IF(ISNUMBER(R51),REPT("█",ROUND(MAX(0,MIN(1,R51))*16,0))&REPT("░",16-ROUND(MAX(0,MIN(1,R51))*16,0)),"") | R51: =IFERROR(AVERAGEIFS('Habit Library'!$M$6:$M$40,'Habit Library'!$D$6:$D$40,"Relationships"),"")
B52: MIND | E52: =IF(ISNUMBER(I52),REPT("█",ROUND(MAX(0,MIN(1,I52))*16,0))&REPT("░",16-ROUND(MAX(0,MIN(1,I52))*16,0)),"") | I52: =IFERROR(AVERAGEIFS('Habit Library'!$M$6:$M$40,'Habit Library'!$D$6:$D$40,"Mind"),"") | K52: LIFE ADMIN | N52: =IF(ISNUMBER(R52),REPT("█",ROUND(MAX(0,MIN(1,R52))*16,0))&REPT("░",16-ROUND(MAX(0,MIN(1,R52))*16,0)),"") | R52: =IFERROR(AVERAGEIFS('Habit Library'!$M$6:$M$40,'Habit Library'!$D$6:$D$40,"Life admin"),"")
B54: FOUNDATION SCORE · last 30 days | K54: WEIGHT · daily vs 7-day average · 60 days
B71: STEPS vs adaptive target · 14 days | K71: SLEEP · ENERGY · STRESS · MOOD · 14 days

Sheet Week Plan
B2: WEEK PLAN | N2: WEEK STARTING | Q2: =TODAY()-WEEKDAY(TODAY(),3)
B3: Plan the week · tick tasks here · check-ins and scores pull from your daily log | N3: type a Monday to plan ahead
B5: DAILY FOUNDATION SCORE | K5: WEEK | N5: CHECK-IN TREND
K14: =IF(ISNUMBER(D64),TEXT(D64,"0%"),"—")
B17: =UPPER(TEXT((WeekStart+0),"dddd")) | E17: =UPPER(TEXT((WeekStart+1),"dddd")) | H17: =UPPER(TEXT((WeekStart+2),"dddd")) | K17: =UPPER(TEXT((WeekStart+3),"dddd")) | N17: =UPPER(TEXT((WeekStart+4),"dddd")) | Q17: =UPPER(TEXT((WeekStart+5),"dddd")) | T17: =UPPER(TEXT((WeekStart+6),"dddd"))
B18: =(WeekStart+0) | E18: =(WeekStart+1) | H18: =(WeekStart+2) | K18: =(WeekStart+3) | N18: =(WeekStart+4) | Q18: =(WeekStart+5) | T18: =(WeekStart+6)
B19: ="06:30 · "&INDEX(PlanTraining,1) | E19: ="06:30 · "&INDEX(PlanTraining,2) | H19: ="06:30 · "&INDEX(PlanTraining,3) | K19: ="06:30 · "&INDEX(PlanTraining,4) | N19: ="06:30 · "&INDEX(PlanTraining,5) | Q19: ="06:30 · "&INDEX(PlanTraining,6) | T19: ="06:30 · "&INDEX(PlanTraining,7)
B28: =IF(ISNUMBER(D57),TEXT(D57,"0%"),"—") | E28: =IF(ISNUMBER(D58),TEXT(D58,"0%"),"—") | H28: =IF(ISNUMBER(D59),TEXT(D59,"0%"),"—") | K28: =IF(ISNUMBER(D60),TEXT(D60,"0%"),"—") | N28: =IF(ISNUMBER(D61),TEXT(D61,"0%"),"—") | Q28: =IF(ISNUMBER(D62),TEXT(D62,"0%"),"—") | T28: =IF(ISNUMBER(D63),TEXT(D63,"0%"),"—")
B29: foundation score | E29: foundation score | H29: foundation score | K29: foundation score | N29: foundation score | Q29: foundation score | T29: foundation score
B30: TOP 3 PRIORITIES | E30: TOP 3 PRIORITIES | H30: TOP 3 PRIORITIES | K30: TOP 3 PRIORITIES | N30: TOP 3 PRIORITIES | Q30: TOP 3 PRIORITIES | T30: TOP 3 PRIORITIES
B34: TASKS | E34: TASKS | H34: TASKS | K34: TASKS | N34: TASKS | Q34: TASKS | T34: TASKS
B43: Completed | C43: =COUNTIF(C31:C42,TRUE)+COUNTIF(C31:C42,"x") | E43: Completed | F43: =COUNTIF(F31:F42,TRUE)+COUNTIF(F31:F42,"x") | H43: Completed | I43: =COUNTIF(I31:I42,TRUE)+COUNTIF(I31:I42,"x") | K43: Completed | L43: =COUNTIF(L31:L42,TRUE)+COUNTIF(L31:L42,"x") | N43: Completed | O43: =COUNTIF(O31:O42,TRUE)+COUNTIF(O31:O42,"x") | Q43: Completed | R43: =COUNTIF(R31:R42,TRUE)+COUNTIF(R31:R42,"x") | T43: Completed | U43: =COUNTIF(U31:U42,TRUE)+COUNTIF(U31:U42,"x")
B44: Not completed | C44: =MAX(0,COUNTA(B31:B33,B35:B42)-(COUNTIF(C31:C42,TRUE)+COUNTIF(C31:C42,"x"))) | E44: Not completed | F44: =MAX(0,COUNTA(E31:E33,E35:E42)-(COUNTIF(F31:F42,TRUE)+COUNTIF(F31:F42,"x"))) | H44: Not completed | I44: =MAX(0,COUNTA(H31:H33,H35:H42)-(COUNTIF(I31:I42,TRUE)+COUNTIF(I31:I42,"x"))) | K44: Not completed | L44: =MAX(0,COUNTA(K31:K33,K35:K42)-(COUNTIF(L31:L42,TRUE)+COUNTIF(L31:L42,"x"))) | N44: Not completed | O44: =MAX(0,COUNTA(N31:N33,N35:N42)-(COUNTIF(O31:O42,TRUE)+COUNTIF(O31:O42,"x"))) | Q44: Not completed | R44: =MAX(0,COUNTA(Q31:Q33,Q35:Q42)-(COUNTIF(R31:R42,TRUE)+COUNTIF(R31:R42,"x"))) | T44: Not completed | U44: =MAX(0,COUNTA(T31:T33,T35:T42)-(COUNTIF(U31:U42,TRUE)+COUNTIF(U31:U42,"x")))
B45: CHECK-IN · from daily log | E45: CHECK-IN · from daily log | H45: CHECK-IN · from daily log | K45: CHECK-IN · from daily log | N45: CHECK-IN · from daily log | Q45: CHECK-IN · from daily log | T45: CHECK-IN · from daily log
B46: ="Sleep "&IF(ISNUMBER(IFERROR(INDEX(Data!$AK$4:$AK$375,MATCH((WeekStart+0),Data!$A$4:$A$375,0)),"")),IF(ISNUMBER((IFERROR(INDEX(Data!$AK$4:$AK$375,MATCH((WeekStart+0),Data!$A$4:$A$375,0)),""))/9),REPT("█",ROUND(MAX(0,MIN(1,(IFERROR(INDEX(Data!$AK$4:$AK$375,MATCH((WeekStart+0),Data!$A$4:$A$375,0)),""))/9))*6,0))&REPT("░",6-ROUND(MAX(0,MIN(1,(IFERROR(INDEX(Data!$AK$4:$AK$375,MATCH((WeekStart+0),Data!$A$4:$A$375,0)),""))/9))*6,0)),""),"") | C46: =IF(ISNUMBER(IFERROR(INDEX(Data!$AK$4:$AK$375,MATCH((WeekStart+0),Data!$A$4:$A$375,0)),"")),IFERROR(INDEX(Data!$AK$4:$AK$375,MATCH((WeekStart+0),Data!$A$4:$A$375,0)),""),"") | E46: ="Sleep "&IF(ISNUMBER(IFERROR(INDEX(Data!$AK$4:$AK$375,MATCH((WeekStart+1),Data!$A$4:$A$375,0)),"")),IF(ISNUMBER((IFERROR(INDEX(Data!$AK$4:$AK$375,MATCH((WeekStart+1),Data!$A$4:$A$375,0)),""))/9),REPT("█",ROUND(MAX(0,MIN(1,(IFERROR(INDEX(Data!$AK$4:$AK$375,MATCH((WeekStart+1),Data!$A$4:$A$375,0)),""))/9))*6,0))&REPT("░",6-ROUND(MAX(0,MIN(1,(IFERROR(INDEX(Data!$AK$4:$AK$375,MATCH((WeekStart+1),Data!$A$4:$A$375,0)),""))/9))*6,0)),""),"") | F46: =IF(ISNUMBER(IFERROR(INDEX(Data!$AK$4:$AK$375,MATCH((WeekStart+1),Data!$A$4:$A$375,0)),"")),IFERROR(INDEX(Data!$AK$4:$AK$375,MATCH((WeekStart+1),Data!$A$4:$A$375,0)),""),"") | H46: ="Sleep "&IF(ISNUMBER(IFERROR(INDEX(Data!$AK$4:$AK$375,MATCH((WeekStart+2),Data!$A$4:$A$375,0)),"")),IF(ISNUMBER((IFERROR(INDEX(Data!$AK$4:$AK$375,MATCH((WeekStart+2),Data!$A$4:$A$375,0)),""))/9),REPT("█",ROUND(MAX(0,MIN(1,(IFERROR(INDEX(Data!$AK$4:$AK$375,MATCH((WeekStart+2),Data!$A$4:$A$375,0)),""))/9))*6,0))&REPT("░",6-ROUND(MAX(0,MIN(1,(IFERROR(INDEX(Data!$AK$4:$AK$375,MATCH((WeekStart+2),Data!$A$4:$A$375,0)),""))/9))*6,0)),""),"") | I46: =IF(ISNUMBER(IFERROR(INDEX(Data!$AK$4:$AK$375,MATCH((WeekStart+2),Data!$A$4:$A$375,0)),"")),IFERROR(INDEX(Data!$AK$4:$AK$375,MATCH((WeekStart+2),Data!$A$4:$A$375,0)),""),"") | K46: ="Sleep "&IF(ISNUMBER(IFERROR(INDEX(Data!$AK$4:$AK$375,MATCH((WeekStart+3),Data!$A$4:$A$375,0)),"")),IF(ISNUMBER((IFERROR(INDEX(Data!$AK$4:$AK$375,MATCH((WeekStart+3),Data!$A$4:$A$375,0)),""))/9),REPT("█",ROUND(MAX(0,MIN(1,(IFERROR(INDEX(Data!$AK$4:$AK$375,MATCH((WeekStart+3),Data!$A$4:$A$375,0)),""))/9))*6,0))&REPT("░",6-ROUND(MAX(0,MIN(1,(IFERROR(INDEX(Data!$AK$4:$AK$375,MATCH((WeekStart+3),Data!$A$4:$A$375,0)),""))/9))*6,0)),""),"") | L46: =IF(ISNUMBER(IFERROR(INDEX(Data!$AK$4:$AK$375,MATCH((WeekStart+3),Data!$A$4:$A$375,0)),"")),IFERROR(INDEX(Data!$AK$4:$AK$375,MATCH((WeekStart+3),Data!$A$4:$A$375,0)),""),"") | N46: ="Sleep "&IF(ISNUMBER(IFERROR(INDEX(Data!$AK$4:$AK$375,MATCH((WeekStart+4),Data!$A$4:$A$375,0)),"")),IF(ISNUMBER((IFERROR(INDEX(Data!$AK$4:$AK$375,MATCH((WeekStart+4),Data!$A$4:$A$375,0)),""))/9),REPT("█",ROUND(MAX(0,MIN(1,(IFERROR(INDEX(Data!$AK$4:$AK$375,MATCH((WeekStart+4),Data!$A$4:$A$375,0)),""))/9))*6,0))&REPT("░",6-ROUND(MAX(0,MIN(1,(IFERROR(INDEX(Data!$AK$4:$AK$375,MATCH((WeekStart+4),Data!$A$4:$A$375,0)),""))/9))*6,0)),""),"") | O46: =IF(ISNUMBER(IFERROR(INDEX(Data!$AK$4:$AK$375,MATCH((WeekStart+4),Data!$A$4:$A$375,0)),"")),IFERROR(INDEX(Data!$AK$4:$AK$375,MATCH((WeekStart+4),Data!$A$4:$A$375,0)),""),"") | Q46: ="Sleep "&IF(ISNUMBER(IFERROR(INDEX(Data!$AK$4:$AK$375,MATCH((WeekStart+5),Data!$A$4:$A$375,0)),"")),IF(ISNUMBER((IFERROR(INDEX(Data!$AK$4:$AK$375,MATCH((WeekStart+5),Data!$A$4:$A$375,0)),""))/9),REPT("█",ROUND(MAX(0,MIN(1,(IFERROR(INDEX(Data!$AK$4:$AK$375,MATCH((WeekStart+5),Data!$A$4:$A$375,0)),""))/9))*6,0))&REPT("░",6-ROUND(MAX(0,MIN(1,(IFERROR(INDEX(Data!$AK$4:$AK$375,MATCH((WeekStart+5),Data!$A$4:$A$375,0)),""))/9))*6,0)),""),"") | R46: =IF(ISNUMBER(IFERROR(INDEX(Data!$AK$4:$AK$375,MATCH((WeekStart+5),Data!$A$4:$A$375,0)),"")),IFERROR(INDEX(Data!$AK$4:$AK$375,MATCH((WeekStart+5),Data!$A$4:$A$375,0)),""),"") | T46: ="Sleep "&IF(ISNUMBER(IFERROR(INDEX(Data!$AK$4:$AK$375,MATCH((WeekStart+6),Data!$A$4:$A$375,0)),"")),IF(ISNUMBER((IFERROR(INDEX(Data!$AK$4:$AK$375,MATCH((WeekStart+6),Data!$A$4:$A$375,0)),""))/9),REPT("█",ROUND(MAX(0,MIN(1,(IFERROR(INDEX(Data!$AK$4:$AK$375,MATCH((WeekStart+6),Data!$A$4:$A$375,0)),""))/9))*6,0))&REPT("░",6-ROUND(MAX(0,MIN(1,(IFERROR(INDEX(Data!$AK$4:$AK$375,MATCH((WeekStart+6),Data!$A$4:$A$375,0)),""))/9))*6,0)),""),"") | U46: =IF(ISNUMBER(IFERROR(INDEX(Data!$AK$4:$AK$375,MATCH((WeekStart+6),Data!$A$4:$A$375,0)),"")),IFERROR(INDEX(Data!$AK$4:$AK$375,MATCH((WeekStart+6),Data!$A$4:$A$375,0)),""),"")
B47: ="Energy "&IF(ISNUMBER(IFERROR(INDEX(Data!$AL$4:$AL$375,MATCH((WeekStart+0),Data!$A$4:$A$375,0)),"")),IF(ISNUMBER((IFERROR(INDEX(Data!$AL$4:$AL$375,MATCH((WeekStart+0),Data!$A$4:$A$375,0)),""))/10),REPT("█",ROUND(MAX(0,MIN(1,(IFERROR(INDEX(Data!$AL$4:$AL$375,MATCH((WeekStart+0),Data!$A$4:$A$375,0)),""))/10))*6,0))&REPT("░",6-ROUND(MAX(0,MIN(1,(IFERROR(INDEX(Data!$AL$4:$AL$375,MATCH((WeekStart+0),Data!$A$4:$A$375,0)),""))/10))*6,0)),""),"") | C47: =IF(ISNUMBER(IFERROR(INDEX(Data!$AL$4:$AL$375,MATCH((WeekStart+0),Data!$A$4:$A$375,0)),"")),IFERROR(INDEX(Data!$AL$4:$AL$375,MATCH((WeekStart+0),Data!$A$4:$A$375,0)),""),"") | E47: ="Energy "&IF(ISNUMBER(IFERROR(INDEX(Data!$AL$4:$AL$375,MATCH((WeekStart+1),Data!$A$4:$A$375,0)),"")),IF(ISNUMBER((IFERROR(INDEX(Data!$AL$4:$AL$375,MATCH((WeekStart+1),Data!$A$4:$A$375,0)),""))/10),REPT("█",ROUND(MAX(0,MIN(1,(IFERROR(INDEX(Data!$AL$4:$AL$375,MATCH((WeekStart+1),Data!$A$4:$A$375,0)),""))/10))*6,0))&REPT("░",6-ROUND(MAX(0,MIN(1,(IFERROR(INDEX(Data!$AL$4:$AL$375,MATCH((WeekStart+1),Data!$A$4:$A$375,0)),""))/10))*6,0)),""),"") | F47: =IF(ISNUMBER(IFERROR(INDEX(Data!$AL$4:$AL$375,MATCH((WeekStart+1),Data!$A$4:$A$375,0)),"")),IFERROR(INDEX(Data!$AL$4:$AL$375,MATCH((WeekStart+1),Data!$A$4:$A$375,0)),""),"") | H47: ="Energy "&IF(ISNUMBER(IFERROR(INDEX(Data!$AL$4:$AL$375,MATCH((WeekStart+2),Data!$A$4:$A$375,0)),"")),IF(ISNUMBER((IFERROR(INDEX(Data!$AL$4:$AL$375,MATCH((WeekStart+2),Data!$A$4:$A$375,0)),""))/10),REPT("█",ROUND(MAX(0,MIN(1,(IFERROR(INDEX(Data!$AL$4:$AL$375,MATCH((WeekStart+2),Data!$A$4:$A$375,0)),""))/10))*6,0))&REPT("░",6-ROUND(MAX(0,MIN(1,(IFERROR(INDEX(Data!$AL$4:$AL$375,MATCH((WeekStart+2),Data!$A$4:$A$375,0)),""))/10))*6,0)),""),"") | I47: =IF(ISNUMBER(IFERROR(INDEX(Data!$AL$4:$AL$375,MATCH((WeekStart+2),Data!$A$4:$A$375,0)),"")),IFERROR(INDEX(Data!$AL$4:$AL$375,MATCH((WeekStart+2),Data!$A$4:$A$375,0)),""),"") | K47: ="Energy "&IF(ISNUMBER(IFERROR(INDEX(Data!$AL$4:$AL$375,MATCH((WeekStart+3),Data!$A$4:$A$375,0)),"")),IF(ISNUMBER((IFERROR(INDEX(Data!$AL$4:$AL$375,MATCH((WeekStart+3),Data!$A$4:$A$375,0)),""))/10),REPT("█",ROUND(MAX(0,MIN(1,(IFERROR(INDEX(Data!$AL$4:$AL$375,MATCH((WeekStart+3),Data!$A$4:$A$375,0)),""))/10))*6,0))&REPT("░",6-ROUND(MAX(0,MIN(1,(IFERROR(INDEX(Data!$AL$4:$AL$375,MATCH((WeekStart+3),Data!$A$4:$A$375,0)),""))/10))*6,0)),""),"") | L47: =IF(ISNUMBER(IFERROR(INDEX(Data!$AL$4:$AL$375,MATCH((WeekStart+3),Data!$A$4:$A$375,0)),"")),IFERROR(INDEX(Data!$AL$4:$AL$375,MATCH((WeekStart+3),Data!$A$4:$A$375,0)),""),"") | N47: ="Energy "&IF(ISNUMBER(IFERROR(INDEX(Data!$AL$4:$AL$375,MATCH((WeekStart+4),Data!$A$4:$A$375,0)),"")),IF(ISNUMBER((IFERROR(INDEX(Data!$AL$4:$AL$375,MATCH((WeekStart+4),Data!$A$4:$A$375,0)),""))/10),REPT("█",ROUND(MAX(0,MIN(1,(IFERROR(INDEX(Data!$AL$4:$AL$375,MATCH((WeekStart+4),Data!$A$4:$A$375,0)),""))/10))*6,0))&REPT("░",6-ROUND(MAX(0,MIN(1,(IFERROR(INDEX(Data!$AL$4:$AL$375,MATCH((WeekStart+4),Data!$A$4:$A$375,0)),""))/10))*6,0)),""),"") | O47: =IF(ISNUMBER(IFERROR(INDEX(Data!$AL$4:$AL$375,MATCH((WeekStart+4),Data!$A$4:$A$375,0)),"")),IFERROR(INDEX(Data!$AL$4:$AL$375,MATCH((WeekStart+4),Data!$A$4:$A$375,0)),""),"") | Q47: ="Energy "&IF(ISNUMBER(IFERROR(INDEX(Data!$AL$4:$AL$375,MATCH((WeekStart+5),Data!$A$4:$A$375,0)),"")),IF(ISNUMBER((IFERROR(INDEX(Data!$AL$4:$AL$375,MATCH((WeekStart+5),Data!$A$4:$A$375,0)),""))/10),REPT("█",ROUND(MAX(0,MIN(1,(IFERROR(INDEX(Data!$AL$4:$AL$375,MATCH((WeekStart+5),Data!$A$4:$A$375,0)),""))/10))*6,0))&REPT("░",6-ROUND(MAX(0,MIN(1,(IFERROR(INDEX(Data!$AL$4:$AL$375,MATCH((WeekStart+5),Data!$A$4:$A$375,0)),""))/10))*6,0)),""),"") | R47: =IF(ISNUMBER(IFERROR(INDEX(Data!$AL$4:$AL$375,MATCH((WeekStart+5),Data!$A$4:$A$375,0)),"")),IFERROR(INDEX(Data!$AL$4:$AL$375,MATCH((WeekStart+5),Data!$A$4:$A$375,0)),""),"") | T47: ="Energy "&IF(ISNUMBER(IFERROR(INDEX(Data!$AL$4:$AL$375,MATCH((WeekStart+6),Data!$A$4:$A$375,0)),"")),IF(ISNUMBER((IFERROR(INDEX(Data!$AL$4:$AL$375,MATCH((WeekStart+6),Data!$A$4:$A$375,0)),""))/10),REPT("█",ROUND(MAX(0,MIN(1,(IFERROR(INDEX(Data!$AL$4:$AL$375,MATCH((WeekStart+6),Data!$A$4:$A$375,0)),""))/10))*6,0))&REPT("░",6-ROUND(MAX(0,MIN(1,(IFERROR(INDEX(Data!$AL$4:$AL$375,MATCH((WeekStart+6),Data!$A$4:$A$375,0)),""))/10))*6,0)),""),"") | U47: =IF(ISNUMBER(IFERROR(INDEX(Data!$AL$4:$AL$375,MATCH((WeekStart+6),Data!$A$4:$A$375,0)),"")),IFERROR(INDEX(Data!$AL$4:$AL$375,MATCH((WeekStart+6),Data!$A$4:$A$375,0)),""),"")
B48: ="Stress "&IF(ISNUMBER(IFERROR(INDEX(Data!$AM$4:$AM$375,MATCH((WeekStart+0),Data!$A$4:$A$375,0)),"")),IF(ISNUMBER((IFERROR(INDEX(Data!$AM$4:$AM$375,MATCH((WeekStart+0),Data!$A$4:$A$375,0)),""))/10),REPT("█",ROUND(MAX(0,MIN(1,(IFERROR(INDEX(Data!$AM$4:$AM$375,MATCH((WeekStart+0),Data!$A$4:$A$375,0)),""))/10))*6,0))&REPT("░",6-ROUND(MAX(0,MIN(1,(IFERROR(INDEX(Data!$AM$4:$AM$375,MATCH((WeekStart+0),Data!$A$4:$A$375,0)),""))/10))*6,0)),""),"") | C48: =IF(ISNUMBER(IFERROR(INDEX(Data!$AM$4:$AM$375,MATCH((WeekStart+0),Data!$A$4:$A$375,0)),"")),IFERROR(INDEX(Data!$AM$4:$AM$375,MATCH((WeekStart+0),Data!$A$4:$A$375,0)),""),"") | E48: ="Stress "&IF(ISNUMBER(IFERROR(INDEX(Data!$AM$4:$AM$375,MATCH((WeekStart+1),Data!$A$4:$A$375,0)),"")),IF(ISNUMBER((IFERROR(INDEX(Data!$AM$4:$AM$375,MATCH((WeekStart+1),Data!$A$4:$A$375,0)),""))/10),REPT("█",ROUND(MAX(0,MIN(1,(IFERROR(INDEX(Data!$AM$4:$AM$375,MATCH((WeekStart+1),Data!$A$4:$A$375,0)),""))/10))*6,0))&REPT("░",6-ROUND(MAX(0,MIN(1,(IFERROR(INDEX(Data!$AM$4:$AM$375,MATCH((WeekStart+1),Data!$A$4:$A$375,0)),""))/10))*6,0)),""),"") | F48: =IF(ISNUMBER(IFERROR(INDEX(Data!$AM$4:$AM$375,MATCH((WeekStart+1),Data!$A$4:$A$375,0)),"")),IFERROR(INDEX(Data!$AM$4:$AM$375,MATCH((WeekStart+1),Data!$A$4:$A$375,0)),""),"") | H48: ="Stress "&IF(ISNUMBER(IFERROR(INDEX(Data!$AM$4:$AM$375,MATCH((WeekStart+2),Data!$A$4:$A$375,0)),"")),IF(ISNUMBER((IFERROR(INDEX(Data!$AM$4:$AM$375,MATCH((WeekStart+2),Data!$A$4:$A$375,0)),""))/10),REPT("█",ROUND(MAX(0,MIN(1,(IFERROR(INDEX(Data!$AM$4:$AM$375,MATCH((WeekStart+2),Data!$A$4:$A$375,0)),""))/10))*6,0))&REPT("░",6-ROUND(MAX(0,MIN(1,(IFERROR(INDEX(Data!$AM$4:$AM$375,MATCH((WeekStart+2),Data!$A$4:$A$375,0)),""))/10))*6,0)),""),"") | I48: =IF(ISNUMBER(IFERROR(INDEX(Data!$AM$4:$AM$375,MATCH((WeekStart+2),Data!$A$4:$A$375,0)),"")),IFERROR(INDEX(Data!$AM$4:$AM$375,MATCH((WeekStart+2),Data!$A$4:$A$375,0)),""),"") | K48: ="Stress "&IF(ISNUMBER(IFERROR(INDEX(Data!$AM$4:$AM$375,MATCH((WeekStart+3),Data!$A$4:$A$375,0)),"")),IF(ISNUMBER((IFERROR(INDEX(Data!$AM$4:$AM$375,MATCH((WeekStart+3),Data!$A$4:$A$375,0)),""))/10),REPT("█",ROUND(MAX(0,MIN(1,(IFERROR(INDEX(Data!$AM$4:$AM$375,MATCH((WeekStart+3),Data!$A$4:$A$375,0)),""))/10))*6,0))&REPT("░",6-ROUND(MAX(0,MIN(1,(IFERROR(INDEX(Data!$AM$4:$AM$375,MATCH((WeekStart+3),Data!$A$4:$A$375,0)),""))/10))*6,0)),""),"") | L48: =IF(ISNUMBER(IFERROR(INDEX(Data!$AM$4:$AM$375,MATCH((WeekStart+3),Data!$A$4:$A$375,0)),"")),IFERROR(INDEX(Data!$AM$4:$AM$375,MATCH((WeekStart+3),Data!$A$4:$A$375,0)),""),"") | N48: ="Stress "&IF(ISNUMBER(IFERROR(INDEX(Data!$AM$4:$AM$375,MATCH((WeekStart+4),Data!$A$4:$A$375,0)),"")),IF(ISNUMBER((IFERROR(INDEX(Data!$AM$4:$AM$375,MATCH((WeekStart+4),Data!$A$4:$A$375,0)),""))/10),REPT("█",ROUND(MAX(0,MIN(1,(IFERROR(INDEX(Data!$AM$4:$AM$375,MATCH((WeekStart+4),Data!$A$4:$A$375,0)),""))/10))*6,0))&REPT("░",6-ROUND(MAX(0,MIN(1,(IFERROR(INDEX(Data!$AM$4:$AM$375,MATCH((WeekStart+4),Data!$A$4:$A$375,0)),""))/10))*6,0)),""),"") | O48: =IF(ISNUMBER(IFERROR(INDEX(Data!$AM$4:$AM$375,MATCH((WeekStart+4),Data!$A$4:$A$375,0)),"")),IFERROR(INDEX(Data!$AM$4:$AM$375,MATCH((WeekStart+4),Data!$A$4:$A$375,0)),""),"") | Q48: ="Stress "&IF(ISNUMBER(IFERROR(INDEX(Data!$AM$4:$AM$375,MATCH((WeekStart+5),Data!$A$4:$A$375,0)),"")),IF(ISNUMBER((IFERROR(INDEX(Data!$AM$4:$AM$375,MATCH((WeekStart+5),Data!$A$4:$A$375,0)),""))/10),REPT("█",ROUND(MAX(0,MIN(1,(IFERROR(INDEX(Data!$AM$4:$AM$375,MATCH((WeekStart+5),Data!$A$4:$A$375,0)),""))/10))*6,0))&REPT("░",6-ROUND(MAX(0,MIN(1,(IFERROR(INDEX(Data!$AM$4:$AM$375,MATCH((WeekStart+5),Data!$A$4:$A$375,0)),""))/10))*6,0)),""),"") | R48: =IF(ISNUMBER(IFERROR(INDEX(Data!$AM$4:$AM$375,MATCH((WeekStart+5),Data!$A$4:$A$375,0)),"")),IFERROR(INDEX(Data!$AM$4:$AM$375,MATCH((WeekStart+5),Data!$A$4:$A$375,0)),""),"") | T48: ="Stress "&IF(ISNUMBER(IFERROR(INDEX(Data!$AM$4:$AM$375,MATCH((WeekStart+6),Data!$A$4:$A$375,0)),"")),IF(ISNUMBER((IFERROR(INDEX(Data!$AM$4:$AM$375,MATCH((WeekStart+6),Data!$A$4:$A$375,0)),""))/10),REPT("█",ROUND(MAX(0,MIN(1,(IFERROR(INDEX(Data!$AM$4:$AM$375,MATCH((WeekStart+6),Data!$A$4:$A$375,0)),""))/10))*6,0))&REPT("░",6-ROUND(MAX(0,MIN(1,(IFERROR(INDEX(Data!$AM$4:$AM$375,MATCH((WeekStart+6),Data!$A$4:$A$375,0)),""))/10))*6,0)),""),"") | U48: =IF(ISNUMBER(IFERROR(INDEX(Data!$AM$4:$AM$375,MATCH((WeekStart+6),Data!$A$4:$A$375,0)),"")),IFERROR(INDEX(Data!$AM$4:$AM$375,MATCH((WeekStart+6),Data!$A$4:$A$375,0)),""),"")
B49: ="Mood "&IF(ISNUMBER(IFERROR(INDEX(Data!$AN$4:$AN$375,MATCH((WeekStart+0),Data!$A$4:$A$375,0)),"")),IF(ISNUMBER((IFERROR(INDEX(Data!$AN$4:$AN$375,MATCH((WeekStart+0),Data!$A$4:$A$375,0)),""))/10),REPT("█",ROUND(MAX(0,MIN(1,(IFERROR(INDEX(Data!$AN$4:$AN$375,MATCH((WeekStart+0),Data!$A$4:$A$375,0)),""))/10))*6,0))&REPT("░",6-ROUND(MAX(0,MIN(1,(IFERROR(INDEX(Data!$AN$4:$AN$375,MATCH((WeekStart+0),Data!$A$4:$A$375,0)),""))/10))*6,0)),""),"") | C49: =IF(ISNUMBER(IFERROR(INDEX(Data!$AN$4:$AN$375,MATCH((WeekStart+0),Data!$A$4:$A$375,0)),"")),IFERROR(INDEX(Data!$AN$4:$AN$375,MATCH((WeekStart+0),Data!$A$4:$A$375,0)),""),"") | E49: ="Mood "&IF(ISNUMBER(IFERROR(INDEX(Data!$AN$4:$AN$375,MATCH((WeekStart+1),Data!$A$4:$A$375,0)),"")),IF(ISNUMBER((IFERROR(INDEX(Data!$AN$4:$AN$375,MATCH((WeekStart+1),Data!$A$4:$A$375,0)),""))/10),REPT("█",ROUND(MAX(0,MIN(1,(IFERROR(INDEX(Data!$AN$4:$AN$375,MATCH((WeekStart+1),Data!$A$4:$A$375,0)),""))/10))*6,0))&REPT("░",6-ROUND(MAX(0,MIN(1,(IFERROR(INDEX(Data!$AN$4:$AN$375,MATCH((WeekStart+1),Data!$A$4:$A$375,0)),""))/10))*6,0)),""),"") | F49: =IF(ISNUMBER(IFERROR(INDEX(Data!$AN$4:$AN$375,MATCH((WeekStart+1),Data!$A$4:$A$375,0)),"")),IFERROR(INDEX(Data!$AN$4:$AN$375,MATCH((WeekStart+1),Data!$A$4:$A$375,0)),""),"") | H49: ="Mood "&IF(ISNUMBER(IFERROR(INDEX(Data!$AN$4:$AN$375,MATCH((WeekStart+2),Data!$A$4:$A$375,0)),"")),IF(ISNUMBER((IFERROR(INDEX(Data!$AN$4:$AN$375,MATCH((WeekStart+2),Data!$A$4:$A$375,0)),""))/10),REPT("█",ROUND(MAX(0,MIN(1,(IFERROR(INDEX(Data!$AN$4:$AN$375,MATCH((WeekStart+2),Data!$A$4:$A$375,0)),""))/10))*6,0))&REPT("░",6-ROUND(MAX(0,MIN(1,(IFERROR(INDEX(Data!$AN$4:$AN$375,MATCH((WeekStart+2),Data!$A$4:$A$375,0)),""))/10))*6,0)),""),"") | I49: =IF(ISNUMBER(IFERROR(INDEX(Data!$AN$4:$AN$375,MATCH((WeekStart+2),Data!$A$4:$A$375,0)),"")),IFERROR(INDEX(Data!$AN$4:$AN$375,MATCH((WeekStart+2),Data!$A$4:$A$375,0)),""),"") | K49: ="Mood "&IF(ISNUMBER(IFERROR(INDEX(Data!$AN$4:$AN$375,MATCH((WeekStart+3),Data!$A$4:$A$375,0)),"")),IF(ISNUMBER((IFERROR(INDEX(Data!$AN$4:$AN$375,MATCH((WeekStart+3),Data!$A$4:$A$375,0)),""))/10),REPT("█",ROUND(MAX(0,MIN(1,(IFERROR(INDEX(Data!$AN$4:$AN$375,MATCH((WeekStart+3),Data!$A$4:$A$375,0)),""))/10))*6,0))&REPT("░",6-ROUND(MAX(0,MIN(1,(IFERROR(INDEX(Data!$AN$4:$AN$375,MATCH((WeekStart+3),Data!$A$4:$A$375,0)),""))/10))*6,0)),""),"") | L49: =IF(ISNUMBER(IFERROR(INDEX(Data!$AN$4:$AN$375,MATCH((WeekStart+3),Data!$A$4:$A$375,0)),"")),IFERROR(INDEX(Data!$AN$4:$AN$375,MATCH((WeekStart+3),Data!$A$4:$A$375,0)),""),"") | N49: ="Mood "&IF(ISNUMBER(IFERROR(INDEX(Data!$AN$4:$AN$375,MATCH((WeekStart+4),Data!$A$4:$A$375,0)),"")),IF(ISNUMBER((IFERROR(INDEX(Data!$AN$4:$AN$375,MATCH((WeekStart+4),Data!$A$4:$A$375,0)),""))/10),REPT("█",ROUND(MAX(0,MIN(1,(IFERROR(INDEX(Data!$AN$4:$AN$375,MATCH((WeekStart+4),Data!$A$4:$A$375,0)),""))/10))*6,0))&REPT("░",6-ROUND(MAX(0,MIN(1,(IFERROR(INDEX(Data!$AN$4:$AN$375,MATCH((WeekStart+4),Data!$A$4:$A$375,0)),""))/10))*6,0)),""),"") | O49: =IF(ISNUMBER(IFERROR(INDEX(Data!$AN$4:$AN$375,MATCH((WeekStart+4),Data!$A$4:$A$375,0)),"")),IFERROR(INDEX(Data!$AN$4:$AN$375,MATCH((WeekStart+4),Data!$A$4:$A$375,0)),""),"") | Q49: ="Mood "&IF(ISNUMBER(IFERROR(INDEX(Data!$AN$4:$AN$375,MATCH((WeekStart+5),Data!$A$4:$A$375,0)),"")),IF(ISNUMBER((IFERROR(INDEX(Data!$AN$4:$AN$375,MATCH((WeekStart+5),Data!$A$4:$A$375,0)),""))/10),REPT("█",ROUND(MAX(0,MIN(1,(IFERROR(INDEX(Data!$AN$4:$AN$375,MATCH((WeekStart+5),Data!$A$4:$A$375,0)),""))/10))*6,0))&REPT("░",6-ROUND(MAX(0,MIN(1,(IFERROR(INDEX(Data!$AN$4:$AN$375,MATCH((WeekStart+5),Data!$A$4:$A$375,0)),""))/10))*6,0)),""),"") | R49: =IF(ISNUMBER(IFERROR(INDEX(Data!$AN$4:$AN$375,MATCH((WeekStart+5),Data!$A$4:$A$375,0)),"")),IFERROR(INDEX(Data!$AN$4:$AN$375,MATCH((WeekStart+5),Data!$A$4:$A$375,0)),""),"") | T49: ="Mood "&IF(ISNUMBER(IFERROR(INDEX(Data!$AN$4:$AN$375,MATCH((WeekStart+6),Data!$A$4:$A$375,0)),"")),IF(ISNUMBER((IFERROR(INDEX(Data!$AN$4:$AN$375,MATCH((WeekStart+6),Data!$A$4:$A$375,0)),""))/10),REPT("█",ROUND(MAX(0,MIN(1,(IFERROR(INDEX(Data!$AN$4:$AN$375,MATCH((WeekStart+6),Data!$A$4:$A$375,0)),""))/10))*6,0))&REPT("░",6-ROUND(MAX(0,MIN(1,(IFERROR(INDEX(Data!$AN$4:$AN$375,MATCH((WeekStart+6),Data!$A$4:$A$375,0)),""))/10))*6,0)),""),"") | U49: =IF(ISNUMBER(IFERROR(INDEX(Data!$AN$4:$AN$375,MATCH((WeekStart+6),Data!$A$4:$A$375,0)),"")),IFERROR(INDEX(Data!$AN$4:$AN$375,MATCH((WeekStart+6),Data!$A$4:$A$375,0)),""),"")
B50: ="Protein "&IF(ISNUMBER(IFERROR(INDEX(Data!$AH$4:$AH$375,MATCH((WeekStart+0),Data!$A$4:$A$375,0)),"")),IF(ISNUMBER((IFERROR(INDEX(Data!$AH$4:$AH$375,MATCH((WeekStart+0),Data!$A$4:$A$375,0)),""))/150),REPT("█",ROUND(MAX(0,MIN(1,(IFERROR(INDEX(Data!$AH$4:$AH$375,MATCH((WeekStart+0),Data!$A$4:$A$375,0)),""))/150))*6,0))&REPT("░",6-ROUND(MAX(0,MIN(1,(IFERROR(INDEX(Data!$AH$4:$AH$375,MATCH((WeekStart+0),Data!$A$4:$A$375,0)),""))/150))*6,0)),""),"") | C50: =IF(ISNUMBER(IFERROR(INDEX(Data!$AH$4:$AH$375,MATCH((WeekStart+0),Data!$A$4:$A$375,0)),"")),IFERROR(INDEX(Data!$AH$4:$AH$375,MATCH((WeekStart+0),Data!$A$4:$A$375,0)),""),"") | E50: ="Protein "&IF(ISNUMBER(IFERROR(INDEX(Data!$AH$4:$AH$375,MATCH((WeekStart+1),Data!$A$4:$A$375,0)),"")),IF(ISNUMBER((IFERROR(INDEX(Data!$AH$4:$AH$375,MATCH((WeekStart+1),Data!$A$4:$A$375,0)),""))/150),REPT("█",ROUND(MAX(0,MIN(1,(IFERROR(INDEX(Data!$AH$4:$AH$375,MATCH((WeekStart+1),Data!$A$4:$A$375,0)),""))/150))*6,0))&REPT("░",6-ROUND(MAX(0,MIN(1,(IFERROR(INDEX(Data!$AH$4:$AH$375,MATCH((WeekStart+1),Data!$A$4:$A$375,0)),""))/150))*6,0)),""),"") | F50: =IF(ISNUMBER(IFERROR(INDEX(Data!$AH$4:$AH$375,MATCH((WeekStart+1),Data!$A$4:$A$375,0)),"")),IFERROR(INDEX(Data!$AH$4:$AH$375,MATCH((WeekStart+1),Data!$A$4:$A$375,0)),""),"") | H50: ="Protein "&IF(ISNUMBER(IFERROR(INDEX(Data!$AH$4:$AH$375,MATCH((WeekStart+2),Data!$A$4:$A$375,0)),"")),IF(ISNUMBER((IFERROR(INDEX(Data!$AH$4:$AH$375,MATCH((WeekStart+2),Data!$A$4:$A$375,0)),""))/150),REPT("█",ROUND(MAX(0,MIN(1,(IFERROR(INDEX(Data!$AH$4:$AH$375,MATCH((WeekStart+2),Data!$A$4:$A$375,0)),""))/150))*6,0))&REPT("░",6-ROUND(MAX(0,MIN(1,(IFERROR(INDEX(Data!$AH$4:$AH$375,MATCH((WeekStart+2),Data!$A$4:$A$375,0)),""))/150))*6,0)),""),"") | I50: =IF(ISNUMBER(IFERROR(INDEX(Data!$AH$4:$AH$375,MATCH((WeekStart+2),Data!$A$4:$A$375,0)),"")),IFERROR(INDEX(Data!$AH$4:$AH$375,MATCH((WeekStart+2),Data!$A$4:$A$375,0)),""),"") | K50: ="Protein "&IF(ISNUMBER(IFERROR(INDEX(Data!$AH$4:$AH$375,MATCH((WeekStart+3),Data!$A$4:$A$375,0)),"")),IF(ISNUMBER((IFERROR(INDEX(Data!$AH$4:$AH$375,MATCH((WeekStart+3),Data!$A$4:$A$375,0)),""))/150),REPT("█",ROUND(MAX(0,MIN(1,(IFERROR(INDEX(Data!$AH$4:$AH$375,MATCH((WeekStart+3),Data!$A$4:$A$375,0)),""))/150))*6,0))&REPT("░",6-ROUND(MAX(0,MIN(1,(IFERROR(INDEX(Data!$AH$4:$AH$375,MATCH((WeekStart+3),Data!$A$4:$A$375,0)),""))/150))*6,0)),""),"") | L50: =IF(ISNUMBER(IFERROR(INDEX(Data!$AH$4:$AH$375,MATCH((WeekStart+3),Data!$A$4:$A$375,0)),"")),IFERROR(INDEX(Data!$AH$4:$AH$375,MATCH((WeekStart+3),Data!$A$4:$A$375,0)),""),"") | N50: ="Protein "&IF(ISNUMBER(IFERROR(INDEX(Data!$AH$4:$AH$375,MATCH((WeekStart+4),Data!$A$4:$A$375,0)),"")),IF(ISNUMBER((IFERROR(INDEX(Data!$AH$4:$AH$375,MATCH((WeekStart+4),Data!$A$4:$A$375,0)),""))/150),REPT("█",ROUND(MAX(0,MIN(1,(IFERROR(INDEX(Data!$AH$4:$AH$375,MATCH((WeekStart+4),Data!$A$4:$A$375,0)),""))/150))*6,0))&REPT("░",6-ROUND(MAX(0,MIN(1,(IFERROR(INDEX(Data!$AH$4:$AH$375,MATCH((WeekStart+4),Data!$A$4:$A$375,0)),""))/150))*6,0)),""),"") | O50: =IF(ISNUMBER(IFERROR(INDEX(Data!$AH$4:$AH$375,MATCH((WeekStart+4),Data!$A$4:$A$375,0)),"")),IFERROR(INDEX(Data!$AH$4:$AH$375,MATCH((WeekStart+4),Data!$A$4:$A$375,0)),""),"") | Q50: ="Protein "&IF(ISNUMBER(IFERROR(INDEX(Data!$AH$4:$AH$375,MATCH((WeekStart+5),Data!$A$4:$A$375,0)),"")),IF(ISNUMBER((IFERROR(INDEX(Data!$AH$4:$AH$375,MATCH((WeekStart+5),Data!$A$4:$A$375,0)),""))/150),REPT("█",ROUND(MAX(0,MIN(1,(IFERROR(INDEX(Data!$AH$4:$AH$375,MATCH((WeekStart+5),Data!$A$4:$A$375,0)),""))/150))*6,0))&REPT("░",6-ROUND(MAX(0,MIN(1,(IFERROR(INDEX(Data!$AH$4:$AH$375,MATCH((WeekStart+5),Data!$A$4:$A$375,0)),""))/150))*6,0)),""),"") | R50: =IF(ISNUMBER(IFERROR(INDEX(Data!$AH$4:$AH$375,MATCH((WeekStart+5),Data!$A$4:$A$375,0)),"")),IFERROR(INDEX(Data!$AH$4:$AH$375,MATCH((WeekStart+5),Data!$A$4:$A$375,0)),""),"") | T50: ="Protein "&IF(ISNUMBER(IFERROR(INDEX(Data!$AH$4:$AH$375,MATCH((WeekStart+6),Data!$A$4:$A$375,0)),"")),IF(ISNUMBER((IFERROR(INDEX(Data!$AH$4:$AH$375,MATCH((WeekStart+6),Data!$A$4:$A$375,0)),""))/150),REPT("█",ROUND(MAX(0,MIN(1,(IFERROR(INDEX(Data!$AH$4:$AH$375,MATCH((WeekStart+6),Data!$A$4:$A$375,0)),""))/150))*6,0))&REPT("░",6-ROUND(MAX(0,MIN(1,(IFERROR(INDEX(Data!$AH$4:$AH$375,MATCH((WeekStart+6),Data!$A$4:$A$375,0)),""))/150))*6,0)),""),"") | U50: =IF(ISNUMBER(IFERROR(INDEX(Data!$AH$4:$AH$375,MATCH((WeekStart+6),Data!$A$4:$A$375,0)),"")),IFERROR(INDEX(Data!$AH$4:$AH$375,MATCH((WeekStart+6),Data!$A$4:$A$375,0)),""),"")
B51: ="Steps "&IF(ISNUMBER(IFERROR(INDEX(Data!$AG$4:$AG$375,MATCH((WeekStart+0),Data!$A$4:$A$375,0)),"")),IF(ISNUMBER((IFERROR(INDEX(Data!$AG$4:$AG$375,MATCH((WeekStart+0),Data!$A$4:$A$375,0)),""))/10000),REPT("█",ROUND(MAX(0,MIN(1,(IFERROR(INDEX(Data!$AG$4:$AG$375,MATCH((WeekStart+0),Data!$A$4:$A$375,0)),""))/10000))*6,0))&REPT("░",6-ROUND(MAX(0,MIN(1,(IFERROR(INDEX(Data!$AG$4:$AG$375,MATCH((WeekStart+0),Data!$A$4:$A$375,0)),""))/10000))*6,0)),""),"") | C51: =IF(ISNUMBER(IFERROR(INDEX(Data!$AG$4:$AG$375,MATCH((WeekStart+0),Data!$A$4:$A$375,0)),"")),(IFERROR(INDEX(Data!$AG$4:$AG$375,MATCH((WeekStart+0),Data!$A$4:$A$375,0)),""))/1000,"") | E51: ="Steps "&IF(ISNUMBER(IFERROR(INDEX(Data!$AG$4:$AG$375,MATCH((WeekStart+1),Data!$A$4:$A$375,0)),"")),IF(ISNUMBER((IFERROR(INDEX(Data!$AG$4:$AG$375,MATCH((WeekStart+1),Data!$A$4:$A$375,0)),""))/10000),REPT("█",ROUND(MAX(0,MIN(1,(IFERROR(INDEX(Data!$AG$4:$AG$375,MATCH((WeekStart+1),Data!$A$4:$A$375,0)),""))/10000))*6,0))&REPT("░",6-ROUND(MAX(0,MIN(1,(IFERROR(INDEX(Data!$AG$4:$AG$375,MATCH((WeekStart+1),Data!$A$4:$A$375,0)),""))/10000))*6,0)),""),"") | F51: =IF(ISNUMBER(IFERROR(INDEX(Data!$AG$4:$AG$375,MATCH((WeekStart+1),Data!$A$4:$A$375,0)),"")),(IFERROR(INDEX(Data!$AG$4:$AG$375,MATCH((WeekStart+1),Data!$A$4:$A$375,0)),""))/1000,"") | H51: ="Steps "&IF(ISNUMBER(IFERROR(INDEX(Data!$AG$4:$AG$375,MATCH((WeekStart+2),Data!$A$4:$A$375,0)),"")),IF(ISNUMBER((IFERROR(INDEX(Data!$AG$4:$AG$375,MATCH((WeekStart+2),Data!$A$4:$A$375,0)),""))/10000),REPT("█",ROUND(MAX(0,MIN(1,(IFERROR(INDEX(Data!$AG$4:$AG$375,MATCH((WeekStart+2),Data!$A$4:$A$375,0)),""))/10000))*6,0))&REPT("░",6-ROUND(MAX(0,MIN(1,(IFERROR(INDEX(Data!$AG$4:$AG$375,MATCH((WeekStart+2),Data!$A$4:$A$375,0)),""))/10000))*6,0)),""),"") | I51: =IF(ISNUMBER(IFERROR(INDEX(Data!$AG$4:$AG$375,MATCH((WeekStart+2),Data!$A$4:$A$375,0)),"")),(IFERROR(INDEX(Data!$AG$4:$AG$375,MATCH((WeekStart+2),Data!$A$4:$A$375,0)),""))/1000,"") | K51: ="Steps "&IF(ISNUMBER(IFERROR(INDEX(Data!$AG$4:$AG$375,MATCH((WeekStart+3),Data!$A$4:$A$375,0)),"")),IF(ISNUMBER((IFERROR(INDEX(Data!$AG$4:$AG$375,MATCH((WeekStart+3),Data!$A$4:$A$375,0)),""))/10000),REPT("█",ROUND(MAX(0,MIN(1,(IFERROR(INDEX(Data!$AG$4:$AG$375,MATCH((WeekStart+3),Data!$A$4:$A$375,0)),""))/10000))*6,0))&REPT("░",6-ROUND(MAX(0,MIN(1,(IFERROR(INDEX(Data!$AG$4:$AG$375,MATCH((WeekStart+3),Data!$A$4:$A$375,0)),""))/10000))*6,0)),""),"") | L51: =IF(ISNUMBER(IFERROR(INDEX(Data!$AG$4:$AG$375,MATCH((WeekStart+3),Data!$A$4:$A$375,0)),"")),(IFERROR(INDEX(Data!$AG$4:$AG$375,MATCH((WeekStart+3),Data!$A$4:$A$375,0)),""))/1000,"") | N51: ="Steps "&IF(ISNUMBER(IFERROR(INDEX(Data!$AG$4:$AG$375,MATCH((WeekStart+4),Data!$A$4:$A$375,0)),"")),IF(ISNUMBER((IFERROR(INDEX(Data!$AG$4:$AG$375,MATCH((WeekStart+4),Data!$A$4:$A$375,0)),""))/10000),REPT("█",ROUND(MAX(0,MIN(1,(IFERROR(INDEX(Data!$AG$4:$AG$375,MATCH((WeekStart+4),Data!$A$4:$A$375,0)),""))/10000))*6,0))&REPT("░",6-ROUND(MAX(0,MIN(1,(IFERROR(INDEX(Data!$AG$4:$AG$375,MATCH((WeekStart+4),Data!$A$4:$A$375,0)),""))/10000))*6,0)),""),"") | O51: =IF(ISNUMBER(IFERROR(INDEX(Data!$AG$4:$AG$375,MATCH((WeekStart+4),Data!$A$4:$A$375,0)),"")),(IFERROR(INDEX(Data!$AG$4:$AG$375,MATCH((WeekStart+4),Data!$A$4:$A$375,0)),""))/1000,"") | Q51: ="Steps "&IF(ISNUMBER(IFERROR(INDEX(Data!$AG$4:$AG$375,MATCH((WeekStart+5),Data!$A$4:$A$375,0)),"")),IF(ISNUMBER((IFERROR(INDEX(Data!$AG$4:$AG$375,MATCH((WeekStart+5),Data!$A$4:$A$375,0)),""))/10000),REPT("█",ROUND(MAX(0,MIN(1,(IFERROR(INDEX(Data!$AG$4:$AG$375,MATCH((WeekStart+5),Data!$A$4:$A$375,0)),""))/10000))*6,0))&REPT("░",6-ROUND(MAX(0,MIN(1,(IFERROR(INDEX(Data!$AG$4:$AG$375,MATCH((WeekStart+5),Data!$A$4:$A$375,0)),""))/10000))*6,0)),""),"") | R51: =IF(ISNUMBER(IFERROR(INDEX(Data!$AG$4:$AG$375,MATCH((WeekStart+5),Data!$A$4:$A$375,0)),"")),(IFERROR(INDEX(Data!$AG$4:$AG$375,MATCH((WeekStart+5),Data!$A$4:$A$375,0)),""))/1000,"") | T51: ="Steps "&IF(ISNUMBER(IFERROR(INDEX(Data!$AG$4:$AG$375,MATCH((WeekStart+6),Data!$A$4:$A$375,0)),"")),IF(ISNUMBER((IFERROR(INDEX(Data!$AG$4:$AG$375,MATCH((WeekStart+6),Data!$A$4:$A$375,0)),""))/10000),REPT("█",ROUND(MAX(0,MIN(1,(IFERROR(INDEX(Data!$AG$4:$AG$375,MATCH((WeekStart+6),Data!$A$4:$A$375,0)),""))/10000))*6,0))&REPT("░",6-ROUND(MAX(0,MIN(1,(IFERROR(INDEX(Data!$AG$4:$AG$375,MATCH((WeekStart+6),Data!$A$4:$A$375,0)),""))/10000))*6,0)),""),"") | U51: =IF(ISNUMBER(IFERROR(INDEX(Data!$AG$4:$AG$375,MATCH((WeekStart+6),Data!$A$4:$A$375,0)),"")),(IFERROR(INDEX(Data!$AG$4:$AG$375,MATCH((WeekStart+6),Data!$A$4:$A$375,0)),""))/1000,"")
B55: chart data below (kept invisible on purpose)
B57: =TEXT((WeekStart+0),"ddd") | C57: =(WeekStart+0) | D57: =IFERROR(INDEX(Data!$BF$4:$BF$375,MATCH((WeekStart+0),Data!$A$4:$A$375,0)),"") | E57: =IF(ISNUMBER(D57),D57,NA()) | F57: =IF(ISNUMBER(D57),D57,0) | G57: =1-F57 | H57: =IF(ISNUMBER(IFERROR(INDEX(Data!$AL$4:$AL$375,MATCH((WeekStart+0),Data!$A$4:$A$375,0)),"")),IFERROR(INDEX(Data!$AL$4:$AL$375,MATCH((WeekStart+0),Data!$A$4:$A$375,0)),""),NA()) | I57: =IF(ISNUMBER(IFERROR(INDEX(Data!$AM$4:$AM$375,MATCH((WeekStart+0),Data!$A$4:$A$375,0)),"")),IFERROR(INDEX(Data!$AM$4:$AM$375,MATCH((WeekStart+0),Data!$A$4:$A$375,0)),""),NA()) | J57: =IF(ISNUMBER(IFERROR(INDEX(Data!$AN$4:$AN$375,MATCH((WeekStart+0),Data!$A$4:$A$375,0)),"")),IFERROR(INDEX(Data!$AN$4:$AN$375,MATCH((WeekStart+0),Data!$A$4:$A$375,0)),""),NA())
B58: =TEXT((WeekStart+1),"ddd") | C58: =(WeekStart+1) | D58: =IFERROR(INDEX(Data!$BF$4:$BF$375,MATCH((WeekStart+1),Data!$A$4:$A$375,0)),"") | E58: =IF(ISNUMBER(D58),D58,NA()) | F58: =IF(ISNUMBER(D58),D58,0) | G58: =1-F58 | H58: =IF(ISNUMBER(IFERROR(INDEX(Data!$AL$4:$AL$375,MATCH((WeekStart+1),Data!$A$4:$A$375,0)),"")),IFERROR(INDEX(Data!$AL$4:$AL$375,MATCH((WeekStart+1),Data!$A$4:$A$375,0)),""),NA()) | I58: =IF(ISNUMBER(IFERROR(INDEX(Data!$AM$4:$AM$375,MATCH((WeekStart+1),Data!$A$4:$A$375,0)),"")),IFERROR(INDEX(Data!$AM$4:$AM$375,MATCH((WeekStart+1),Data!$A$4:$A$375,0)),""),NA()) | J58: =IF(ISNUMBER(IFERROR(INDEX(Data!$AN$4:$AN$375,MATCH((WeekStart+1),Data!$A$4:$A$375,0)),"")),IFERROR(INDEX(Data!$AN$4:$AN$375,MATCH((WeekStart+1),Data!$A$4:$A$375,0)),""),NA())
B59: =TEXT((WeekStart+2),"ddd") | C59: =(WeekStart+2) | D59: =IFERROR(INDEX(Data!$BF$4:$BF$375,MATCH((WeekStart+2),Data!$A$4:$A$375,0)),"") | E59: =IF(ISNUMBER(D59),D59,NA()) | F59: =IF(ISNUMBER(D59),D59,0) | G59: =1-F59 | H59: =IF(ISNUMBER(IFERROR(INDEX(Data!$AL$4:$AL$375,MATCH((WeekStart+2),Data!$A$4:$A$375,0)),"")),IFERROR(INDEX(Data!$AL$4:$AL$375,MATCH((WeekStart+2),Data!$A$4:$A$375,0)),""),NA()) | I59: =IF(ISNUMBER(IFERROR(INDEX(Data!$AM$4:$AM$375,MATCH((WeekStart+2),Data!$A$4:$A$375,0)),"")),IFERROR(INDEX(Data!$AM$4:$AM$375,MATCH((WeekStart+2),Data!$A$4:$A$375,0)),""),NA()) | J59: =IF(ISNUMBER(IFERROR(INDEX(Data!$AN$4:$AN$375,MATCH((WeekStart+2),Data!$A$4:$A$375,0)),"")),IFERROR(INDEX(Data!$AN$4:$AN$375,MATCH((WeekStart+2),Data!$A$4:$A$375,0)),""),NA())
B60: =TEXT((WeekStart+3),"ddd") | C60: =(WeekStart+3) | D60: =IFERROR(INDEX(Data!$BF$4:$BF$375,MATCH((WeekStart+3),Data!$A$4:$A$375,0)),"") | E60: =IF(ISNUMBER(D60),D60,NA()) | F60: =IF(ISNUMBER(D60),D60,0) | G60: =1-F60 | H60: =IF(ISNUMBER(IFERROR(INDEX(Data!$AL$4:$AL$375,MATCH((WeekStart+3),Data!$A$4:$A$375,0)),"")),IFERROR(INDEX(Data!$AL$4:$AL$375,MATCH((WeekStart+3),Data!$A$4:$A$375,0)),""),NA()) | I60: =IF(ISNUMBER(IFERROR(INDEX(Data!$AM$4:$AM$375,MATCH((WeekStart+3),Data!$A$4:$A$375,0)),"")),IFERROR(INDEX(Data!$AM$4:$AM$375,MATCH((WeekStart+3),Data!$A$4:$A$375,0)),""),NA()) | J60: =IF(ISNUMBER(IFERROR(INDEX(Data!$AN$4:$AN$375,MATCH((WeekStart+3),Data!$A$4:$A$375,0)),"")),IFERROR(INDEX(Data!$AN$4:$AN$375,MATCH((WeekStart+3),Data!$A$4:$A$375,0)),""),NA())
B61: =TEXT((WeekStart+4),"ddd") | C61: =(WeekStart+4) | D61: =IFERROR(INDEX(Data!$BF$4:$BF$375,MATCH((WeekStart+4),Data!$A$4:$A$375,0)),"") | E61: =IF(ISNUMBER(D61),D61,NA()) | F61: =IF(ISNUMBER(D61),D61,0) | G61: =1-F61 | H61: =IF(ISNUMBER(IFERROR(INDEX(Data!$AL$4:$AL$375,MATCH((WeekStart+4),Data!$A$4:$A$375,0)),"")),IFERROR(INDEX(Data!$AL$4:$AL$375,MATCH((WeekStart+4),Data!$A$4:$A$375,0)),""),NA()) | I61: =IF(ISNUMBER(IFERROR(INDEX(Data!$AM$4:$AM$375,MATCH((WeekStart+4),Data!$A$4:$A$375,0)),"")),IFERROR(INDEX(Data!$AM$4:$AM$375,MATCH((WeekStart+4),Data!$A$4:$A$375,0)),""),NA()) | J61: =IF(ISNUMBER(IFERROR(INDEX(Data!$AN$4:$AN$375,MATCH((WeekStart+4),Data!$A$4:$A$375,0)),"")),IFERROR(INDEX(Data!$AN$4:$AN$375,MATCH((WeekStart+4),Data!$A$4:$A$375,0)),""),NA())
B62: =TEXT((WeekStart+5),"ddd") | C62: =(WeekStart+5) | D62: =IFERROR(INDEX(Data!$BF$4:$BF$375,MATCH((WeekStart+5),Data!$A$4:$A$375,0)),"") | E62: =IF(ISNUMBER(D62),D62,NA()) | F62: =IF(ISNUMBER(D62),D62,0) | G62: =1-F62 | H62: =IF(ISNUMBER(IFERROR(INDEX(Data!$AL$4:$AL$375,MATCH((WeekStart+5),Data!$A$4:$A$375,0)),"")),IFERROR(INDEX(Data!$AL$4:$AL$375,MATCH((WeekStart+5),Data!$A$4:$A$375,0)),""),NA()) | I62: =IF(ISNUMBER(IFERROR(INDEX(Data!$AM$4:$AM$375,MATCH((WeekStart+5),Data!$A$4:$A$375,0)),"")),IFERROR(INDEX(Data!$AM$4:$AM$375,MATCH((WeekStart+5),Data!$A$4:$A$375,0)),""),NA()) | J62: =IF(ISNUMBER(IFERROR(INDEX(Data!$AN$4:$AN$375,MATCH((WeekStart+5),Data!$A$4:$A$375,0)),"")),IFERROR(INDEX(Data!$AN$4:$AN$375,MATCH((WeekStart+5),Data!$A$4:$A$375,0)),""),NA())
B63: =TEXT((WeekStart+6),"ddd") | C63: =(WeekStart+6) | D63: =IFERROR(INDEX(Data!$BF$4:$BF$375,MATCH((WeekStart+6),Data!$A$4:$A$375,0)),"") | E63: =IF(ISNUMBER(D63),D63,NA()) | F63: =IF(ISNUMBER(D63),D63,0) | G63: =1-F63 | H63: =IF(ISNUMBER(IFERROR(INDEX(Data!$AL$4:$AL$375,MATCH((WeekStart+6),Data!$A$4:$A$375,0)),"")),IFERROR(INDEX(Data!$AL$4:$AL$375,MATCH((WeekStart+6),Data!$A$4:$A$375,0)),""),NA()) | I63: =IF(ISNUMBER(IFERROR(INDEX(Data!$AM$4:$AM$375,MATCH((WeekStart+6),Data!$A$4:$A$375,0)),"")),IFERROR(INDEX(Data!$AM$4:$AM$375,MATCH((WeekStart+6),Data!$A$4:$A$375,0)),""),NA()) | J63: =IF(ISNUMBER(IFERROR(INDEX(Data!$AN$4:$AN$375,MATCH((WeekStart+6),Data!$A$4:$A$375,0)),"")),IFERROR(INDEX(Data!$AN$4:$AN$375,MATCH((WeekStart+6),Data!$A$4:$A$375,0)),""),NA())
B64: week | D64: =IFERROR(AVERAGE(D57:D63),"") | F64: =IF(ISNUMBER(D64),D64,0) | G64: =1-F64

Sheet Oct 2026
AP1: =DATE(2026,10,1)
B2: =UPPER(TEXT($AP$1,"mmmm")) | E2: HABITS | L2: CHECK-INS | S2: FOUNDATION · MONTH | AC2: ROLLING 7-DAY | AK2: ROLLING 30-DAY | AP2: =ProtHit
B3: ="— Life OS · Habit Tracker · "&YEAR($AP$1)&" —" | E3: =COUNTA(B10:B18,B20:B32,B34:B37) | L3: =COUNTIF(E10:AI18,TRUE)+COUNTIF(E10:AI18,"x")+COUNTIF(E20:AI32,TRUE)+COUNTIF(E20:AI32,"x")+COUNTIF(E34:AI37,TRUE)+COUNTIF(E34:AI37,"x") | S3: =IF(ISNUMBER(AK39),TEXT(AK39,"0%")&" "&IF(ISNUMBER(AK39),REPT("█",ROUND(MAX(0,MIN(1,AK39))*12,0))&REPT("░",12-ROUND(MAX(0,MIN(1,AK39))*12,0)),""),"—") | AC3: =IF(ISNUMBER(IFERROR(INDEX(Data!$BG$4:$BG$375,MATCH($AP$13,Data!$A$4:$A$375,0)),"")),TEXT(IFERROR(INDEX(Data!$BG$4:$BG$375,MATCH($AP$13,Data!$A$4:$A$375,0)),""),"0%")&" · "&IF(NOT(ISNUMBER(IFERROR(INDEX(Data!$BG$4:$BG$375,MATCH($AP$13,Data!$A$4:$A$375,0)),""))),"—",IF(IFERROR(INDEX(Data!$BG$4:$BG$375,MATCH($AP$13,Data!$A$4:$A$375,0)),"")>=Band1,"GREEN",IF(IFERROR(INDEX(Data!$BG$4:$BG$375,MATCH($AP$13,Data!$A$4:$A$375,0)),"")>=Band2,"GOOD",IF(IFERROR(INDEX(Data!$BG$4:$BG$375,MATCH($AP$13,Data!$A$4:$A$375,0)),"")>=Band3,"NEEDS ATTENTION","RESET")))),"—") | AK3: =IF(ISNUMBER(IFERROR(INDEX(Data!$BH$4:$BH$375,MATCH($AP$13,Data!$A$4:$A$375,0)),"")),TEXT(IFERROR(INDEX(Data!$BH$4:$BH$375,MATCH($AP$13,Data!$A$4:$A$375,0)),""),"0%")&" · "&IF(NOT(ISNUMBER(IFERROR(INDEX(Data!$BH$4:$BH$375,MATCH($AP$13,Data!$A$4:$A$375,0)),""))),"—",IF(IFERROR(INDEX(Data!$BH$4:$BH$375,MATCH($AP$13,Data!$A$4:$A$375,0)),"")>=Band1,"GREEN",IF(IFERROR(INDEX(Data!$BH$4:$BH$375,MATCH($AP$13,Data!$A$4:$A$375,0)),"")>=Band2,"GOOD",IF(IFERROR(INDEX(Data!$BH$4:$BH$375,MATCH($AP$13,Data!$A$4:$A$375,0)),"")>=Band3,"NEEDS ATTENTION","RESET")))),"—") | AP3: =WaterHit
AP4: =SleepMin
B5: MY HABITS | E5: Week 1 | L5: Week 2 | S5: Week 3 | Z5: Week 4 | AG5: Week 5 | AK5: ANALYSIS | AP5: =SleepLow
B6: Tick what you did. Missed is data, not failure. | E6: =IF(E7="","",LEFT(TEXT(E7,"ddd"),2)) | F6: =IF(F7="","",LEFT(TEXT(F7,"ddd"),2)) | G6: =IF(G7="","",LEFT(TEXT(G7,"ddd"),2)) | H6: =IF(H7="","",LEFT(TEXT(H7,"ddd"),2)) | I6: =IF(I7="","",LEFT(TEXT(I7,"ddd"),2)) | J6: =IF(J7="","",LEFT(TEXT(J7,"ddd"),2)) | K6: =IF(K7="","",LEFT(TEXT(K7,"ddd"),2)) | L6: =IF(L7="","",LEFT(TEXT(L7,"ddd"),2)) | ... AI6: =IF(AI7="","",LEFT(TEXT(AI7,"ddd"),2)) | AK6: Done | AL6: Goal | AM6: Progress | AN6: % | AP6: =TODAY()
B7: Habit | C7: Pillar | D7: Target | E7: =IF(1<=DAY(EOMONTH($AP$1,0)),$AP$1+0,"") | F7: =IF(2<=DAY(EOMONTH($AP$1,0)),$AP$1+1,"") | G7: =IF(3<=DAY(EOMONTH($AP$1,0)),$AP$1+2,"") | H7: =IF(4<=DAY(EOMONTH($AP$1,0)),$AP$1+3,"") | I7: =IF(5<=DAY(EOMONTH($AP$1,0)),$AP$1+4,"") | J7: =IF(6<=DAY(EOMONTH($AP$1,0)),$AP$1+5,"") | K7: =IF(7<=DAY(EOMONTH($AP$1,0)),$AP$1+6,"") | L7: =IF(8<=DAY(EOMONTH($AP$1,0)),$AP$1+7,"") | M7: =IF(9<=DAY(EOMONTH($AP$1,0)),$AP$1+8,"") | N7: =IF(10<=DAY(EOMONTH($AP$1,0)),$AP$1+9,"") | O7: =IF(11<=DAY(EOMONTH($AP$1,0)),$AP$1+10,"") | P7: =IF(12<=DAY(EOMONTH($AP$1,0)),$AP$1+11,"") | Q7: =IF(13<=DAY(EOMONTH($AP$1,0)),$AP$1+12,"") | R7: =IF(14<=DAY(EOMONTH($AP$1,0)),$AP$1+13,"") | S7: =IF(15<=DAY(EOMONTH($AP$1,0)),$AP$1+14,"") | T7: =IF(16<=DAY(EOMONTH($AP$1,0)),$AP$1+15,"") | U7: =IF(17<=DAY(EOMONTH($AP$1,0)),$AP$1+16,"") | V7: =IF(18<=DAY(EOMONTH($AP$1,0)),$AP$1+17,"") | W7: =IF(19<=DAY(EOMONTH($AP$1,0)),$AP$1+18,"") | X7: =IF(20<=DAY(EOMONTH($AP$1,0)),$AP$1+19,"") | Y7: =IF(21<=DAY(EOMONTH($AP$1,0)),$AP$1+20,"") | Z7: =IF(22<=DAY(EOMONTH($AP$1,0)),$AP$1+21,"") | AA7: =IF(23<=DAY(EOMONTH($AP$1,0)),$AP$1+22,"") | AB7: =IF(24<=DAY(EOMONTH($AP$1,0)),$AP$1+23,"") | AC7: =IF(25<=DAY(EOMONTH($AP$1,0)),$AP$1+24,"") | AD7: =IF(26<=DAY(EOMONTH($AP$1,0)),$AP$1+25,"") | AE7: =IF(27<=DAY(EOMONTH($AP$1,0)),$AP$1+26,"") | AF7: =IF(28<=DAY(EOMONTH($AP$1,0)),$AP$1+27,"") | AG7: =IF(29<=DAY(EOMONTH($AP$1,0)),$AP$1+28,"") | AH7: =IF(30<=DAY(EOMONTH($AP$1,0)),$AP$1+29,"") | AI7: =IF(31<=DAY(EOMONTH($AP$1,0)),$AP$1+30,"") | AK7: goal = weekly target × days tracked | AP7: =KcalMin
B8: Day mode | C8: M = minimum · S = sick · R = rest | AK8: =COUNTIF(E8:AI8,"M")&" min · "&COUNTIF(E8:AI8,"S")&" sick · "&COUNTIF(E8:AI8,"R")&" rest" | AP8: =KcalMax
B9: LEVEL 1 · NON-NEGOTIABLES | AK9: the daily foundation | AP9: =COUNTIFS(Data!$B$4:$B$375,1,Data!$AO$4:$AO$375,1,Data!$E$4:$E$375,"<>S")
B10: 🌅 Morning reset | C10: HEALTH | D10: Daily | AK10: =COUNTIF(E10:AI10,TRUE)+COUNTIF(E10:AI10,"x") | AL10: =ROUND($AP$9*7/7,0) | AM10: =IF(ISNUMBER(AN10),REPT("█",ROUND(MAX(0,MIN(1,AN10))*10,0))&REPT("░",10-ROUND(MAX(0,MIN(1,AN10))*10,0)),"") | AN10: =IF(N(AL10)=0,"",MIN(1,AK10/AL10)) | AP10: =COUNTIFS(Data!$B$4:$B$375,1,Data!$AO$4:$AO$375,1,Data!$E$4:$E$375,"<>S",Data!$AS$4:$AS$375,1)
B11: 🙏 Prayer + Scripture ◆ | C11: SPIRIT | D11: Daily | AK11: =COUNTIF(E11:AI11,TRUE)+COUNTIF(E11:AI11,"x") | AL11: =ROUND($AP$9*7/7,0) | AM11: =IF(ISNUMBER(AN11),REPT("█",ROUND(MAX(0,MIN(1,AN11))*10,0))&REPT("░",10-ROUND(MAX(0,MIN(1,AN11))*10,0)),"") | AN11: =IF(N(AL11)=0,"",MIN(1,AK11/AL11)) | AP11: =_xlfn.MAXIFS(Data!$A$4:$A$375,Data!$B$4:$B$375,1,Data!$AF$4:$AF$375,">0")
B12: 🧘 Mobility & posture ◆ | C12: POSTURE | D12: Daily | AK12: =COUNTIF(E12:AI12,TRUE)+COUNTIF(E12:AI12,"x") | AL12: =ROUND($AP$9*7/7,0) | AM12: =IF(ISNUMBER(AN12),REPT("█",ROUND(MAX(0,MIN(1,AN12))*10,0))&REPT("░",10-ROUND(MAX(0,MIN(1,AN12))*10,0)),"") | AN12: =IF(N(AL12)=0,"",MIN(1,AK12/AL12)) | AP12: =_xlfn.MINIFS(Data!$A$4:$A$375,Data!$B$4:$B$375,1,Data!$AF$4:$AF$375,">0")
B13: 💪 Training / movement ◆ | C13: BODY | D13: Daily | AK13: =COUNTIF(E13:AI13,TRUE)+COUNTIF(E13:AI13,"x") | AL13: =ROUND($AP$9*7/7,0) | AM13: =IF(ISNUMBER(AN13),REPT("█",ROUND(MAX(0,MIN(1,AN13))*10,0))&REPT("░",10-ROUND(MAX(0,MIN(1,AN13))*10,0)),"") | AN13: =IF(N(AL13)=0,"",MIN(1,AK13/AL13)) | AP13: =MIN(AP6,EOMONTH(AP1,0))
B14: 🎯 Top 3 priorities | C14: WORK | D14: 5× / wk | AK14: =COUNTIF(E14:AI14,TRUE)+COUNTIF(E14:AI14,"x") | AL14: =$AP$10 | AM14: =IF(ISNUMBER(AN14),REPT("█",ROUND(MAX(0,MIN(1,AN14))*10,0))&REPT("░",10-ROUND(MAX(0,MIN(1,AN14))*10,0)),"") | AN14: =IF(N(AL14)=0,"",MIN(1,AK14/AL14))
B15: ❤️ Fiancée time ◆ | C15: RELATIONSHIPS | D15: Daily | AK15: =COUNTIF(E15:AI15,TRUE)+COUNTIF(E15:AI15,"x") | AL15: =ROUND($AP$9*7/7,0) | AM15: =IF(ISNUMBER(AN15),REPT("█",ROUND(MAX(0,MIN(1,AN15))*10,0))&REPT("░",10-ROUND(MAX(0,MIN(1,AN15))*10,0)),"") | AN15: =IF(N(AL15)=0,"",MIN(1,AK15/AL15))
B16: 📖 Read / learn | C16: MIND | D16: Daily | AK16: =COUNTIF(E16:AI16,TRUE)+COUNTIF(E16:AI16,"x") | AL16: =ROUND($AP$9*7/7,0) | AM16: =IF(ISNUMBER(AN16),REPT("█",ROUND(MAX(0,MIN(1,AN16))*10,0))&REPT("░",10-ROUND(MAX(0,MIN(1,AN16))*10,0)),"") | AN16: =IF(N(AL16)=0,"",MIN(1,AK16/AL16))
B17: 🌙 Evening shutdown | C17: WORK | D17: Daily | AK17: =COUNTIF(E17:AI17,TRUE)+COUNTIF(E17:AI17,"x") | AL17: =ROUND($AP$9*7/7,0) | AM17: =IF(ISNUMBER(AN17),REPT("█",ROUND(MAX(0,MIN(1,AN17))*10,0))&REPT("░",10-ROUND(MAX(0,MIN(1,AN17))*10,0)),"") | AN17: =IF(N(AL17)=0,"",MIN(1,AK17/AL17))
B18: 😴 Lights out 22:00 ◆ | C18: HEALTH | D18: Daily | AK18: =COUNTIF(E18:AI18,TRUE)+COUNTIF(E18:AI18,"x") | AL18: =ROUND($AP$9*7/7,0) | AM18: =IF(ISNUMBER(AN18),REPT("█",ROUND(MAX(0,MIN(1,AN18))*10,0))&REPT("░",10-ROUND(MAX(0,MIN(1,AN18))*10,0)),"") | AN18: =IF(N(AL18)=0,"",MIN(1,AK18/AL18))
B19: LEVEL 2 · HIGH VALUE | AK19: weekly targets
B20: 🏋️ Strength session | C20: BODY | D20: 4× / wk | AK20: =COUNTIF(E20:AI20,TRUE)+COUNTIF(E20:AI20,"x") | AL20: =ROUND($AP$9*4/7,0) | AM20: =IF(ISNUMBER(AN20),REPT("█",ROUND(MAX(0,MIN(1,AN20))*10,0))&REPT("░",10-ROUND(MAX(0,MIN(1,AN20))*10,0)),"") | AN20: =IF(N(AL20)=0,"",MIN(1,AK20/AL20))
B21: 📈 Progression achieved | C21: BODY | D21: 4× / wk | AK21: =COUNTIF(E21:AI21,TRUE)+COUNTIF(E21:AI21,"x") | AL21: =ROUND($AP$9*4/7,0) | AM21: =IF(ISNUMBER(AN21),REPT("█",ROUND(MAX(0,MIN(1,AN21))*10,0))&REPT("░",10-ROUND(MAX(0,MIN(1,AN21))*10,0)),"") | AN21: =IF(N(AL21)=0,"",MIN(1,AK21/AL21))
B22: 🧱 Core | C22: BODY | D22: 3× / wk | AK22: =COUNTIF(E22:AI22,TRUE)+COUNTIF(E22:AI22,"x") | AL22: =ROUND($AP$9*3/7,0) | AM22: =IF(ISNUMBER(AN22),REPT("█",ROUND(MAX(0,MIN(1,AN22))*10,0))&REPT("░",10-ROUND(MAX(0,MIN(1,AN22))*10,0)),"") | AN22: =IF(N(AL22)=0,"",MIN(1,AK22/AL22))
B23: 🦵 Calves | C23: BODY | D23: 3× / wk | AK23: =COUNTIF(E23:AI23,TRUE)+COUNTIF(E23:AI23,"x") | AL23: =ROUND($AP$9*3/7,0) | AM23: =IF(ISNUMBER(AN23),REPT("█",ROUND(MAX(0,MIN(1,AN23))*10,0))&REPT("░",10-ROUND(MAX(0,MIN(1,AN23))*10,0)),"") | AN23: =IF(N(AL23)=0,"",MIN(1,AK23/AL23))
B24: 🚶 Cardio | C24: BODY | D24: 2× / wk | AK24: =COUNTIF(E24:AI24,TRUE)+COUNTIF(E24:AI24,"x") | AL24: =ROUND($AP$9*2/7,0) | AM24: =IF(ISNUMBER(AN24),REPT("█",ROUND(MAX(0,MIN(1,AN24))*10,0))&REPT("░",10-ROUND(MAX(0,MIN(1,AN24))*10,0)),"") | AN24: =IF(N(AL24)=0,"",MIN(1,AK24/AL24))
B25: 🧠 Deep work 2+ blocks | C25: WORK | D25: 5× / wk | AK25: =COUNTIF(E25:AI25,TRUE)+COUNTIF(E25:AI25,"x") | AL25: =ROUND($AP$9*5/7,0) | AM25: =IF(ISNUMBER(AN25),REPT("█",ROUND(MAX(0,MIN(1,AN25))*10,0))&REPT("░",10-ROUND(MAX(0,MIN(1,AN25))*10,0)),"") | AN25: =IF(N(AL25)=0,"",MIN(1,AK25/AL25))
B26: 👀 Posture & eye breaks | C26: POSTURE | D26: 5× / wk | AK26: =COUNTIF(E26:AI26,TRUE)+COUNTIF(E26:AI26,"x") | AL26: =ROUND($AP$9*5/7,0) | AM26: =IF(ISNUMBER(AN26),REPT("█",ROUND(MAX(0,MIN(1,AN26))*10,0))&REPT("░",10-ROUND(MAX(0,MIN(1,AN26))*10,0)),"") | AN26: =IF(N(AL26)=0,"",MIN(1,AK26/AL26))
B27: 🧹 Home reset | C27: LIFE ADMIN | D27: 5× / wk | AK27: =COUNTIF(E27:AI27,TRUE)+COUNTIF(E27:AI27,"x") | AL27: =ROUND($AP$9*5/7,0) | AM27: =IF(ISNUMBER(AN27),REPT("█",ROUND(MAX(0,MIN(1,AN27))*10,0))&REPT("░",10-ROUND(MAX(0,MIN(1,AN27))*10,0)),"") | AN27: =IF(N(AL27)=0,"",MIN(1,AK27/AL27))
B28: 👦 Father–son time | C28: RELATIONSHIPS | D28: 1× / wk | AK28: =COUNTIF(E28:AI28,TRUE)+COUNTIF(E28:AI28,"x") | AL28: =ROUND($AP$9*1/7,0) | AM28: =IF(ISNUMBER(AN28),REPT("█",ROUND(MAX(0,MIN(1,AN28))*10,0))&REPT("░",10-ROUND(MAX(0,MIN(1,AN28))*10,0)),"") | AN28: =IF(N(AL28)=0,"",MIN(1,AK28/AL28))
B29: 🥂 Couple time / date | C29: RELATIONSHIPS | D29: 1× / wk | AK29: =COUNTIF(E29:AI29,TRUE)+COUNTIF(E29:AI29,"x") | AL29: =ROUND($AP$9*1/7,0) | AM29: =IF(ISNUMBER(AN29),REPT("█",ROUND(MAX(0,MIN(1,AN29))*10,0))&REPT("░",10-ROUND(MAX(0,MIN(1,AN29))*10,0)),"") | AN29: =IF(N(AL29)=0,"",MIN(1,AK29/AL29))
B30: 📞 Family check-in | C30: RELATIONSHIPS | D30: 1× / wk | AK30: =COUNTIF(E30:AI30,TRUE)+COUNTIF(E30:AI30,"x") | AL30: =ROUND($AP$9*1/7,0) | AM30: =IF(ISNUMBER(AN30),REPT("█",ROUND(MAX(0,MIN(1,AN30))*10,0))&REPT("░",10-ROUND(MAX(0,MIN(1,AN30))*10,0)),"") | AN30: =IF(N(AL30)=0,"",MIN(1,AK30/AL30))
B31: ⛪ Church / worship | C31: SPIRIT | D31: 1× / wk | AK31: =COUNTIF(E31:AI31,TRUE)+COUNTIF(E31:AI31,"x") | AL31: =ROUND($AP$9*1/7,0) | AM31: =IF(ISNUMBER(AN31),REPT("█",ROUND(MAX(0,MIN(1,AN31))*10,0))&REPT("░",10-ROUND(MAX(0,MIN(1,AN31))*10,0)),"") | AN31: =IF(N(AL31)=0,"",MIN(1,AK31/AL31))
B32: 🍱 Meal prep | C32: LIFE ADMIN | D32: 1× / wk | AK32: =COUNTIF(E32:AI32,TRUE)+COUNTIF(E32:AI32,"x") | AL32: =ROUND($AP$9*1/7,0) | AM32: =IF(ISNUMBER(AN32),REPT("█",ROUND(MAX(0,MIN(1,AN32))*10,0))&REPT("░",10-ROUND(MAX(0,MIN(1,AN32))*10,0)),"") | AN32: =IF(N(AL32)=0,"",MIN(1,AK32/AL32))
B33: LEVEL 3 · OPTIONAL | AK33: bonus, never guilt
B34: 🕊️ Meditation / journal | C34: MIND | D34: Optional | AK34: =COUNTIF(E34:AI34,TRUE)+COUNTIF(E34:AI34,"x") | AL34: — | AM34: =IF(AK34=0,"",AK34&" × bonus")
B35: ➕ Extra walk / cardio | C35: BODY | D35: Optional | AK35: =COUNTIF(E35:AI35,TRUE)+COUNTIF(E35:AI35,"x") | AL35: — | AM35: =IF(AK35=0,"",AK35&" × bonus")
B36: ➕ Extra mobility | C36: POSTURE | D36: Optional | AK36: =COUNTIF(E36:AI36,TRUE)+COUNTIF(E36:AI36,"x") | AL36: — | AM36: =IF(AK36=0,"",AK36&" × bonus")
B37: ➕ Extra reading | C37: MIND | D37: Optional | AK37: =COUNTIF(E37:AI37,TRUE)+COUNTIF(E37:AI37,"x") | AL37: — | AM37: =IF(AK37=0,"",AK37&" × bonus")
B39: Foundation score | C39: auto · 9 pillars of the day | E39: =Data!BF4 | F39: =Data!BF5 | G39: =Data!BF6 | H39: =Data!BF7 | I39: =Data!BF8 | J39: =Data!BF9 | K39: =Data!BF10 | L39: =Data!BF11 | M39: =Data!BF12 | N39: =Data!BF13 | O39: =Data!BF14 | P39: =Data!BF15 | Q39: =Data!BF16 | R39: =Data!BF17 | S39: =Data!BF18 | T39: =Data!BF19 | U39: =Data!BF20 | V39: =Data!BF21 | W39: =Data!BF22 | X39: =Data!BF23 | Y39: =Data!BF24 | Z39: =Data!BF25 | AA39: =Data!BF26 | AB39: =Data!BF27 | AC39: =Data!BF28 | AD39: =Data!BF29 | AE39: =Data!BF30 | AF39: =Data!BF31 | AG39: =Data!BF32 | AH39: =Data!BF33 | AI39: =Data!BF34 | AK39: =IFERROR(AVERAGE(E39:AI39),"") | AL39: avg | AM39: =IF(ISNUMBER(AN39),REPT("█",ROUND(MAX(0,MIN(1,AN39))*10,0))&REPT("░",10-ROUND(MAX(0,MIN(1,AN39))*10,0)),"") | AN39: =AK39
B40: Non-negotiables done | C40: of 9 (8 on non-work days) | E40: =IF(Data!BF4="","",Data!BJ4) | F40: =IF(Data!BF5="","",Data!BJ5) | G40: =IF(Data!BF6="","",Data!BJ6) | H40: =IF(Data!BF7="","",Data!BJ7) | I40: =IF(Data!BF8="","",Data!BJ8) | J40: =IF(Data!BF9="","",Data!BJ9) | K40: =IF(Data!BF10="","",Data!BJ10) | L40: =IF(Data!BF11="","",Data!BJ11) | M40: =IF(Data!BF12="","",Data!BJ12) | N40: =IF(Data!BF13="","",Data!BJ13) | O40: =IF(Data!BF14="","",Data!BJ14) | P40: =IF(Data!BF15="","",Data!BJ15) | Q40: =IF(Data!BF16="","",Data!BJ16) | R40: =IF(Data!BF17="","",Data!BJ17) | S40: =IF(Data!BF18="","",Data!BJ18) | T40: =IF(Data!BF19="","",Data!BJ19) | U40: =IF(Data!BF20="","",Data!BJ20) | V40: =IF(Data!BF21="","",Data!BJ21) | W40: =IF(Data!BF22="","",Data!BJ22) | X40: =IF(Data!BF23="","",Data!BJ23) | Y40: =IF(Data!BF24="","",Data!BJ24) | Z40: =IF(Data!BF25="","",Data!BJ25) | AA40: =IF(Data!BF26="","",Data!BJ26) | AB40: =IF(Data!BF27="","",Data!BJ27) | AC40: =IF(Data!BF28="","",Data!BJ28) | AD40: =IF(Data!BF29="","",Data!BJ29) | AE40: =IF(Data!BF30="","",Data!BJ30) | AF40: =IF(Data!BF31="","",Data!BJ31) | AG40: =IF(Data!BF32="","",Data!BJ32) | AH40: =IF(Data!BF33="","",Data!BJ33) | AI40: =IF(Data!BF34="","",Data!BJ34)
B42: DAILY FOUNDATION SCORE | AK42: WEEKLY AVERAGE
B43: One number for the day, built from 9 things: Sleep · Movement · Protein · Water · Steps · Prayer · Top 3 (work days) · Fiancée · Read/learn M days are scored on the Minimum Viable Day. S days are paused — no score, no guilt. ◆ = part of the Minimum Viable Day
AK44: Week 1 | AM44: =IF(ISNUMBER(AN44),REPT("█",ROUND(MAX(0,MIN(1,AN44))*10,0))&REPT("░",10-ROUND(MAX(0,MIN(1,AN44))*10,0)),"") | AN44: =IFERROR(AVERAGE(E39:K39),"")
AK46: Week 2 | AM46: =IF(ISNUMBER(AN46),REPT("█",ROUND(MAX(0,MIN(1,AN46))*10,0))&REPT("░",10-ROUND(MAX(0,MIN(1,AN46))*10,0)),"") | AN46: =IFERROR(AVERAGE(L39:R39),"")
AK48: Week 3 | AM48: =IF(ISNUMBER(AN48),REPT("█",ROUND(MAX(0,MIN(1,AN48))*10,0))&REPT("░",10-ROUND(MAX(0,MIN(1,AN48))*10,0)),"") | AN48: =IFERROR(AVERAGE(S39:Y39),"")
AK50: Week 4 | AM50: =IF(ISNUMBER(AN50),REPT("█",ROUND(MAX(0,MIN(1,AN50))*10,0))&REPT("░",10-ROUND(MAX(0,MIN(1,AN50))*10,0)),"") | AN50: =IFERROR(AVERAGE(Z39:AF39),"")
AK52: Week 5 | AM52: =IF(ISNUMBER(AN52),REPT("█",ROUND(MAX(0,MIN(1,AN52))*10,0))&REPT("░",10-ROUND(MAX(0,MIN(1,AN52))*10,0)),"") | AN52: =IFERROR(AVERAGE(AG39:AI39),"")
B56: BODY & MIND | E56: Week 1 | L56: Week 2 | S56: Week 3 | Z56: Week 4 | AG56: Week 5 | AK56: ANALYSIS
B57: Log the numbers you have. Blank is fine. | E57: =E6 | F57: =F6 | G57: =G6 | H57: =H6 | I57: =I6 | J57: =J6 | K57: =K6 | L57: =L6 | ... AI57: =AI6 | AK57: Avg | AL57: Target | AM57: Progress | AN57: Hit %
B58: Metric | C58: Unit | D58: Target | E58: =E7 | F58: =F7 | G58: =G7 | H58: =H7 | I58: =I7 | J58: =J7 | K58: =K7 | L58: =L7 | ... AI58: =AI7 | AK58: hit % = days on target ÷ days logged
B59: ⚖️ Weight | C59: kg | D59: AM, 7-day avg | AK59: =IF($AP$11=0,"",INDEX(Data!$BI$4:$BI$375,MATCH($AP$11,Data!$A$4:$A$375,0))) | AL59: 7d avg | AM59: =IF($AP$11=0,"",IFERROR("Δ month "&TEXT(AK59-INDEX(Data!$BI$4:$BI$375,MATCH($AP$12,Data!$A$4:$A$375,0)),"+0.0;-0.0")&" kg",""))
B60: 👣 Steps | C60: steps | D60: adaptive | AK60: =IFERROR(AVERAGE(E60:AI60),"") | AL60: =IFERROR(MAX(E69:AI69)*1000,"") | AM60: =IF(AND(ISNUMBER(AK60),ISNUMBER(AL60)),IF(ISNUMBER(AK60/AL60),REPT("█",ROUND(MAX(0,MIN(1,AK60/AL60))*10,0))&REPT("░",10-ROUND(MAX(0,MIN(1,AK60/AL60))*10,0)),""),"") | AN60: =IFERROR(SUMIFS(Data!$AY$4:$AY$375,Data!$B$4:$B$375,1)/COUNTIFS(Data!$B$4:$B$375,1,Data!$AG$4:$AG$375,">0"),"")
B61: 🍗 Protein | C61: g | D61: 150 g | AK61: =IFERROR(AVERAGE(E61:AI61),"") | AL61: =ProtTarget | AM61: =IF(AND(ISNUMBER(AK61),ISNUMBER(AL61)),IF(ISNUMBER(AK61/AL61),REPT("█",ROUND(MAX(0,MIN(1,AK61/AL61))*10,0))&REPT("░",10-ROUND(MAX(0,MIN(1,AK61/AL61))*10,0)),""),"") | AN61: =IFERROR(SUMIFS(Data!$AW$4:$AW$375,Data!$B$4:$B$375,1)/COUNTIFS(Data!$B$4:$B$375,1,Data!$AH$4:$AH$375,">0"),"")
B62: 💧 Water | C62: L | D62: 2.5–3 L | AK62: =IFERROR(AVERAGE(E62:AI62),"") | AL62: =WaterHit | AM62: =IF(AND(ISNUMBER(AK62),ISNUMBER(AL62)),IF(ISNUMBER(AK62/AL62),REPT("█",ROUND(MAX(0,MIN(1,AK62/AL62))*10,0))&REPT("░",10-ROUND(MAX(0,MIN(1,AK62/AL62))*10,0)),""),"") | AN62: =IFERROR(SUMIFS(Data!$AX$4:$AX$375,Data!$B$4:$B$375,1)/COUNTIFS(Data!$B$4:$B$375,1,Data!$AI$4:$AI$375,">0"),"")
B63: 🔥 Calories | C63: kcal | D63: 1.8–2k | AK63: =IFERROR(AVERAGE(E63:AI63),"") | AL63: =TEXT(KcalMin,"#,##0")&"–"&TEXT(KcalMax,"#,##0") | AM63: =IF(ISNUMBER(AN63),REPT("█",ROUND(MAX(0,MIN(1,AN63))*10,0))&REPT("░",10-ROUND(MAX(0,MIN(1,AN63))*10,0)),"") | AN63: =IFERROR(COUNTIFS(E63:AI63,">="&$AP$7,E63:AI63,"<="&$AP$8)/COUNT(E63:AI63),"")
B64: 🛌 Sleep | C64: hours | D64: 7.5–8.5 h | AK64: =IFERROR(AVERAGE(E64:AI64),"") | AL64: =SleepTarget | AM64: =IF(AND(ISNUMBER(AK64),ISNUMBER(AL64)),IF(ISNUMBER(AK64/AL64),REPT("█",ROUND(MAX(0,MIN(1,AK64/AL64))*10,0))&REPT("░",10-ROUND(MAX(0,MIN(1,AK64/AL64))*10,0)),""),"") | AN64: =IFERROR(COUNTIF(E64:AI64,">="&$AP$4)/COUNT(E64:AI64),"")
B65: ⚡ Energy | C65: 1–10 | D65: 1–10 | AK65: =IFERROR(AVERAGE(E65:AI65),"") | AL65: / 10 | AM65: =IF(ISNUMBER(AK65),IF(ISNUMBER(AK65/10),REPT("█",ROUND(MAX(0,MIN(1,AK65/10))*10,0))&REPT("░",10-ROUND(MAX(0,MIN(1,AK65/10))*10,0)),""),"")
B66: 🌡️ Stress | C66: 1–10 | D66: 1–10 | AK66: =IFERROR(AVERAGE(E66:AI66),"") | AL66: / 10 | AM66: =IF(ISNUMBER(AK66),IF(ISNUMBER(AK66/10),REPT("█",ROUND(MAX(0,MIN(1,AK66/10))*10,0))&REPT("░",10-ROUND(MAX(0,MIN(1,AK66/10))*10,0)),""),"")
B67: 🙂 Mood | C67: 1–10 | D67: 1–10 | AK67: =IFERROR(AVERAGE(E67:AI67),"") | AL67: / 10 | AM67: =IF(ISNUMBER(AK67),IF(ISNUMBER(AK67/10),REPT("█",ROUND(MAX(0,MIN(1,AK67/10))*10,0))&REPT("░",10-ROUND(MAX(0,MIN(1,AK67/10))*10,0)),""),"")
B68: ↳ Weight · 7-day average | C68: decide on this | E68: =Data!BI4 | F68: =Data!BI5 | G68: =Data!BI6 | H68: =Data!BI7 | I68: =Data!BI8 | J68: =Data!BI9 | K68: =Data!BI10 | L68: =Data!BI11 | M68: =Data!BI12 | N68: =Data!BI13 | O68: =Data!BI14 | P68: =Data!BI15 | Q68: =Data!BI16 | R68: =Data!BI17 | S68: =Data!BI18 | T68: =Data!BI19 | U68: =Data!BI20 | V68: =Data!BI21 | W68: =Data!BI22 | X68: =Data!BI23 | Y68: =Data!BI24 | Z68: =Data!BI25 | AA68: =Data!BI26 | AB68: =Data!BI27 | AC68: =Data!BI28 | AD68: =Data!BI29 | AE68: =Data!BI30 | AF68: =Data!BI31 | AG68: =Data!BI32 | AH68: =Data!BI33 | AI68: =Data!BI34
B69: ↳ Steps target (adaptive) | C69: 7k → 8k → 9k | E69: =IF(Data!A4="","",Data!AR4/1000) | F69: =IF(Data!A5="","",Data!AR5/1000) | G69: =IF(Data!A6="","",Data!AR6/1000) | H69: =IF(Data!A7="","",Data!AR7/1000) | I69: =IF(Data!A8="","",Data!AR8/1000) | J69: =IF(Data!A9="","",Data!AR9/1000) | K69: =IF(Data!A10="","",Data!AR10/1000) | L69: =IF(Data!A11="","",Data!AR11/1000) | M69: =IF(Data!A12="","",Data!AR12/1000) | N69: =IF(Data!A13="","",Data!AR13/1000) | O69: =IF(Data!A14="","",Data!AR14/1000) | P69: =IF(Data!A15="","",Data!AR15/1000) | Q69: =IF(Data!A16="","",Data!AR16/1000) | R69: =IF(Data!A17="","",Data!AR17/1000) | S69: =IF(Data!A18="","",Data!AR18/1000) | T69: =IF(Data!A19="","",Data!AR19/1000) | U69: =IF(Data!A20="","",Data!AR20/1000) | V69: =IF(Data!A21="","",Data!AR21/1000) | W69: =IF(Data!A22="","",Data!AR22/1000) | X69: =IF(Data!A23="","",Data!AR23/1000) | Y69: =IF(Data!A24="","",Data!AR24/1000) | Z69: =IF(Data!A25="","",Data!AR25/1000) | AA69: =IF(Data!A26="","",Data!AR26/1000) | AB69: =IF(Data!A27="","",Data!AR27/1000) | AC69: =IF(Data!A28="","",Data!AR28/1000) | AD69: =IF(Data!A29="","",Data!AR29/1000) | AE69: =IF(Data!A30="","",Data!AR30/1000) | AF69: =IF(Data!A31="","",Data!AR31/1000) | AG69: =IF(Data!A32="","",Data!AR32/1000) | AH69: =IF(Data!A33="","",Data!AR33/1000) | AI69: =IF(Data!A34="","",Data!AR34/1000)
B71: TRENDS | E71: MIND & RECOVERY · energy · stress · mood | U71: WEIGHT · daily vs 7-day average
B72: Energy, stress and mood show how the month feels, not just what got done. Weight: the dots jump around with water and salt. The 7-day average is the only line that decides anything. Target pace: −0.4 to −0.8 kg a week.

Sheet Nov 2026
AP1: =DATE(2026,11,1)
B2: =UPPER(TEXT($AP$1,"mmmm")) | E2: HABITS | L2: CHECK-INS | S2: FOUNDATION · MONTH | AC2: ROLLING 7-DAY | AK2: ROLLING 30-DAY | AP2: =ProtHit
B3: ="— Life OS · Habit Tracker · "&YEAR($AP$1)&" —" | E3: =COUNTA(B10:B18,B20:B32,B34:B37) | L3: =COUNTIF(E10:AI18,TRUE)+COUNTIF(E10:AI18,"x")+COUNTIF(E20:AI32,TRUE)+COUNTIF(E20:AI32,"x")+COUNTIF(E34:AI37,TRUE)+COUNTIF(E34:AI37,"x") | S3: =IF(ISNUMBER(AK39),TEXT(AK39,"0%")&" "&IF(ISNUMBER(AK39),REPT("█",ROUND(MAX(0,MIN(1,AK39))*12,0))&REPT("░",12-ROUND(MAX(0,MIN(1,AK39))*12,0)),""),"—") | AC3: =IF(ISNUMBER(IFERROR(INDEX(Data!$BG$4:$BG$375,MATCH($AP$13,Data!$A$4:$A$375,0)),"")),TEXT(IFERROR(INDEX(Data!$BG$4:$BG$375,MATCH($AP$13,Data!$A$4:$A$375,0)),""),"0%")&" · "&IF(NOT(ISNUMBER(IFERROR(INDEX(Data!$BG$4:$BG$375,MATCH($AP$13,Data!$A$4:$A$375,0)),""))),"—",IF(IFERROR(INDEX(Data!$BG$4:$BG$375,MATCH($AP$13,Data!$A$4:$A$375,0)),"")>=Band1,"GREEN",IF(IFERROR(INDEX(Data!$BG$4:$BG$375,MATCH($AP$13,Data!$A$4:$A$375,0)),"")>=Band2,"GOOD",IF(IFERROR(INDEX(Data!$BG$4:$BG$375,MATCH($AP$13,Data!$A$4:$A$375,0)),"")>=Band3,"NEEDS ATTENTION","RESET")))),"—") | AK3: =IF(ISNUMBER(IFERROR(INDEX(Data!$BH$4:$BH$375,MATCH($AP$13,Data!$A$4:$A$375,0)),"")),TEXT(IFERROR(INDEX(Data!$BH$4:$BH$375,MATCH($AP$13,Data!$A$4:$A$375,0)),""),"0%")&" · "&IF(NOT(ISNUMBER(IFERROR(INDEX(Data!$BH$4:$BH$375,MATCH($AP$13,Data!$A$4:$A$375,0)),""))),"—",IF(IFERROR(INDEX(Data!$BH$4:$BH$375,MATCH($AP$13,Data!$A$4:$A$375,0)),"")>=Band1,"GREEN",IF(IFERROR(INDEX(Data!$BH$4:$BH$375,MATCH($AP$13,Data!$A$4:$A$375,0)),"")>=Band2,"GOOD",IF(IFERROR(INDEX(Data!$BH$4:$BH$375,MATCH($AP$13,Data!$A$4:$A$375,0)),"")>=Band3,"NEEDS ATTENTION","RESET")))),"—") | AP3: =WaterHit
AP4: =SleepMin
B5: MY HABITS | E5: Week 1 | L5: Week 2 | S5: Week 3 | Z5: Week 4 | AG5: Week 5 | AK5: ANALYSIS | AP5: =SleepLow
B6: Tick what you did. Missed is data, not failure. | E6: =IF(E7="","",LEFT(TEXT(E7,"ddd"),2)) | F6: =IF(F7="","",LEFT(TEXT(F7,"ddd"),2)) | G6: =IF(G7="","",LEFT(TEXT(G7,"ddd"),2)) | H6: =IF(H7="","",LEFT(TEXT(H7,"ddd"),2)) | I6: =IF(I7="","",LEFT(TEXT(I7,"ddd"),2)) | J6: =IF(J7="","",LEFT(TEXT(J7,"ddd"),2)) | K6: =IF(K7="","",LEFT(TEXT(K7,"ddd"),2)) | L6: =IF(L7="","",LEFT(TEXT(L7,"ddd"),2)) | ... AI6: =IF(AI7="","",LEFT(TEXT(AI7,"ddd"),2)) | AK6: Done | AL6: Goal | AM6: Progress | AN6: % | AP6: =TODAY()
B7: Habit | C7: Pillar | D7: Target | E7: =IF(1<=DAY(EOMONTH($AP$1,0)),$AP$1+0,"") | F7: =IF(2<=DAY(EOMONTH($AP$1,0)),$AP$1+1,"") | G7: =IF(3<=DAY(EOMONTH($AP$1,0)),$AP$1+2,"") | H7: =IF(4<=DAY(EOMONTH($AP$1,0)),$AP$1+3,"") | I7: =IF(5<=DAY(EOMONTH($AP$1,0)),$AP$1+4,"") | J7: =IF(6<=DAY(EOMONTH($AP$1,0)),$AP$1+5,"") | K7: =IF(7<=DAY(EOMONTH($AP$1,0)),$AP$1+6,"") | L7: =IF(8<=DAY(EOMONTH($AP$1,0)),$AP$1+7,"") | M7: =IF(9<=DAY(EOMONTH($AP$1,0)),$AP$1+8,"") | N7: =IF(10<=DAY(EOMONTH($AP$1,0)),$AP$1+9,"") | O7: =IF(11<=DAY(EOMONTH($AP$1,0)),$AP$1+10,"") | P7: =IF(12<=DAY(EOMONTH($AP$1,0)),$AP$1+11,"") | Q7: =IF(13<=DAY(EOMONTH($AP$1,0)),$AP$1+12,"") | R7: =IF(14<=DAY(EOMONTH($AP$1,0)),$AP$1+13,"") | S7: =IF(15<=DAY(EOMONTH($AP$1,0)),$AP$1+14,"") | T7: =IF(16<=DAY(EOMONTH($AP$1,0)),$AP$1+15,"") | U7: =IF(17<=DAY(EOMONTH($AP$1,0)),$AP$1+16,"") | V7: =IF(18<=DAY(EOMONTH($AP$1,0)),$AP$1+17,"") | W7: =IF(19<=DAY(EOMONTH($AP$1,0)),$AP$1+18,"") | X7: =IF(20<=DAY(EOMONTH($AP$1,0)),$AP$1+19,"") | Y7: =IF(21<=DAY(EOMONTH($AP$1,0)),$AP$1+20,"") | Z7: =IF(22<=DAY(EOMONTH($AP$1,0)),$AP$1+21,"") | AA7: =IF(23<=DAY(EOMONTH($AP$1,0)),$AP$1+22,"") | AB7: =IF(24<=DAY(EOMONTH($AP$1,0)),$AP$1+23,"") | AC7: =IF(25<=DAY(EOMONTH($AP$1,0)),$AP$1+24,"") | AD7: =IF(26<=DAY(EOMONTH($AP$1,0)),$AP$1+25,"") | AE7: =IF(27<=DAY(EOMONTH($AP$1,0)),$AP$1+26,"") | AF7: =IF(28<=DAY(EOMONTH($AP$1,0)),$AP$1+27,"") | AG7: =IF(29<=DAY(EOMONTH($AP$1,0)),$AP$1+28,"") | AH7: =IF(30<=DAY(EOMONTH($AP$1,0)),$AP$1+29,"") | AI7: =IF(31<=DAY(EOMONTH($AP$1,0)),$AP$1+30,"") | AK7: goal = weekly target × days tracked | AP7: =KcalMin
B8: Day mode | C8: M = minimum · S = sick · R = rest | AK8: =COUNTIF(E8:AI8,"M")&" min · "&COUNTIF(E8:AI8,"S")&" sick · "&COUNTIF(E8:AI8,"R")&" rest" | AP8: =KcalMax
B9: LEVEL 1 · NON-NEGOTIABLES | AK9: the daily foundation | AP9: =COUNTIFS(Data!$B$4:$B$375,2,Data!$AO$4:$AO$375,1,Data!$E$4:$E$375,"<>S")
B10: 🌅 Morning reset | C10: HEALTH | D10: Daily | AK10: =COUNTIF(E10:AI10,TRUE)+COUNTIF(E10:AI10,"x") | AL10: =ROUND($AP$9*7/7,0) | AM10: =IF(ISNUMBER(AN10),REPT("█",ROUND(MAX(0,MIN(1,AN10))*10,0))&REPT("░",10-ROUND(MAX(0,MIN(1,AN10))*10,0)),"") | AN10: =IF(N(AL10)=0,"",MIN(1,AK10/AL10)) | AP10: =COUNTIFS(Data!$B$4:$B$375,2,Data!$AO$4:$AO$375,1,Data!$E$4:$E$375,"<>S",Data!$AS$4:$AS$375,1)
B11: 🙏 Prayer + Scripture ◆ | C11: SPIRIT | D11: Daily | AK11: =COUNTIF(E11:AI11,TRUE)+COUNTIF(E11:AI11,"x") | AL11: =ROUND($AP$9*7/7,0) | AM11: =IF(ISNUMBER(AN11),REPT("█",ROUND(MAX(0,MIN(1,AN11))*10,0))&REPT("░",10-ROUND(MAX(0,MIN(1,AN11))*10,0)),"") | AN11: =IF(N(AL11)=0,"",MIN(1,AK11/AL11)) | AP11: =_xlfn.MAXIFS(Data!$A$4:$A$375,Data!$B$4:$B$375,2,Data!$AF$4:$AF$375,">0")
B12: 🧘 Mobility & posture ◆ | C12: POSTURE | D12: Daily | AK12: =COUNTIF(E12:AI12,TRUE)+COUNTIF(E12:AI12,"x") | AL12: =ROUND($AP$9*7/7,0) | AM12: =IF(ISNUMBER(AN12),REPT("█",ROUND(MAX(0,MIN(1,AN12))*10,0))&REPT("░",10-ROUND(MAX(0,MIN(1,AN12))*10,0)),"") | AN12: =IF(N(AL12)=0,"",MIN(1,AK12/AL12)) | AP12: =_xlfn.MINIFS(Data!$A$4:$A$375,Data!$B$4:$B$375,2,Data!$AF$4:$AF$375,">0")
B13: 💪 Training / movement ◆ | C13: BODY | D13: Daily | AK13: =COUNTIF(E13:AI13,TRUE)+COUNTIF(E13:AI13,"x") | AL13: =ROUND($AP$9*7/7,0) | AM13: =IF(ISNUMBER(AN13),REPT("█",ROUND(MAX(0,MIN(1,AN13))*10,0))&REPT("░",10-ROUND(MAX(0,MIN(1,AN13))*10,0)),"") | AN13: =IF(N(AL13)=0,"",MIN(1,AK13/AL13)) | AP13: =MIN(AP6,EOMONTH(AP1,0))
B14: 🎯 Top 3 priorities | C14: WORK | D14: 5× / wk | AK14: =COUNTIF(E14:AI14,TRUE)+COUNTIF(E14:AI14,"x") | AL14: =$AP$10 | AM14: =IF(ISNUMBER(AN14),REPT("█",ROUND(MAX(0,MIN(1,AN14))*10,0))&REPT("░",10-ROUND(MAX(0,MIN(1,AN14))*10,0)),"") | AN14: =IF(N(AL14)=0,"",MIN(1,AK14/AL14))
B15: ❤️ Fiancée time ◆ | C15: RELATIONSHIPS | D15: Daily | AK15: =COUNTIF(E15:AI15,TRUE)+COUNTIF(E15:AI15,"x") | AL15: =ROUND($AP$9*7/7,0) | AM15: =IF(ISNUMBER(AN15),REPT("█",ROUND(MAX(0,MIN(1,AN15))*10,0))&REPT("░",10-ROUND(MAX(0,MIN(1,AN15))*10,0)),"") | AN15: =IF(N(AL15)=0,"",MIN(1,AK15/AL15))
B16: 📖 Read / learn | C16: MIND | D16: Daily | AK16: =COUNTIF(E16:AI16,TRUE)+COUNTIF(E16:AI16,"x") | AL16: =ROUND($AP$9*7/7,0) | AM16: =IF(ISNUMBER(AN16),REPT("█",ROUND(MAX(0,MIN(1,AN16))*10,0))&REPT("░",10-ROUND(MAX(0,MIN(1,AN16))*10,0)),"") | AN16: =IF(N(AL16)=0,"",MIN(1,AK16/AL16))
B17: 🌙 Evening shutdown | C17: WORK | D17: Daily | AK17: =COUNTIF(E17:AI17,TRUE)+COUNTIF(E17:AI17,"x") | AL17: =ROUND($AP$9*7/7,0) | AM17: =IF(ISNUMBER(AN17),REPT("█",ROUND(MAX(0,MIN(1,AN17))*10,0))&REPT("░",10-ROUND(MAX(0,MIN(1,AN17))*10,0)),"") | AN17: =IF(N(AL17)=0,"",MIN(1,AK17/AL17))
B18: 😴 Lights out 22:00 ◆ | C18: HEALTH | D18: Daily | AK18: =COUNTIF(E18:AI18,TRUE)+COUNTIF(E18:AI18,"x") | AL18: =ROUND($AP$9*7/7,0) | AM18: =IF(ISNUMBER(AN18),REPT("█",ROUND(MAX(0,MIN(1,AN18))*10,0))&REPT("░",10-ROUND(MAX(0,MIN(1,AN18))*10,0)),"") | AN18: =IF(N(AL18)=0,"",MIN(1,AK18/AL18))
B19: LEVEL 2 · HIGH VALUE | AK19: weekly targets
B20: 🏋️ Strength session | C20: BODY | D20: 4× / wk | AK20: =COUNTIF(E20:AI20,TRUE)+COUNTIF(E20:AI20,"x") | AL20: =ROUND($AP$9*4/7,0) | AM20: =IF(ISNUMBER(AN20),REPT("█",ROUND(MAX(0,MIN(1,AN20))*10,0))&REPT("░",10-ROUND(MAX(0,MIN(1,AN20))*10,0)),"") | AN20: =IF(N(AL20)=0,"",MIN(1,AK20/AL20))
B21: 📈 Progression achieved | C21: BODY | D21: 4× / wk | AK21: =COUNTIF(E21:AI21,TRUE)+COUNTIF(E21:AI21,"x") | AL21: =ROUND($AP$9*4/7,0) | AM21: =IF(ISNUMBER(AN21),REPT("█",ROUND(MAX(0,MIN(1,AN21))*10,0))&REPT("░",10-ROUND(MAX(0,MIN(1,AN21))*10,0)),"") | AN21: =IF(N(AL21)=0,"",MIN(1,AK21/AL21))
B22: 🧱 Core | C22: BODY | D22: 3× / wk | AK22: =COUNTIF(E22:AI22,TRUE)+COUNTIF(E22:AI22,"x") | AL22: =ROUND($AP$9*3/7,0) | AM22: =IF(ISNUMBER(AN22),REPT("█",ROUND(MAX(0,MIN(1,AN22))*10,0))&REPT("░",10-ROUND(MAX(0,MIN(1,AN22))*10,0)),"") | AN22: =IF(N(AL22)=0,"",MIN(1,AK22/AL22))
B23: 🦵 Calves | C23: BODY | D23: 3× / wk | AK23: =COUNTIF(E23:AI23,TRUE)+COUNTIF(E23:AI23,"x") | AL23: =ROUND($AP$9*3/7,0) | AM23: =IF(ISNUMBER(AN23),REPT("█",ROUND(MAX(0,MIN(1,AN23))*10,0))&REPT("░",10-ROUND(MAX(0,MIN(1,AN23))*10,0)),"") | AN23: =IF(N(AL23)=0,"",MIN(1,AK23/AL23))
B24: 🚶 Cardio | C24: BODY | D24: 2× / wk | AK24: =COUNTIF(E24:AI24,TRUE)+COUNTIF(E24:AI24,"x") | AL24: =ROUND($AP$9*2/7,0) | AM24: =IF(ISNUMBER(AN24),REPT("█",ROUND(MAX(0,MIN(1,AN24))*10,0))&REPT("░",10-ROUND(MAX(0,MIN(1,AN24))*10,0)),"") | AN24: =IF(N(AL24)=0,"",MIN(1,AK24/AL24))
B25: 🧠 Deep work 2+ blocks | C25: WORK | D25: 5× / wk | AK25: =COUNTIF(E25:AI25,TRUE)+COUNTIF(E25:AI25,"x") | AL25: =ROUND($AP$9*5/7,0) | AM25: =IF(ISNUMBER(AN25),REPT("█",ROUND(MAX(0,MIN(1,AN25))*10,0))&REPT("░",10-ROUND(MAX(0,MIN(1,AN25))*10,0)),"") | AN25: =IF(N(AL25)=0,"",MIN(1,AK25/AL25))
B26: 👀 Posture & eye breaks | C26: POSTURE | D26: 5× / wk | AK26: =COUNTIF(E26:AI26,TRUE)+COUNTIF(E26:AI26,"x") | AL26: =ROUND($AP$9*5/7,0) | AM26: =IF(ISNUMBER(AN26),REPT("█",ROUND(MAX(0,MIN(1,AN26))*10,0))&REPT("░",10-ROUND(MAX(0,MIN(1,AN26))*10,0)),"") | AN26: =IF(N(AL26)=0,"",MIN(1,AK26/AL26))
B27: 🧹 Home reset | C27: LIFE ADMIN | D27: 5× / wk | AK27: =COUNTIF(E27:AI27,TRUE)+COUNTIF(E27:AI27,"x") | AL27: =ROUND($AP$9*5/7,0) | AM27: =IF(ISNUMBER(AN27),REPT("█",ROUND(MAX(0,MIN(1,AN27))*10,0))&REPT("░",10-ROUND(MAX(0,MIN(1,AN27))*10,0)),"") | AN27: =IF(N(AL27)=0,"",MIN(1,AK27/AL27))
B28: 👦 Father–son time | C28: RELATIONSHIPS | D28: 1× / wk | AK28: =COUNTIF(E28:AI28,TRUE)+COUNTIF(E28:AI28,"x") | AL28: =ROUND($AP$9*1/7,0) | AM28: =IF(ISNUMBER(AN28),REPT("█",ROUND(MAX(0,MIN(1,AN28))*10,0))&REPT("░",10-ROUND(MAX(0,MIN(1,AN28))*10,0)),"") | AN28: =IF(N(AL28)=0,"",MIN(1,AK28/AL28))
B29: 🥂 Couple time / date | C29: RELATIONSHIPS | D29: 1× / wk | AK29: =COUNTIF(E29:AI29,TRUE)+COUNTIF(E29:AI29,"x") | AL29: =ROUND($AP$9*1/7,0) | AM29: =IF(ISNUMBER(AN29),REPT("█",ROUND(MAX(0,MIN(1,AN29))*10,0))&REPT("░",10-ROUND(MAX(0,MIN(1,AN29))*10,0)),"") | AN29: =IF(N(AL29)=0,"",MIN(1,AK29/AL29))
B30: 📞 Family check-in | C30: RELATIONSHIPS | D30: 1× / wk | AK30: =COUNTIF(E30:AI30,TRUE)+COUNTIF(E30:AI30,"x") | AL30: =ROUND($AP$9*1/7,0) | AM30: =IF(ISNUMBER(AN30),REPT("█",ROUND(MAX(0,MIN(1,AN30))*10,0))&REPT("░",10-ROUND(MAX(0,MIN(1,AN30))*10,0)),"") | AN30: =IF(N(AL30)=0,"",MIN(1,AK30/AL30))
B31: ⛪ Church / worship | C31: SPIRIT | D31: 1× / wk | AK31: =COUNTIF(E31:AI31,TRUE)+COUNTIF(E31:AI31,"x") | AL31: =ROUND($AP$9*1/7,0) | AM31: =IF(ISNUMBER(AN31),REPT("█",ROUND(MAX(0,MIN(1,AN31))*10,0))&REPT("░",10-ROUND(MAX(0,MIN(1,AN31))*10,0)),"") | AN31: =IF(N(AL31)=0,"",MIN(1,AK31/AL31))
B32: 🍱 Meal prep | C32: LIFE ADMIN | D32: 1× / wk | AK32: =COUNTIF(E32:AI32,TRUE)+COUNTIF(E32:AI32,"x") | AL32: =ROUND($AP$9*1/7,0) | AM32: =IF(ISNUMBER(AN32),REPT("█",ROUND(MAX(0,MIN(1,AN32))*10,0))&REPT("░",10-ROUND(MAX(0,MIN(1,AN32))*10,0)),"") | AN32: =IF(N(AL32)=0,"",MIN(1,AK32/AL32))
B33: LEVEL 3 · OPTIONAL | AK33: bonus, never guilt
B34: 🕊️ Meditation / journal | C34: MIND | D34: Optional | AK34: =COUNTIF(E34:AI34,TRUE)+COUNTIF(E34:AI34,"x") | AL34: — | AM34: =IF(AK34=0,"",AK34&" × bonus")
B35: ➕ Extra walk / cardio | C35: BODY | D35: Optional | AK35: =COUNTIF(E35:AI35,TRUE)+COUNTIF(E35:AI35,"x") | AL35: — | AM35: =IF(AK35=0,"",AK35&" × bonus")
B36: ➕ Extra mobility | C36: POSTURE | D36: Optional | AK36: =COUNTIF(E36:AI36,TRUE)+COUNTIF(E36:AI36,"x") | AL36: — | AM36: =IF(AK36=0,"",AK36&" × bonus")
B37: ➕ Extra reading | C37: MIND | D37: Optional | AK37: =COUNTIF(E37:AI37,TRUE)+COUNTIF(E37:AI37,"x") | AL37: — | AM37: =IF(AK37=0,"",AK37&" × bonus")
B39: Foundation score | C39: auto · 9 pillars of the day | E39: =Data!BF35 | F39: =Data!BF36 | G39: =Data!BF37 | H39: =Data!BF38 | I39: =Data!BF39 | J39: =Data!BF40 | K39: =Data!BF41 | L39: =Data!BF42 | M39: =Data!BF43 | N39: =Data!BF44 | O39: =Data!BF45 | P39: =Data!BF46 | Q39: =Data!BF47 | R39: =Data!BF48 | S39: =Data!BF49 | T39: =Data!BF50 | U39: =Data!BF51 | V39: =Data!BF52 | W39: =Data!BF53 | X39: =Data!BF54 | Y39: =Data!BF55 | Z39: =Data!BF56 | AA39: =Data!BF57 | AB39: =Data!BF58 | AC39: =Data!BF59 | AD39: =Data!BF60 | AE39: =Data!BF61 | AF39: =Data!BF62 | AG39: =Data!BF63 | AH39: =Data!BF64 | AI39: =Data!BF65 | AK39: =IFERROR(AVERAGE(E39:AI39),"") | AL39: avg | AM39: =IF(ISNUMBER(AN39),REPT("█",ROUND(MAX(0,MIN(1,AN39))*10,0))&REPT("░",10-ROUND(MAX(0,MIN(1,AN39))*10,0)),"") | AN39: =AK39
B40: Non-negotiables done | C40: of 9 (8 on non-work days) | E40: =IF(Data!BF35="","",Data!BJ35) | F40: =IF(Data!BF36="","",Data!BJ36) | G40: =IF(Data!BF37="","",Data!BJ37) | H40: =IF(Data!BF38="","",Data!BJ38) | I40: =IF(Data!BF39="","",Data!BJ39) | J40: =IF(Data!BF40="","",Data!BJ40) | K40: =IF(Data!BF41="","",Data!BJ41) | L40: =IF(Data!BF42="","",Data!BJ42) | M40: =IF(Data!BF43="","",Data!BJ43) | N40: =IF(Data!BF44="","",Data!BJ44) | O40: =IF(Data!BF45="","",Data!BJ45) | P40: =IF(Data!BF46="","",Data!BJ46) | Q40: =IF(Data!BF47="","",Data!BJ47) | R40: =IF(Data!BF48="","",Data!BJ48) | S40: =IF(Data!BF49="","",Data!BJ49) | T40: =IF(Data!BF50="","",Data!BJ50) | U40: =IF(Data!BF51="","",Data!BJ51) | V40: =IF(Data!BF52="","",Data!BJ52) | W40: =IF(Data!BF53="","",Data!BJ53) | X40: =IF(Data!BF54="","",Data!BJ54) | Y40: =IF(Data!BF55="","",Data!BJ55) | Z40: =IF(Data!BF56="","",Data!BJ56) | AA40: =IF(Data!BF57="","",Data!BJ57) | AB40: =IF(Data!BF58="","",Data!BJ58) | AC40: =IF(Data!BF59="","",Data!BJ59) | AD40: =IF(Data!BF60="","",Data!BJ60) | AE40: =IF(Data!BF61="","",Data!BJ61) | AF40: =IF(Data!BF62="","",Data!BJ62) | AG40: =IF(Data!BF63="","",Data!BJ63) | AH40: =IF(Data!BF64="","",Data!BJ64) | AI40: =IF(Data!BF65="","",Data!BJ65)
B42: DAILY FOUNDATION SCORE | AK42: WEEKLY AVERAGE
B43: One number for the day, built from 9 things: Sleep · Movement · Protein · Water · Steps · Prayer · Top 3 (work days) · Fiancée · Read/learn M days are scored on the Minimum Viable Day. S days are paused — no score, no guilt. ◆ = part of the Minimum Viable Day
AK44: Week 1 | AM44: =IF(ISNUMBER(AN44),REPT("█",ROUND(MAX(0,MIN(1,AN44))*10,0))&REPT("░",10-ROUND(MAX(0,MIN(1,AN44))*10,0)),"") | AN44: =IFERROR(AVERAGE(E39:K39),"")
AK46: Week 2 | AM46: =IF(ISNUMBER(AN46),REPT("█",ROUND(MAX(0,MIN(1,AN46))*10,0))&REPT("░",10-ROUND(MAX(0,MIN(1,AN46))*10,0)),"") | AN46: =IFERROR(AVERAGE(L39:R39),"")
AK48: Week 3 | AM48: =IF(ISNUMBER(AN48),REPT("█",ROUND(MAX(0,MIN(1,AN48))*10,0))&REPT("░",10-ROUND(MAX(0,MIN(1,AN48))*10,0)),"") | AN48: =IFERROR(AVERAGE(S39:Y39),"")
AK50: Week 4 | AM50: =IF(ISNUMBER(AN50),REPT("█",ROUND(MAX(0,MIN(1,AN50))*10,0))&REPT("░",10-ROUND(MAX(0,MIN(1,AN50))*10,0)),"") | AN50: =IFERROR(AVERAGE(Z39:AF39),"")
AK52: Week 5 | AM52: =IF(ISNUMBER(AN52),REPT("█",ROUND(MAX(0,MIN(1,AN52))*10,0))&REPT("░",10-ROUND(MAX(0,MIN(1,AN52))*10,0)),"") | AN52: =IFERROR(AVERAGE(AG39:AI39),"")
B56: BODY & MIND | E56: Week 1 | L56: Week 2 | S56: Week 3 | Z56: Week 4 | AG56: Week 5 | AK56: ANALYSIS
B57: Log the numbers you have. Blank is fine. | E57: =E6 | F57: =F6 | G57: =G6 | H57: =H6 | I57: =I6 | J57: =J6 | K57: =K6 | L57: =L6 | ... AI57: =AI6 | AK57: Avg | AL57: Target | AM57: Progress | AN57: Hit %
B58: Metric | C58: Unit | D58: Target | E58: =E7 | F58: =F7 | G58: =G7 | H58: =H7 | I58: =I7 | J58: =J7 | K58: =K7 | L58: =L7 | ... AI58: =AI7 | AK58: hit % = days on target ÷ days logged
B59: ⚖️ Weight | C59: kg | D59: AM, 7-day avg | AK59: =IF($AP$11=0,"",INDEX(Data!$BI$4:$BI$375,MATCH($AP$11,Data!$A$4:$A$375,0))) | AL59: 7d avg | AM59: =IF($AP$11=0,"",IFERROR("Δ month "&TEXT(AK59-INDEX(Data!$BI$4:$BI$375,MATCH($AP$12,Data!$A$4:$A$375,0)),"+0.0;-0.0")&" kg",""))
B60: 👣 Steps | C60: steps | D60: adaptive | AK60: =IFERROR(AVERAGE(E60:AI60),"") | AL60: =IFERROR(MAX(E69:AI69)*1000,"") | AM60: =IF(AND(ISNUMBER(AK60),ISNUMBER(AL60)),IF(ISNUMBER(AK60/AL60),REPT("█",ROUND(MAX(0,MIN(1,AK60/AL60))*10,0))&REPT("░",10-ROUND(MAX(0,MIN(1,AK60/AL60))*10,0)),""),"") | AN60: =IFERROR(SUMIFS(Data!$AY$4:$AY$375,Data!$B$4:$B$375,2)/COUNTIFS(Data!$B$4:$B$375,2,Data!$AG$4:$AG$375,">0"),"")
B61: 🍗 Protein | C61: g | D61: 150 g | AK61: =IFERROR(AVERAGE(E61:AI61),"") | AL61: =ProtTarget | AM61: =IF(AND(ISNUMBER(AK61),ISNUMBER(AL61)),IF(ISNUMBER(AK61/AL61),REPT("█",ROUND(MAX(0,MIN(1,AK61/AL61))*10,0))&REPT("░",10-ROUND(MAX(0,MIN(1,AK61/AL61))*10,0)),""),"") | AN61: =IFERROR(SUMIFS(Data!$AW$4:$AW$375,Data!$B$4:$B$375,2)/COUNTIFS(Data!$B$4:$B$375,2,Data!$AH$4:$AH$375,">0"),"")
B62: 💧 Water | C62: L | D62: 2.5–3 L | AK62: =IFERROR(AVERAGE(E62:AI62),"") | AL62: =WaterHit | AM62: =IF(AND(ISNUMBER(AK62),ISNUMBER(AL62)),IF(ISNUMBER(AK62/AL62),REPT("█",ROUND(MAX(0,MIN(1,AK62/AL62))*10,0))&REPT("░",10-ROUND(MAX(0,MIN(1,AK62/AL62))*10,0)),""),"") | AN62: =IFERROR(SUMIFS(Data!$AX$4:$AX$375,Data!$B$4:$B$375,2)/COUNTIFS(Data!$B$4:$B$375,2,Data!$AI$4:$AI$375,">0"),"")
B63: 🔥 Calories | C63: kcal | D63: 1.8–2k | AK63: =IFERROR(AVERAGE(E63:AI63),"") | AL63: =TEXT(KcalMin,"#,##0")&"–"&TEXT(KcalMax,"#,##0") | AM63: =IF(ISNUMBER(AN63),REPT("█",ROUND(MAX(0,MIN(1,AN63))*10,0))&REPT("░",10-ROUND(MAX(0,MIN(1,AN63))*10,0)),"") | AN63: =IFERROR(COUNTIFS(E63:AI63,">="&$AP$7,E63:AI63,"<="&$AP$8)/COUNT(E63:AI63),"")
B64: 🛌 Sleep | C64: hours | D64: 7.5–8.5 h | AK64: =IFERROR(AVERAGE(E64:AI64),"") | AL64: =SleepTarget | AM64: =IF(AND(ISNUMBER(AK64),ISNUMBER(AL64)),IF(ISNUMBER(AK64/AL64),REPT("█",ROUND(MAX(0,MIN(1,AK64/AL64))*10,0))&REPT("░",10-ROUND(MAX(0,MIN(1,AK64/AL64))*10,0)),""),"") | AN64: =IFERROR(COUNTIF(E64:AI64,">="&$AP$4)/COUNT(E64:AI64),"")
B65: ⚡ Energy | C65: 1–10 | D65: 1–10 | AK65: =IFERROR(AVERAGE(E65:AI65),"") | AL65: / 10 | AM65: =IF(ISNUMBER(AK65),IF(ISNUMBER(AK65/10),REPT("█",ROUND(MAX(0,MIN(1,AK65/10))*10,0))&REPT("░",10-ROUND(MAX(0,MIN(1,AK65/10))*10,0)),""),"")
B66: 🌡️ Stress | C66: 1–10 | D66: 1–10 | AK66: =IFERROR(AVERAGE(E66:AI66),"") | AL66: / 10 | AM66: =IF(ISNUMBER(AK66),IF(ISNUMBER(AK66/10),REPT("█",ROUND(MAX(0,MIN(1,AK66/10))*10,0))&REPT("░",10-ROUND(MAX(0,MIN(1,AK66/10))*10,0)),""),"")
B67: 🙂 Mood | C67: 1–10 | D67: 1–10 | AK67: =IFERROR(AVERAGE(E67:AI67),"") | AL67: / 10 | AM67: =IF(ISNUMBER(AK67),IF(ISNUMBER(AK67/10),REPT("█",ROUND(MAX(0,MIN(1,AK67/10))*10,0))&REPT("░",10-ROUND(MAX(0,MIN(1,AK67/10))*10,0)),""),"")
B68: ↳ Weight · 7-day average | C68: decide on this | E68: =Data!BI35 | F68: =Data!BI36 | G68: =Data!BI37 | H68: =Data!BI38 | I68: =Data!BI39 | J68: =Data!BI40 | K68: =Data!BI41 | L68: =Data!BI42 | M68: =Data!BI43 | N68: =Data!BI44 | O68: =Data!BI45 | P68: =Data!BI46 | Q68: =Data!BI47 | R68: =Data!BI48 | S68: =Data!BI49 | T68: =Data!BI50 | U68: =Data!BI51 | V68: =Data!BI52 | W68: =Data!BI53 | X68: =Data!BI54 | Y68: =Data!BI55 | Z68: =Data!BI56 | AA68: =Data!BI57 | AB68: =Data!BI58 | AC68: =Data!BI59 | AD68: =Data!BI60 | AE68: =Data!BI61 | AF68: =Data!BI62 | AG68: =Data!BI63 | AH68: =Data!BI64 | AI68: =Data!BI65
B69: ↳ Steps target (adaptive) | C69: 7k → 8k → 9k | E69: =IF(Data!A35="","",Data!AR35/1000) | F69: =IF(Data!A36="","",Data!AR36/1000) | G69: =IF(Data!A37="","",Data!AR37/1000) | H69: =IF(Data!A38="","",Data!AR38/1000) | I69: =IF(Data!A39="","",Data!AR39/1000) | J69: =IF(Data!A40="","",Data!AR40/1000) | K69: =IF(Data!A41="","",Data!AR41/1000) | L69: =IF(Data!A42="","",Data!AR42/1000) | M69: =IF(Data!A43="","",Data!AR43/1000) | N69: =IF(Data!A44="","",Data!AR44/1000) | O69: =IF(Data!A45="","",Data!AR45/1000) | P69: =IF(Data!A46="","",Data!AR46/1000) | Q69: =IF(Data!A47="","",Data!AR47/1000) | R69: =IF(Data!A48="","",Data!AR48/1000) | S69: =IF(Data!A49="","",Data!AR49/1000) | T69: =IF(Data!A50="","",Data!AR50/1000) | U69: =IF(Data!A51="","",Data!AR51/1000) | V69: =IF(Data!A52="","",Data!AR52/1000) | W69: =IF(Data!A53="","",Data!AR53/1000) | X69: =IF(Data!A54="","",Data!AR54/1000) | Y69: =IF(Data!A55="","",Data!AR55/1000) | Z69: =IF(Data!A56="","",Data!AR56/1000) | AA69: =IF(Data!A57="","",Data!AR57/1000) | AB69: =IF(Data!A58="","",Data!AR58/1000) | AC69: =IF(Data!A59="","",Data!AR59/1000) | AD69: =IF(Data!A60="","",Data!AR60/1000) | AE69: =IF(Data!A61="","",Data!AR61/1000) | AF69: =IF(Data!A62="","",Data!AR62/1000) | AG69: =IF(Data!A63="","",Data!AR63/1000) | AH69: =IF(Data!A64="","",Data!AR64/1000) | AI69: =IF(Data!A65="","",Data!AR65/1000)
B71: TRENDS | E71: MIND & RECOVERY · energy · stress · mood | U71: WEIGHT · daily vs 7-day average
B72: Energy, stress and mood show how the month feels, not just what got done. Weight: the dots jump around with water and salt. The 7-day average is the only line that decides anything. Target pace: −0.4 to −0.8 kg a week.

Sheet Dec 2026
AP1: =DATE(2026,12,1)
B2: =UPPER(TEXT($AP$1,"mmmm")) | E2: HABITS | L2: CHECK-INS | S2: FOUNDATION · MONTH | AC2: ROLLING 7-DAY | AK2: ROLLING 30-DAY | AP2: =ProtHit
B3: ="— Life OS · Habit Tracker · "&YEAR($AP$1)&" —" | E3: =COUNTA(B10:B18,B20:B32,B34:B37) | L3: =COUNTIF(E10:AI18,TRUE)+COUNTIF(E10:AI18,"x")+COUNTIF(E20:AI32,TRUE)+COUNTIF(E20:AI32,"x")+COUNTIF(E34:AI37,TRUE)+COUNTIF(E34:AI37,"x") | S3: =IF(ISNUMBER(AK39),TEXT(AK39,"0%")&" "&IF(ISNUMBER(AK39),REPT("█",ROUND(MAX(0,MIN(1,AK39))*12,0))&REPT("░",12-ROUND(MAX(0,MIN(1,AK39))*12,0)),""),"—") | AC3: =IF(ISNUMBER(IFERROR(INDEX(Data!$BG$4:$BG$375,MATCH($AP$13,Data!$A$4:$A$375,0)),"")),TEXT(IFERROR(INDEX(Data!$BG$4:$BG$375,MATCH($AP$13,Data!$A$4:$A$375,0)),""),"0%")&" · "&IF(NOT(ISNUMBER(IFERROR(INDEX(Data!$BG$4:$BG$375,MATCH($AP$13,Data!$A$4:$A$375,0)),""))),"—",IF(IFERROR(INDEX(Data!$BG$4:$BG$375,MATCH($AP$13,Data!$A$4:$A$375,0)),"")>=Band1,"GREEN",IF(IFERROR(INDEX(Data!$BG$4:$BG$375,MATCH($AP$13,Data!$A$4:$A$375,0)),"")>=Band2,"GOOD",IF(IFERROR(INDEX(Data!$BG$4:$BG$375,MATCH($AP$13,Data!$A$4:$A$375,0)),"")>=Band3,"NEEDS ATTENTION","RESET")))),"—") | AK3: =IF(ISNUMBER(IFERROR(INDEX(Data!$BH$4:$BH$375,MATCH($AP$13,Data!$A$4:$A$375,0)),"")),TEXT(IFERROR(INDEX(Data!$BH$4:$BH$375,MATCH($AP$13,Data!$A$4:$A$375,0)),""),"0%")&" · "&IF(NOT(ISNUMBER(IFERROR(INDEX(Data!$BH$4:$BH$375,MATCH($AP$13,Data!$A$4:$A$375,0)),""))),"—",IF(IFERROR(INDEX(Data!$BH$4:$BH$375,MATCH($AP$13,Data!$A$4:$A$375,0)),"")>=Band1,"GREEN",IF(IFERROR(INDEX(Data!$BH$4:$BH$375,MATCH($AP$13,Data!$A$4:$A$375,0)),"")>=Band2,"GOOD",IF(IFERROR(INDEX(Data!$BH$4:$BH$375,MATCH($AP$13,Data!$A$4:$A$375,0)),"")>=Band3,"NEEDS ATTENTION","RESET")))),"—") | AP3: =WaterHit
AP4: =SleepMin
B5: MY HABITS | E5: Week 1 | L5: Week 2 | S5: Week 3 | Z5: Week 4 | AG5: Week 5 | AK5: ANALYSIS | AP5: =SleepLow
B6: Tick what you did. Missed is data, not failure. | E6: =IF(E7="","",LEFT(TEXT(E7,"ddd"),2)) | F6: =IF(F7="","",LEFT(TEXT(F7,"ddd"),2)) | G6: =IF(G7="","",LEFT(TEXT(G7,"ddd"),2)) | H6: =IF(H7="","",LEFT(TEXT(H7,"ddd"),2)) | I6: =IF(I7="","",LEFT(TEXT(I7,"ddd"),2)) | J6: =IF(J7="","",LEFT(TEXT(J7,"ddd"),2)) | K6: =IF(K7="","",LEFT(TEXT(K7,"ddd"),2)) | L6: =IF(L7="","",LEFT(TEXT(L7,"ddd"),2)) | ... AI6: =IF(AI7="","",LEFT(TEXT(AI7,"ddd"),2)) | AK6: Done | AL6: Goal | AM6: Progress | AN6: % | AP6: =TODAY()
B7: Habit | C7: Pillar | D7: Target | E7: =IF(1<=DAY(EOMONTH($AP$1,0)),$AP$1+0,"") | F7: =IF(2<=DAY(EOMONTH($AP$1,0)),$AP$1+1,"") | G7: =IF(3<=DAY(EOMONTH($AP$1,0)),$AP$1+2,"") | H7: =IF(4<=DAY(EOMONTH($AP$1,0)),$AP$1+3,"") | I7: =IF(5<=DAY(EOMONTH($AP$1,0)),$AP$1+4,"") | J7: =IF(6<=DAY(EOMONTH($AP$1,0)),$AP$1+5,"") | K7: =IF(7<=DAY(EOMONTH($AP$1,0)),$AP$1+6,"") | L7: =IF(8<=DAY(EOMONTH($AP$1,0)),$AP$1+7,"") | M7: =IF(9<=DAY(EOMONTH($AP$1,0)),$AP$1+8,"") | N7: =IF(10<=DAY(EOMONTH($AP$1,0)),$AP$1+9,"") | O7: =IF(11<=DAY(EOMONTH($AP$1,0)),$AP$1+10,"") | P7: =IF(12<=DAY(EOMONTH($AP$1,0)),$AP$1+11,"") | Q7: =IF(13<=DAY(EOMONTH($AP$1,0)),$AP$1+12,"") | R7: =IF(14<=DAY(EOMONTH($AP$1,0)),$AP$1+13,"") | S7: =IF(15<=DAY(EOMONTH($AP$1,0)),$AP$1+14,"") | T7: =IF(16<=DAY(EOMONTH($AP$1,0)),$AP$1+15,"") | U7: =IF(17<=DAY(EOMONTH($AP$1,0)),$AP$1+16,"") | V7: =IF(18<=DAY(EOMONTH($AP$1,0)),$AP$1+17,"") | W7: =IF(19<=DAY(EOMONTH($AP$1,0)),$AP$1+18,"") | X7: =IF(20<=DAY(EOMONTH($AP$1,0)),$AP$1+19,"") | Y7: =IF(21<=DAY(EOMONTH($AP$1,0)),$AP$1+20,"") | Z7: =IF(22<=DAY(EOMONTH($AP$1,0)),$AP$1+21,"") | AA7: =IF(23<=DAY(EOMONTH($AP$1,0)),$AP$1+22,"") | AB7: =IF(24<=DAY(EOMONTH($AP$1,0)),$AP$1+23,"") | AC7: =IF(25<=DAY(EOMONTH($AP$1,0)),$AP$1+24,"") | AD7: =IF(26<=DAY(EOMONTH($AP$1,0)),$AP$1+25,"") | AE7: =IF(27<=DAY(EOMONTH($AP$1,0)),$AP$1+26,"") | AF7: =IF(28<=DAY(EOMONTH($AP$1,0)),$AP$1+27,"") | AG7: =IF(29<=DAY(EOMONTH($AP$1,0)),$AP$1+28,"") | AH7: =IF(30<=DAY(EOMONTH($AP$1,0)),$AP$1+29,"") | AI7: =IF(31<=DAY(EOMONTH($AP$1,0)),$AP$1+30,"") | AK7: goal = weekly target × days tracked | AP7: =KcalMin
B8: Day mode | C8: M = minimum · S = sick · R = rest | AK8: =COUNTIF(E8:AI8,"M")&" min · "&COUNTIF(E8:AI8,"S")&" sick · "&COUNTIF(E8:AI8,"R")&" rest" | AP8: =KcalMax
B9: LEVEL 1 · NON-NEGOTIABLES | AK9: the daily foundation | AP9: =COUNTIFS(Data!$B$4:$B$375,3,Data!$AO$4:$AO$375,1,Data!$E$4:$E$375,"<>S")
B10: 🌅 Morning reset | C10: HEALTH | D10: Daily | AK10: =COUNTIF(E10:AI10,TRUE)+COUNTIF(E10:AI10,"x") | AL10: =ROUND($AP$9*7/7,0) | AM10: =IF(ISNUMBER(AN10),REPT("█",ROUND(MAX(0,MIN(1,AN10))*10,0))&REPT("░",10-ROUND(MAX(0,MIN(1,AN10))*10,0)),"") | AN10: =IF(N(AL10)=0,"",MIN(1,AK10/AL10)) | AP10: =COUNTIFS(Data!$B$4:$B$375,3,Data!$AO$4:$AO$375,1,Data!$E$4:$E$375,"<>S",Data!$AS$4:$AS$375,1)
B11: 🙏 Prayer + Scripture ◆ | C11: SPIRIT | D11: Daily | AK11: =COUNTIF(E11:AI11,TRUE)+COUNTIF(E11:AI11,"x") | AL11: =ROUND($AP$9*7/7,0) | AM11: =IF(ISNUMBER(AN11),REPT("█",ROUND(MAX(0,MIN(1,AN11))*10,0))&REPT("░",10-ROUND(MAX(0,MIN(1,AN11))*10,0)),"") | AN11: =IF(N(AL11)=0,"",MIN(1,AK11/AL11)) | AP11: =_xlfn.MAXIFS(Data!$A$4:$A$375,Data!$B$4:$B$375,3,Data!$AF$4:$AF$375,">0")
B12: 🧘 Mobility & posture ◆ | C12: POSTURE | D12: Daily | AK12: =COUNTIF(E12:AI12,TRUE)+COUNTIF(E12:AI12,"x") | AL12: =ROUND($AP$9*7/7,0) | AM12: =IF(ISNUMBER(AN12),REPT("█",ROUND(MAX(0,MIN(1,AN12))*10,0))&REPT("░",10-ROUND(MAX(0,MIN(1,AN12))*10,0)),"") | AN12: =IF(N(AL12)=0,"",MIN(1,AK12/AL12)) | AP12: =_xlfn.MINIFS(Data!$A$4:$A$375,Data!$B$4:$B$375,3,Data!$AF$4:$AF$375,">0")
B13: 💪 Training / movement ◆ | C13: BODY | D13: Daily | AK13: =COUNTIF(E13:AI13,TRUE)+COUNTIF(E13:AI13,"x") | AL13: =ROUND($AP$9*7/7,0) | AM13: =IF(ISNUMBER(AN13),REPT("█",ROUND(MAX(0,MIN(1,AN13))*10,0))&REPT("░",10-ROUND(MAX(0,MIN(1,AN13))*10,0)),"") | AN13: =IF(N(AL13)=0,"",MIN(1,AK13/AL13)) | AP13: =MIN(AP6,EOMONTH(AP1,0))
B14: 🎯 Top 3 priorities | C14: WORK | D14: 5× / wk | AK14: =COUNTIF(E14:AI14,TRUE)+COUNTIF(E14:AI14,"x") | AL14: =$AP$10 | AM14: =IF(ISNUMBER(AN14),REPT("█",ROUND(MAX(0,MIN(1,AN14))*10,0))&REPT("░",10-ROUND(MAX(0,MIN(1,AN14))*10,0)),"") | AN14: =IF(N(AL14)=0,"",MIN(1,AK14/AL14))
B15: ❤️ Fiancée time ◆ | C15: RELATIONSHIPS | D15: Daily | AK15: =COUNTIF(E15:AI15,TRUE)+COUNTIF(E15:AI15,"x") | AL15: =ROUND($AP$9*7/7,0) | AM15: =IF(ISNUMBER(AN15),REPT("█",ROUND(MAX(0,MIN(1,AN15))*10,0))&REPT("░",10-ROUND(MAX(0,MIN(1,AN15))*10,0)),"") | AN15: =IF(N(AL15)=0,"",MIN(1,AK15/AL15))
B16: 📖 Read / learn | C16: MIND | D16: Daily | AK16: =COUNTIF(E16:AI16,TRUE)+COUNTIF(E16:AI16,"x") | AL16: =ROUND($AP$9*7/7,0) | AM16: =IF(ISNUMBER(AN16),REPT("█",ROUND(MAX(0,MIN(1,AN16))*10,0))&REPT("░",10-ROUND(MAX(0,MIN(1,AN16))*10,0)),"") | AN16: =IF(N(AL16)=0,"",MIN(1,AK16/AL16))
B17: 🌙 Evening shutdown | C17: WORK | D17: Daily | AK17: =COUNTIF(E17:AI17,TRUE)+COUNTIF(E17:AI17,"x") | AL17: =ROUND($AP$9*7/7,0) | AM17: =IF(ISNUMBER(AN17),REPT("█",ROUND(MAX(0,MIN(1,AN17))*10,0))&REPT("░",10-ROUND(MAX(0,MIN(1,AN17))*10,0)),"") | AN17: =IF(N(AL17)=0,"",MIN(1,AK17/AL17))
B18: 😴 Lights out 22:00 ◆ | C18: HEALTH | D18: Daily | AK18: =COUNTIF(E18:AI18,TRUE)+COUNTIF(E18:AI18,"x") | AL18: =ROUND($AP$9*7/7,0) | AM18: =IF(ISNUMBER(AN18),REPT("█",ROUND(MAX(0,MIN(1,AN18))*10,0))&REPT("░",10-ROUND(MAX(0,MIN(1,AN18))*10,0)),"") | AN18: =IF(N(AL18)=0,"",MIN(1,AK18/AL18))
B19: LEVEL 2 · HIGH VALUE | AK19: weekly targets
B20: 🏋️ Strength session | C20: BODY | D20: 4× / wk | AK20: =COUNTIF(E20:AI20,TRUE)+COUNTIF(E20:AI20,"x") | AL20: =ROUND($AP$9*4/7,0) | AM20: =IF(ISNUMBER(AN20),REPT("█",ROUND(MAX(0,MIN(1,AN20))*10,0))&REPT("░",10-ROUND(MAX(0,MIN(1,AN20))*10,0)),"") | AN20: =IF(N(AL20)=0,"",MIN(1,AK20/AL20))
B21: 📈 Progression achieved | C21: BODY | D21: 4× / wk | AK21: =COUNTIF(E21:AI21,TRUE)+COUNTIF(E21:AI21,"x") | AL21: =ROUND($AP$9*4/7,0) | AM21: =IF(ISNUMBER(AN21),REPT("█",ROUND(MAX(0,MIN(1,AN21))*10,0))&REPT("░",10-ROUND(MAX(0,MIN(1,AN21))*10,0)),"") | AN21: =IF(N(AL21)=0,"",MIN(1,AK21/AL21))
B22: 🧱 Core | C22: BODY | D22: 3× / wk | AK22: =COUNTIF(E22:AI22,TRUE)+COUNTIF(E22:AI22,"x") | AL22: =ROUND($AP$9*3/7,0) | AM22: =IF(ISNUMBER(AN22),REPT("█",ROUND(MAX(0,MIN(1,AN22))*10,0))&REPT("░",10-ROUND(MAX(0,MIN(1,AN22))*10,0)),"") | AN22: =IF(N(AL22)=0,"",MIN(1,AK22/AL22))
B23: 🦵 Calves | C23: BODY | D23: 3× / wk | AK23: =COUNTIF(E23:AI23,TRUE)+COUNTIF(E23:AI23,"x") | AL23: =ROUND($AP$9*3/7,0) | AM23: =IF(ISNUMBER(AN23),REPT("█",ROUND(MAX(0,MIN(1,AN23))*10,0))&REPT("░",10-ROUND(MAX(0,MIN(1,AN23))*10,0)),"") | AN23: =IF(N(AL23)=0,"",MIN(1,AK23/AL23))
B24: 🚶 Cardio | C24: BODY | D24: 2× / wk | AK24: =COUNTIF(E24:AI24,TRUE)+COUNTIF(E24:AI24,"x") | AL24: =ROUND($AP$9*2/7,0) | AM24: =IF(ISNUMBER(AN24),REPT("█",ROUND(MAX(0,MIN(1,AN24))*10,0))&REPT("░",10-ROUND(MAX(0,MIN(1,AN24))*10,0)),"") | AN24: =IF(N(AL24)=0,"",MIN(1,AK24/AL24))
B25: 🧠 Deep work 2+ blocks | C25: WORK | D25: 5× / wk | AK25: =COUNTIF(E25:AI25,TRUE)+COUNTIF(E25:AI25,"x") | AL25: =ROUND($AP$9*5/7,0) | AM25: =IF(ISNUMBER(AN25),REPT("█",ROUND(MAX(0,MIN(1,AN25))*10,0))&REPT("░",10-ROUND(MAX(0,MIN(1,AN25))*10,0)),"") | AN25: =IF(N(AL25)=0,"",MIN(1,AK25/AL25))
B26: 👀 Posture & eye breaks | C26: POSTURE | D26: 5× / wk | AK26: =COUNTIF(E26:AI26,TRUE)+COUNTIF(E26:AI26,"x") | AL26: =ROUND($AP$9*5/7,0) | AM26: =IF(ISNUMBER(AN26),REPT("█",ROUND(MAX(0,MIN(1,AN26))*10,0))&REPT("░",10-ROUND(MAX(0,MIN(1,AN26))*10,0)),"") | AN26: =IF(N(AL26)=0,"",MIN(1,AK26/AL26))
B27: 🧹 Home reset | C27: LIFE ADMIN | D27: 5× / wk | AK27: =COUNTIF(E27:AI27,TRUE)+COUNTIF(E27:AI27,"x") | AL27: =ROUND($AP$9*5/7,0) | AM27: =IF(ISNUMBER(AN27),REPT("█",ROUND(MAX(0,MIN(1,AN27))*10,0))&REPT("░",10-ROUND(MAX(0,MIN(1,AN27))*10,0)),"") | AN27: =IF(N(AL27)=0,"",MIN(1,AK27/AL27))
B28: 👦 Father–son time | C28: RELATIONSHIPS | D28: 1× / wk | AK28: =COUNTIF(E28:AI28,TRUE)+COUNTIF(E28:AI28,"x") | AL28: =ROUND($AP$9*1/7,0) | AM28: =IF(ISNUMBER(AN28),REPT("█",ROUND(MAX(0,MIN(1,AN28))*10,0))&REPT("░",10-ROUND(MAX(0,MIN(1,AN28))*10,0)),"") | AN28: =IF(N(AL28)=0,"",MIN(1,AK28/AL28))
B29: 🥂 Couple time / date | C29: RELATIONSHIPS | D29: 1× / wk | AK29: =COUNTIF(E29:AI29,TRUE)+COUNTIF(E29:AI29,"x") | AL29: =ROUND($AP$9*1/7,0) | AM29: =IF(ISNUMBER(AN29),REPT("█",ROUND(MAX(0,MIN(1,AN29))*10,0))&REPT("░",10-ROUND(MAX(0,MIN(1,AN29))*10,0)),"") | AN29: =IF(N(AL29)=0,"",MIN(1,AK29/AL29))
B30: 📞 Family check-in | C30: RELATIONSHIPS | D30: 1× / wk | AK30: =COUNTIF(E30:AI30,TRUE)+COUNTIF(E30:AI30,"x") | AL30: =ROUND($AP$9*1/7,0) | AM30: =IF(ISNUMBER(AN30),REPT("█",ROUND(MAX(0,MIN(1,AN30))*10,0))&REPT("░",10-ROUND(MAX(0,MIN(1,AN30))*10,0)),"") | AN30: =IF(N(AL30)=0,"",MIN(1,AK30/AL30))
B31: ⛪ Church / worship | C31: SPIRIT | D31: 1× / wk | AK31: =COUNTIF(E31:AI31,TRUE)+COUNTIF(E31:AI31,"x") | AL31: =ROUND($AP$9*1/7,0) | AM31: =IF(ISNUMBER(AN31),REPT("█",ROUND(MAX(0,MIN(1,AN31))*10,0))&REPT("░",10-ROUND(MAX(0,MIN(1,AN31))*10,0)),"") | AN31: =IF(N(AL31)=0,"",MIN(1,AK31/AL31))
B32: 🍱 Meal prep | C32: LIFE ADMIN | D32: 1× / wk | AK32: =COUNTIF(E32:AI32,TRUE)+COUNTIF(E32:AI32,"x") | AL32: =ROUND($AP$9*1/7,0) | AM32: =IF(ISNUMBER(AN32),REPT("█",ROUND(MAX(0,MIN(1,AN32))*10,0))&REPT("░",10-ROUND(MAX(0,MIN(1,AN32))*10,0)),"") | AN32: =IF(N(AL32)=0,"",MIN(1,AK32/AL32))
B33: LEVEL 3 · OPTIONAL | AK33: bonus, never guilt
B34: 🕊️ Meditation / journal | C34: MIND | D34: Optional | AK34: =COUNTIF(E34:AI34,TRUE)+COUNTIF(E34:AI34,"x") | AL34: — | AM34: =IF(AK34=0,"",AK34&" × bonus")
B35: ➕ Extra walk / cardio | C35: BODY | D35: Optional | AK35: =COUNTIF(E35:AI35,TRUE)+COUNTIF(E35:AI35,"x") | AL35: — | AM35: =IF(AK35=0,"",AK35&" × bonus")
B36: ➕ Extra mobility | C36: POSTURE | D36: Optional | AK36: =COUNTIF(E36:AI36,TRUE)+COUNTIF(E36:AI36,"x") | AL36: — | AM36: =IF(AK36=0,"",AK36&" × bonus")
B37: ➕ Extra reading | C37: MIND | D37: Optional | AK37: =COUNTIF(E37:AI37,TRUE)+COUNTIF(E37:AI37,"x") | AL37: — | AM37: =IF(AK37=0,"",AK37&" × bonus")
B39: Foundation score | C39: auto · 9 pillars of the day | E39: =Data!BF66 | F39: =Data!BF67 | G39: =Data!BF68 | H39: =Data!BF69 | I39: =Data!BF70 | J39: =Data!BF71 | K39: =Data!BF72 | L39: =Data!BF73 | M39: =Data!BF74 | N39: =Data!BF75 | O39: =Data!BF76 | P39: =Data!BF77 | Q39: =Data!BF78 | R39: =Data!BF79 | S39: =Data!BF80 | T39: =Data!BF81 | U39: =Data!BF82 | V39: =Data!BF83 | W39: =Data!BF84 | X39: =Data!BF85 | Y39: =Data!BF86 | Z39: =Data!BF87 | AA39: =Data!BF88 | AB39: =Data!BF89 | AC39: =Data!BF90 | AD39: =Data!BF91 | AE39: =Data!BF92 | AF39: =Data!BF93 | AG39: =Data!BF94 | AH39: =Data!BF95 | AI39: =Data!BF96 | AK39: =IFERROR(AVERAGE(E39:AI39),"") | AL39: avg | AM39: =IF(ISNUMBER(AN39),REPT("█",ROUND(MAX(0,MIN(1,AN39))*10,0))&REPT("░",10-ROUND(MAX(0,MIN(1,AN39))*10,0)),"") | AN39: =AK39
B40: Non-negotiables done | C40: of 9 (8 on non-work days) | E40: =IF(Data!BF66="","",Data!BJ66) | F40: =IF(Data!BF67="","",Data!BJ67) | G40: =IF(Data!BF68="","",Data!BJ68) | H40: =IF(Data!BF69="","",Data!BJ69) | I40: =IF(Data!BF70="","",Data!BJ70) | J40: =IF(Data!BF71="","",Data!BJ71) | K40: =IF(Data!BF72="","",Data!BJ72) | L40: =IF(Data!BF73="","",Data!BJ73) | M40: =IF(Data!BF74="","",Data!BJ74) | N40: =IF(Data!BF75="","",Data!BJ75) | O40: =IF(Data!BF76="","",Data!BJ76) | P40: =IF(Data!BF77="","",Data!BJ77) | Q40: =IF(Data!BF78="","",Data!BJ78) | R40: =IF(Data!BF79="","",Data!BJ79) | S40: =IF(Data!BF80="","",Data!BJ80) | T40: =IF(Data!BF81="","",Data!BJ81) | U40: =IF(Data!BF82="","",Data!BJ82) | V40: =IF(Data!BF83="","",Data!BJ83) | W40: =IF(Data!BF84="","",Data!BJ84) | X40: =IF(Data!BF85="","",Data!BJ85) | Y40: =IF(Data!BF86="","",Data!BJ86) | Z40: =IF(Data!BF87="","",Data!BJ87) | AA40: =IF(Data!BF88="","",Data!BJ88) | AB40: =IF(Data!BF89="","",Data!BJ89) | AC40: =IF(Data!BF90="","",Data!BJ90) | AD40: =IF(Data!BF91="","",Data!BJ91) | AE40: =IF(Data!BF92="","",Data!BJ92) | AF40: =IF(Data!BF93="","",Data!BJ93) | AG40: =IF(Data!BF94="","",Data!BJ94) | AH40: =IF(Data!BF95="","",Data!BJ95) | AI40: =IF(Data!BF96="","",Data!BJ96)
B42: DAILY FOUNDATION SCORE | AK42: WEEKLY AVERAGE
B43: One number for the day, built from 9 things: Sleep · Movement · Protein · Water · Steps · Prayer · Top 3 (work days) · Fiancée · Read/learn M days are scored on the Minimum Viable Day. S days are paused — no score, no guilt. ◆ = part of the Minimum Viable Day
AK44: Week 1 | AM44: =IF(ISNUMBER(AN44),REPT("█",ROUND(MAX(0,MIN(1,AN44))*10,0))&REPT("░",10-ROUND(MAX(0,MIN(1,AN44))*10,0)),"") | AN44: =IFERROR(AVERAGE(E39:K39),"")
AK46: Week 2 | AM46: =IF(ISNUMBER(AN46),REPT("█",ROUND(MAX(0,MIN(1,AN46))*10,0))&REPT("░",10-ROUND(MAX(0,MIN(1,AN46))*10,0)),"") | AN46: =IFERROR(AVERAGE(L39:R39),"")
AK48: Week 3 | AM48: =IF(ISNUMBER(AN48),REPT("█",ROUND(MAX(0,MIN(1,AN48))*10,0))&REPT("░",10-ROUND(MAX(0,MIN(1,AN48))*10,0)),"") | AN48: =IFERROR(AVERAGE(S39:Y39),"")
AK50: Week 4 | AM50: =IF(ISNUMBER(AN50),REPT("█",ROUND(MAX(0,MIN(1,AN50))*10,0))&REPT("░",10-ROUND(MAX(0,MIN(1,AN50))*10,0)),"") | AN50: =IFERROR(AVERAGE(Z39:AF39),"")
AK52: Week 5 | AM52: =IF(ISNUMBER(AN52),REPT("█",ROUND(MAX(0,MIN(1,AN52))*10,0))&REPT("░",10-ROUND(MAX(0,MIN(1,AN52))*10,0)),"") | AN52: =IFERROR(AVERAGE(AG39:AI39),"")
B56: BODY & MIND | E56: Week 1 | L56: Week 2 | S56: Week 3 | Z56: Week 4 | AG56: Week 5 | AK56: ANALYSIS
B57: Log the numbers you have. Blank is fine. | E57: =E6 | F57: =F6 | G57: =G6 | H57: =H6 | I57: =I6 | J57: =J6 | K57: =K6 | L57: =L6 | ... AI57: =AI6 | AK57: Avg | AL57: Target | AM57: Progress | AN57: Hit %
B58: Metric | C58: Unit | D58: Target | E58: =E7 | F58: =F7 | G58: =G7 | H58: =H7 | I58: =I7 | J58: =J7 | K58: =K7 | L58: =L7 | ... AI58: =AI7 | AK58: hit % = days on target ÷ days logged
B59: ⚖️ Weight | C59: kg | D59: AM, 7-day avg | AK59: =IF($AP$11=0,"",INDEX(Data!$BI$4:$BI$375,MATCH($AP$11,Data!$A$4:$A$375,0))) | AL59: 7d avg | AM59: =IF($AP$11=0,"",IFERROR("Δ month "&TEXT(AK59-INDEX(Data!$BI$4:$BI$375,MATCH($AP$12,Data!$A$4:$A$375,0)),"+0.0;-0.0")&" kg",""))
B60: 👣 Steps | C60: steps | D60: adaptive | AK60: =IFERROR(AVERAGE(E60:AI60),"") | AL60: =IFERROR(MAX(E69:AI69)*1000,"") | AM60: =IF(AND(ISNUMBER(AK60),ISNUMBER(AL60)),IF(ISNUMBER(AK60/AL60),REPT("█",ROUND(MAX(0,MIN(1,AK60/AL60))*10,0))&REPT("░",10-ROUND(MAX(0,MIN(1,AK60/AL60))*10,0)),""),"") | AN60: =IFERROR(SUMIFS(Data!$AY$4:$AY$375,Data!$B$4:$B$375,3)/COUNTIFS(Data!$B$4:$B$375,3,Data!$AG$4:$AG$375,">0"),"")
B61: 🍗 Protein | C61: g | D61: 150 g | AK61: =IFERROR(AVERAGE(E61:AI61),"") | AL61: =ProtTarget | AM61: =IF(AND(ISNUMBER(AK61),ISNUMBER(AL61)),IF(ISNUMBER(AK61/AL61),REPT("█",ROUND(MAX(0,MIN(1,AK61/AL61))*10,0))&REPT("░",10-ROUND(MAX(0,MIN(1,AK61/AL61))*10,0)),""),"") | AN61: =IFERROR(SUMIFS(Data!$AW$4:$AW$375,Data!$B$4:$B$375,3)/COUNTIFS(Data!$B$4:$B$375,3,Data!$AH$4:$AH$375,">0"),"")
B62: 💧 Water | C62: L | D62: 2.5–3 L | AK62: =IFERROR(AVERAGE(E62:AI62),"") | AL62: =WaterHit | AM62: =IF(AND(ISNUMBER(AK62),ISNUMBER(AL62)),IF(ISNUMBER(AK62/AL62),REPT("█",ROUND(MAX(0,MIN(1,AK62/AL62))*10,0))&REPT("░",10-ROUND(MAX(0,MIN(1,AK62/AL62))*10,0)),""),"") | AN62: =IFERROR(SUMIFS(Data!$AX$4:$AX$375,Data!$B$4:$B$375,3)/COUNTIFS(Data!$B$4:$B$375,3,Data!$AI$4:$AI$375,">0"),"")
B63: 🔥 Calories | C63: kcal | D63: 1.8–2k | AK63: =IFERROR(AVERAGE(E63:AI63),"") | AL63: =TEXT(KcalMin,"#,##0")&"–"&TEXT(KcalMax,"#,##0") | AM63: =IF(ISNUMBER(AN63),REPT("█",ROUND(MAX(0,MIN(1,AN63))*10,0))&REPT("░",10-ROUND(MAX(0,MIN(1,AN63))*10,0)),"") | AN63: =IFERROR(COUNTIFS(E63:AI63,">="&$AP$7,E63:AI63,"<="&$AP$8)/COUNT(E63:AI63),"")
B64: 🛌 Sleep | C64: hours | D64: 7.5–8.5 h | AK64: =IFERROR(AVERAGE(E64:AI64),"") | AL64: =SleepTarget | AM64: =IF(AND(ISNUMBER(AK64),ISNUMBER(AL64)),IF(ISNUMBER(AK64/AL64),REPT("█",ROUND(MAX(0,MIN(1,AK64/AL64))*10,0))&REPT("░",10-ROUND(MAX(0,MIN(1,AK64/AL64))*10,0)),""),"") | AN64: =IFERROR(COUNTIF(E64:AI64,">="&$AP$4)/COUNT(E64:AI64),"")
B65: ⚡ Energy | C65: 1–10 | D65: 1–10 | AK65: =IFERROR(AVERAGE(E65:AI65),"") | AL65: / 10 | AM65: =IF(ISNUMBER(AK65),IF(ISNUMBER(AK65/10),REPT("█",ROUND(MAX(0,MIN(1,AK65/10))*10,0))&REPT("░",10-ROUND(MAX(0,MIN(1,AK65/10))*10,0)),""),"")
B66: 🌡️ Stress | C66: 1–10 | D66: 1–10 | AK66: =IFERROR(AVERAGE(E66:AI66),"") | AL66: / 10 | AM66: =IF(ISNUMBER(AK66),IF(ISNUMBER(AK66/10),REPT("█",ROUND(MAX(0,MIN(1,AK66/10))*10,0))&REPT("░",10-ROUND(MAX(0,MIN(1,AK66/10))*10,0)),""),"")
B67: 🙂 Mood | C67: 1–10 | D67: 1–10 | AK67: =IFERROR(AVERAGE(E67:AI67),"") | AL67: / 10 | AM67: =IF(ISNUMBER(AK67),IF(ISNUMBER(AK67/10),REPT("█",ROUND(MAX(0,MIN(1,AK67/10))*10,0))&REPT("░",10-ROUND(MAX(0,MIN(1,AK67/10))*10,0)),""),"")
B68: ↳ Weight · 7-day average | C68: decide on this | E68: =Data!BI66 | F68: =Data!BI67 | G68: =Data!BI68 | H68: =Data!BI69 | I68: =Data!BI70 | J68: =Data!BI71 | K68: =Data!BI72 | L68: =Data!BI73 | M68: =Data!BI74 | N68: =Data!BI75 | O68: =Data!BI76 | P68: =Data!BI77 | Q68: =Data!BI78 | R68: =Data!BI79 | S68: =Data!BI80 | T68: =Data!BI81 | U68: =Data!BI82 | V68: =Data!BI83 | W68: =Data!BI84 | X68: =Data!BI85 | Y68: =Data!BI86 | Z68: =Data!BI87 | AA68: =Data!BI88 | AB68: =Data!BI89 | AC68: =Data!BI90 | AD68: =Data!BI91 | AE68: =Data!BI92 | AF68: =Data!BI93 | AG68: =Data!BI94 | AH68: =Data!BI95 | AI68: =Data!BI96
B69: ↳ Steps target (adaptive) | C69: 7k → 8k → 9k | E69: =IF(Data!A66="","",Data!AR66/1000) | F69: =IF(Data!A67="","",Data!AR67/1000) | G69: =IF(Data!A68="","",Data!AR68/1000) | H69: =IF(Data!A69="","",Data!AR69/1000) | I69: =IF(Data!A70="","",Data!AR70/1000) | J69: =IF(Data!A71="","",Data!AR71/1000) | K69: =IF(Data!A72="","",Data!AR72/1000) | L69: =IF(Data!A73="","",Data!AR73/1000) | M69: =IF(Data!A74="","",Data!AR74/1000) | N69: =IF(Data!A75="","",Data!AR75/1000) | O69: =IF(Data!A76="","",Data!AR76/1000) | P69: =IF(Data!A77="","",Data!AR77/1000) | Q69: =IF(Data!A78="","",Data!AR78/1000) | R69: =IF(Data!A79="","",Data!AR79/1000) | S69: =IF(Data!A80="","",Data!AR80/1000) | T69: =IF(Data!A81="","",Data!AR81/1000) | U69: =IF(Data!A82="","",Data!AR82/1000) | V69: =IF(Data!A83="","",Data!AR83/1000) | W69: =IF(Data!A84="","",Data!AR84/1000) | X69: =IF(Data!A85="","",Data!AR85/1000) | Y69: =IF(Data!A86="","",Data!AR86/1000) | Z69: =IF(Data!A87="","",Data!AR87/1000) | AA69: =IF(Data!A88="","",Data!AR88/1000) | AB69: =IF(Data!A89="","",Data!AR89/1000) | AC69: =IF(Data!A90="","",Data!AR90/1000) | AD69: =IF(Data!A91="","",Data!AR91/1000) | AE69: =IF(Data!A92="","",Data!AR92/1000) | AF69: =IF(Data!A93="","",Data!AR93/1000) | AG69: =IF(Data!A94="","",Data!AR94/1000) | AH69: =IF(Data!A95="","",Data!AR95/1000) | AI69: =IF(Data!A96="","",Data!AR96/1000)
B71: TRENDS | E71: MIND & RECOVERY · energy · stress · mood | U71: WEIGHT · daily vs 7-day average
B72: Energy, stress and mood show how the month feels, not just what got done. Weight: the dots jump around with water and salt. The 7-day average is the only line that decides anything. Target pace: −0.4 to −0.8 kg a week.

Sheet Jan 2027
AP1: =DATE(2027,1,1)
B2: =UPPER(TEXT($AP$1,"mmmm")) | E2: HABITS | L2: CHECK-INS | S2: FOUNDATION · MONTH | AC2: ROLLING 7-DAY | AK2: ROLLING 30-DAY | AP2: =ProtHit
B3: ="— Life OS · Habit Tracker · "&YEAR($AP$1)&" —" | E3: =COUNTA(B10:B18,B20:B32,B34:B37) | L3: =COUNTIF(E10:AI18,TRUE)+COUNTIF(E10:AI18,"x")+COUNTIF(E20:AI32,TRUE)+COUNTIF(E20:AI32,"x")+COUNTIF(E34:AI37,TRUE)+COUNTIF(E34:AI37,"x") | S3: =IF(ISNUMBER(AK39),TEXT(AK39,"0%")&" "&IF(ISNUMBER(AK39),REPT("█",ROUND(MAX(0,MIN(1,AK39))*12,0))&REPT("░",12-ROUND(MAX(0,MIN(1,AK39))*12,0)),""),"—") | AC3: =IF(ISNUMBER(IFERROR(INDEX(Data!$BG$4:$BG$375,MATCH($AP$13,Data!$A$4:$A$375,0)),"")),TEXT(IFERROR(INDEX(Data!$BG$4:$BG$375,MATCH($AP$13,Data!$A$4:$A$375,0)),""),"0%")&" · "&IF(NOT(ISNUMBER(IFERROR(INDEX(Data!$BG$4:$BG$375,MATCH($AP$13,Data!$A$4:$A$375,0)),""))),"—",IF(IFERROR(INDEX(Data!$BG$4:$BG$375,MATCH($AP$13,Data!$A$4:$A$375,0)),"")>=Band1,"GREEN",IF(IFERROR(INDEX(Data!$BG$4:$BG$375,MATCH($AP$13,Data!$A$4:$A$375,0)),"")>=Band2,"GOOD",IF(IFERROR(INDEX(Data!$BG$4:$BG$375,MATCH($AP$13,Data!$A$4:$A$375,0)),"")>=Band3,"NEEDS ATTENTION","RESET")))),"—") | AK3: =IF(ISNUMBER(IFERROR(INDEX(Data!$BH$4:$BH$375,MATCH($AP$13,Data!$A$4:$A$375,0)),"")),TEXT(IFERROR(INDEX(Data!$BH$4:$BH$375,MATCH($AP$13,Data!$A$4:$A$375,0)),""),"0%")&" · "&IF(NOT(ISNUMBER(IFERROR(INDEX(Data!$BH$4:$BH$375,MATCH($AP$13,Data!$A$4:$A$375,0)),""))),"—",IF(IFERROR(INDEX(Data!$BH$4:$BH$375,MATCH($AP$13,Data!$A$4:$A$375,0)),"")>=Band1,"GREEN",IF(IFERROR(INDEX(Data!$BH$4:$BH$375,MATCH($AP$13,Data!$A$4:$A$375,0)),"")>=Band2,"GOOD",IF(IFERROR(INDEX(Data!$BH$4:$BH$375,MATCH($AP$13,Data!$A$4:$A$375,0)),"")>=Band3,"NEEDS ATTENTION","RESET")))),"—") | AP3: =WaterHit
AP4: =SleepMin
B5: MY HABITS | E5: Week 1 | L5: Week 2 | S5: Week 3 | Z5: Week 4 | AG5: Week 5 | AK5: ANALYSIS | AP5: =SleepLow
B6: Tick what you did. Missed is data, not failure. | E6: =IF(E7="","",LEFT(TEXT(E7,"ddd"),2)) | F6: =IF(F7="","",LEFT(TEXT(F7,"ddd"),2)) | G6: =IF(G7="","",LEFT(TEXT(G7,"ddd"),2)) | H6: =IF(H7="","",LEFT(TEXT(H7,"ddd"),2)) | I6: =IF(I7="","",LEFT(TEXT(I7,"ddd"),2)) | J6: =IF(J7="","",LEFT(TEXT(J7,"ddd"),2)) | K6: =IF(K7="","",LEFT(TEXT(K7,"ddd"),2)) | L6: =IF(L7="","",LEFT(TEXT(L7,"ddd"),2)) | ... AI6: =IF(AI7="","",LEFT(TEXT(AI7,"ddd"),2)) | AK6: Done | AL6: Goal | AM6: Progress | AN6: % | AP6: =TODAY()
B7: Habit | C7: Pillar | D7: Target | E7: =IF(1<=DAY(EOMONTH($AP$1,0)),$AP$1+0,"") | F7: =IF(2<=DAY(EOMONTH($AP$1,0)),$AP$1+1,"") | G7: =IF(3<=DAY(EOMONTH($AP$1,0)),$AP$1+2,"") | H7: =IF(4<=DAY(EOMONTH($AP$1,0)),$AP$1+3,"") | I7: =IF(5<=DAY(EOMONTH($AP$1,0)),$AP$1+4,"") | J7: =IF(6<=DAY(EOMONTH($AP$1,0)),$AP$1+5,"") | K7: =IF(7<=DAY(EOMONTH($AP$1,0)),$AP$1+6,"") | L7: =IF(8<=DAY(EOMONTH($AP$1,0)),$AP$1+7,"") | M7: =IF(9<=DAY(EOMONTH($AP$1,0)),$AP$1+8,"") | N7: =IF(10<=DAY(EOMONTH($AP$1,0)),$AP$1+9,"") | O7: =IF(11<=DAY(EOMONTH($AP$1,0)),$AP$1+10,"") | P7: =IF(12<=DAY(EOMONTH($AP$1,0)),$AP$1+11,"") | Q7: =IF(13<=DAY(EOMONTH($AP$1,0)),$AP$1+12,"") | R7: =IF(14<=DAY(EOMONTH($AP$1,0)),$AP$1+13,"") | S7: =IF(15<=DAY(EOMONTH($AP$1,0)),$AP$1+14,"") | T7: =IF(16<=DAY(EOMONTH($AP$1,0)),$AP$1+15,"") | U7: =IF(17<=DAY(EOMONTH($AP$1,0)),$AP$1+16,"") | V7: =IF(18<=DAY(EOMONTH($AP$1,0)),$AP$1+17,"") | W7: =IF(19<=DAY(EOMONTH($AP$1,0)),$AP$1+18,"") | X7: =IF(20<=DAY(EOMONTH($AP$1,0)),$AP$1+19,"") | Y7: =IF(21<=DAY(EOMONTH($AP$1,0)),$AP$1+20,"") | Z7: =IF(22<=DAY(EOMONTH($AP$1,0)),$AP$1+21,"") | AA7: =IF(23<=DAY(EOMONTH($AP$1,0)),$AP$1+22,"") | AB7: =IF(24<=DAY(EOMONTH($AP$1,0)),$AP$1+23,"") | AC7: =IF(25<=DAY(EOMONTH($AP$1,0)),$AP$1+24,"") | AD7: =IF(26<=DAY(EOMONTH($AP$1,0)),$AP$1+25,"") | AE7: =IF(27<=DAY(EOMONTH($AP$1,0)),$AP$1+26,"") | AF7: =IF(28<=DAY(EOMONTH($AP$1,0)),$AP$1+27,"") | AG7: =IF(29<=DAY(EOMONTH($AP$1,0)),$AP$1+28,"") | AH7: =IF(30<=DAY(EOMONTH($AP$1,0)),$AP$1+29,"") | AI7: =IF(31<=DAY(EOMONTH($AP$1,0)),$AP$1+30,"") | AK7: goal = weekly target × days tracked | AP7: =KcalMin
B8: Day mode | C8: M = minimum · S = sick · R = rest | AK8: =COUNTIF(E8:AI8,"M")&" min · "&COUNTIF(E8:AI8,"S")&" sick · "&COUNTIF(E8:AI8,"R")&" rest" | AP8: =KcalMax
B9: LEVEL 1 · NON-NEGOTIABLES | AK9: the daily foundation | AP9: =COUNTIFS(Data!$B$4:$B$375,4,Data!$AO$4:$AO$375,1,Data!$E$4:$E$375,"<>S")
B10: 🌅 Morning reset | C10: HEALTH | D10: Daily | AK10: =COUNTIF(E10:AI10,TRUE)+COUNTIF(E10:AI10,"x") | AL10: =ROUND($AP$9*7/7,0) | AM10: =IF(ISNUMBER(AN10),REPT("█",ROUND(MAX(0,MIN(1,AN10))*10,0))&REPT("░",10-ROUND(MAX(0,MIN(1,AN10))*10,0)),"") | AN10: =IF(N(AL10)=0,"",MIN(1,AK10/AL10)) | AP10: =COUNTIFS(Data!$B$4:$B$375,4,Data!$AO$4:$AO$375,1,Data!$E$4:$E$375,"<>S",Data!$AS$4:$AS$375,1)
B11: 🙏 Prayer + Scripture ◆ | C11: SPIRIT | D11: Daily | AK11: =COUNTIF(E11:AI11,TRUE)+COUNTIF(E11:AI11,"x") | AL11: =ROUND($AP$9*7/7,0) | AM11: =IF(ISNUMBER(AN11),REPT("█",ROUND(MAX(0,MIN(1,AN11))*10,0))&REPT("░",10-ROUND(MAX(0,MIN(1,AN11))*10,0)),"") | AN11: =IF(N(AL11)=0,"",MIN(1,AK11/AL11)) | AP11: =_xlfn.MAXIFS(Data!$A$4:$A$375,Data!$B$4:$B$375,4,Data!$AF$4:$AF$375,">0")
B12: 🧘 Mobility & posture ◆ | C12: POSTURE | D12: Daily | AK12: =COUNTIF(E12:AI12,TRUE)+COUNTIF(E12:AI12,"x") | AL12: =ROUND($AP$9*7/7,0) | AM12: =IF(ISNUMBER(AN12),REPT("█",ROUND(MAX(0,MIN(1,AN12))*10,0))&REPT("░",10-ROUND(MAX(0,MIN(1,AN12))*10,0)),"") | AN12: =IF(N(AL12)=0,"",MIN(1,AK12/AL12)) | AP12: =_xlfn.MINIFS(Data!$A$4:$A$375,Data!$B$4:$B$375,4,Data!$AF$4:$AF$375,">0")
B13: 💪 Training / movement ◆ | C13: BODY | D13: Daily | AK13: =COUNTIF(E13:AI13,TRUE)+COUNTIF(E13:AI13,"x") | AL13: =ROUND($AP$9*7/7,0) | AM13: =IF(ISNUMBER(AN13),REPT("█",ROUND(MAX(0,MIN(1,AN13))*10,0))&REPT("░",10-ROUND(MAX(0,MIN(1,AN13))*10,0)),"") | AN13: =IF(N(AL13)=0,"",MIN(1,AK13/AL13)) | AP13: =MIN(AP6,EOMONTH(AP1,0))
B14: 🎯 Top 3 priorities | C14: WORK | D14: 5× / wk | AK14: =COUNTIF(E14:AI14,TRUE)+COUNTIF(E14:AI14,"x") | AL14: =$AP$10 | AM14: =IF(ISNUMBER(AN14),REPT("█",ROUND(MAX(0,MIN(1,AN14))*10,0))&REPT("░",10-ROUND(MAX(0,MIN(1,AN14))*10,0)),"") | AN14: =IF(N(AL14)=0,"",MIN(1,AK14/AL14))
B15: ❤️ Fiancée time ◆ | C15: RELATIONSHIPS | D15: Daily | AK15: =COUNTIF(E15:AI15,TRUE)+COUNTIF(E15:AI15,"x") | AL15: =ROUND($AP$9*7/7,0) | AM15: =IF(ISNUMBER(AN15),REPT("█",ROUND(MAX(0,MIN(1,AN15))*10,0))&REPT("░",10-ROUND(MAX(0,MIN(1,AN15))*10,0)),"") | AN15: =IF(N(AL15)=0,"",MIN(1,AK15/AL15))
B16: 📖 Read / learn | C16: MIND | D16: Daily | AK16: =COUNTIF(E16:AI16,TRUE)+COUNTIF(E16:AI16,"x") | AL16: =ROUND($AP$9*7/7,0) | AM16: =IF(ISNUMBER(AN16),REPT("█",ROUND(MAX(0,MIN(1,AN16))*10,0))&REPT("░",10-ROUND(MAX(0,MIN(1,AN16))*10,0)),"") | AN16: =IF(N(AL16)=0,"",MIN(1,AK16/AL16))
B17: 🌙 Evening shutdown | C17: WORK | D17: Daily | AK17: =COUNTIF(E17:AI17,TRUE)+COUNTIF(E17:AI17,"x") | AL17: =ROUND($AP$9*7/7,0) | AM17: =IF(ISNUMBER(AN17),REPT("█",ROUND(MAX(0,MIN(1,AN17))*10,0))&REPT("░",10-ROUND(MAX(0,MIN(1,AN17))*10,0)),"") | AN17: =IF(N(AL17)=0,"",MIN(1,AK17/AL17))
B18: 😴 Lights out 22:00 ◆ | C18: HEALTH | D18: Daily | AK18: =COUNTIF(E18:AI18,TRUE)+COUNTIF(E18:AI18,"x") | AL18: =ROUND($AP$9*7/7,0) | AM18: =IF(ISNUMBER(AN18),REPT("█",ROUND(MAX(0,MIN(1,AN18))*10,0))&REPT("░",10-ROUND(MAX(0,MIN(1,AN18))*10,0)),"") | AN18: =IF(N(AL18)=0,"",MIN(1,AK18/AL18))
B19: LEVEL 2 · HIGH VALUE | AK19: weekly targets
B20: 🏋️ Strength session | C20: BODY | D20: 4× / wk | AK20: =COUNTIF(E20:AI20,TRUE)+COUNTIF(E20:AI20,"x") | AL20: =ROUND($AP$9*4/7,0) | AM20: =IF(ISNUMBER(AN20),REPT("█",ROUND(MAX(0,MIN(1,AN20))*10,0))&REPT("░",10-ROUND(MAX(0,MIN(1,AN20))*10,0)),"") | AN20: =IF(N(AL20)=0,"",MIN(1,AK20/AL20))
B21: 📈 Progression achieved | C21: BODY | D21: 4× / wk | AK21: =COUNTIF(E21:AI21,TRUE)+COUNTIF(E21:AI21,"x") | AL21: =ROUND($AP$9*4/7,0) | AM21: =IF(ISNUMBER(AN21),REPT("█",ROUND(MAX(0,MIN(1,AN21))*10,0))&REPT("░",10-ROUND(MAX(0,MIN(1,AN21))*10,0)),"") | AN21: =IF(N(AL21)=0,"",MIN(1,AK21/AL21))
B22: 🧱 Core | C22: BODY | D22: 3× / wk | AK22: =COUNTIF(E22:AI22,TRUE)+COUNTIF(E22:AI22,"x") | AL22: =ROUND($AP$9*3/7,0) | AM22: =IF(ISNUMBER(AN22),REPT("█",ROUND(MAX(0,MIN(1,AN22))*10,0))&REPT("░",10-ROUND(MAX(0,MIN(1,AN22))*10,0)),"") | AN22: =IF(N(AL22)=0,"",MIN(1,AK22/AL22))
B23: 🦵 Calves | C23: BODY | D23: 3× / wk | AK23: =COUNTIF(E23:AI23,TRUE)+COUNTIF(E23:AI23,"x") | AL23: =ROUND($AP$9*3/7,0) | AM23: =IF(ISNUMBER(AN23),REPT("█",ROUND(MAX(0,MIN(1,AN23))*10,0))&REPT("░",10-ROUND(MAX(0,MIN(1,AN23))*10,0)),"") | AN23: =IF(N(AL23)=0,"",MIN(1,AK23/AL23))
B24: 🚶 Cardio | C24: BODY | D24: 2× / wk | AK24: =COUNTIF(E24:AI24,TRUE)+COUNTIF(E24:AI24,"x") | AL24: =ROUND($AP$9*2/7,0) | AM24: =IF(ISNUMBER(AN24),REPT("█",ROUND(MAX(0,MIN(1,AN24))*10,0))&REPT("░",10-ROUND(MAX(0,MIN(1,AN24))*10,0)),"") | AN24: =IF(N(AL24)=0,"",MIN(1,AK24/AL24))
B25: 🧠 Deep work 2+ blocks | C25: WORK | D25: 5× / wk | AK25: =COUNTIF(E25:AI25,TRUE)+COUNTIF(E25:AI25,"x") | AL25: =ROUND($AP$9*5/7,0) | AM25: =IF(ISNUMBER(AN25),REPT("█",ROUND(MAX(0,MIN(1,AN25))*10,0))&REPT("░",10-ROUND(MAX(0,MIN(1,AN25))*10,0)),"") | AN25: =IF(N(AL25)=0,"",MIN(1,AK25/AL25))
B26: 👀 Posture & eye breaks | C26: POSTURE | D26: 5× / wk | AK26: =COUNTIF(E26:AI26,TRUE)+COUNTIF(E26:AI26,"x") | AL26: =ROUND($AP$9*5/7,0) | AM26: =IF(ISNUMBER(AN26),REPT("█",ROUND(MAX(0,MIN(1,AN26))*10,0))&REPT("░",10-ROUND(MAX(0,MIN(1,AN26))*10,0)),"") | AN26: =IF(N(AL26)=0,"",MIN(1,AK26/AL26))
B27: 🧹 Home reset | C27: LIFE ADMIN | D27: 5× / wk | AK27: =COUNTIF(E27:AI27,TRUE)+COUNTIF(E27:AI27,"x") | AL27: =ROUND($AP$9*5/7,0) | AM27: =IF(ISNUMBER(AN27),REPT("█",ROUND(MAX(0,MIN(1,AN27))*10,0))&REPT("░",10-ROUND(MAX(0,MIN(1,AN27))*10,0)),"") | AN27: =IF(N(AL27)=0,"",MIN(1,AK27/AL27))
B28: 👦 Father–son time | C28: RELATIONSHIPS | D28: 1× / wk | AK28: =COUNTIF(E28:AI28,TRUE)+COUNTIF(E28:AI28,"x") | AL28: =ROUND($AP$9*1/7,0) | AM28: =IF(ISNUMBER(AN28),REPT("█",ROUND(MAX(0,MIN(1,AN28))*10,0))&REPT("░",10-ROUND(MAX(0,MIN(1,AN28))*10,0)),"") | AN28: =IF(N(AL28)=0,"",MIN(1,AK28/AL28))
B29: 🥂 Couple time / date | C29: RELATIONSHIPS | D29: 1× / wk | AK29: =COUNTIF(E29:AI29,TRUE)+COUNTIF(E29:AI29,"x") | AL29: =ROUND($AP$9*1/7,0) | AM29: =IF(ISNUMBER(AN29),REPT("█",ROUND(MAX(0,MIN(1,AN29))*10,0))&REPT("░",10-ROUND(MAX(0,MIN(1,AN29))*10,0)),"") | AN29: =IF(N(AL29)=0,"",MIN(1,AK29/AL29))
B30: 📞 Family check-in | C30: RELATIONSHIPS | D30: 1× / wk | AK30: =COUNTIF(E30:AI30,TRUE)+COUNTIF(E30:AI30,"x") | AL30: =ROUND($AP$9*1/7,0) | AM30: =IF(ISNUMBER(AN30),REPT("█",ROUND(MAX(0,MIN(1,AN30))*10,0))&REPT("░",10-ROUND(MAX(0,MIN(1,AN30))*10,0)),"") | AN30: =IF(N(AL30)=0,"",MIN(1,AK30/AL30))
B31: ⛪ Church / worship | C31: SPIRIT | D31: 1× / wk | AK31: =COUNTIF(E31:AI31,TRUE)+COUNTIF(E31:AI31,"x") | AL31: =ROUND($AP$9*1/7,0) | AM31: =IF(ISNUMBER(AN31),REPT("█",ROUND(MAX(0,MIN(1,AN31))*10,0))&REPT("░",10-ROUND(MAX(0,MIN(1,AN31))*10,0)),"") | AN31: =IF(N(AL31)=0,"",MIN(1,AK31/AL31))
B32: 🍱 Meal prep | C32: LIFE ADMIN | D32: 1× / wk | AK32: =COUNTIF(E32:AI32,TRUE)+COUNTIF(E32:AI32,"x") | AL32: =ROUND($AP$9*1/7,0) | AM32: =IF(ISNUMBER(AN32),REPT("█",ROUND(MAX(0,MIN(1,AN32))*10,0))&REPT("░",10-ROUND(MAX(0,MIN(1,AN32))*10,0)),"") | AN32: =IF(N(AL32)=0,"",MIN(1,AK32/AL32))
B33: LEVEL 3 · OPTIONAL | AK33: bonus, never guilt
B34: 🕊️ Meditation / journal | C34: MIND | D34: Optional | AK34: =COUNTIF(E34:AI34,TRUE)+COUNTIF(E34:AI34,"x") | AL34: — | AM34: =IF(AK34=0,"",AK34&" × bonus")
B35: ➕ Extra walk / cardio | C35: BODY | D35: Optional | AK35: =COUNTIF(E35:AI35,TRUE)+COUNTIF(E35:AI35,"x") | AL35: — | AM35: =IF(AK35=0,"",AK35&" × bonus")
B36: ➕ Extra mobility | C36: POSTURE | D36: Optional | AK36: =COUNTIF(E36:AI36,TRUE)+COUNTIF(E36:AI36,"x") | AL36: — | AM36: =IF(AK36=0,"",AK36&" × bonus")
B37: ➕ Extra reading | C37: MIND | D37: Optional | AK37: =COUNTIF(E37:AI37,TRUE)+COUNTIF(E37:AI37,"x") | AL37: — | AM37: =IF(AK37=0,"",AK37&" × bonus")
B39: Foundation score | C39: auto · 9 pillars of the day | E39: =Data!BF97 | F39: =Data!BF98 | G39: =Data!BF99 | H39: =Data!BF100 | I39: =Data!BF101 | J39: =Data!BF102 | K39: =Data!BF103 | L39: =Data!BF104 | M39: =Data!BF105 | N39: =Data!BF106 | O39: =Data!BF107 | P39: =Data!BF108 | Q39: =Data!BF109 | R39: =Data!BF110 | S39: =Data!BF111 | T39: =Data!BF112 | U39: =Data!BF113 | V39: =Data!BF114 | W39: =Data!BF115 | X39: =Data!BF116 | Y39: =Data!BF117 | Z39: =Data!BF118 | AA39: =Data!BF119 | AB39: =Data!BF120 | AC39: =Data!BF121 | AD39: =Data!BF122 | AE39: =Data!BF123 | AF39: =Data!BF124 | AG39: =Data!BF125 | AH39: =Data!BF126 | AI39: =Data!BF127 | AK39: =IFERROR(AVERAGE(E39:AI39),"") | AL39: avg | AM39: =IF(ISNUMBER(AN39),REPT("█",ROUND(MAX(0,MIN(1,AN39))*10,0))&REPT("░",10-ROUND(MAX(0,MIN(1,AN39))*10,0)),"") | AN39: =AK39
B40: Non-negotiables done | C40: of 9 (8 on non-work days) | E40: =IF(Data!BF97="","",Data!BJ97) | F40: =IF(Data!BF98="","",Data!BJ98) | G40: =IF(Data!BF99="","",Data!BJ99) | H40: =IF(Data!BF100="","",Data!BJ100) | I40: =IF(Data!BF101="","",Data!BJ101) | J40: =IF(Data!BF102="","",Data!BJ102) | K40: =IF(Data!BF103="","",Data!BJ103) | L40: =IF(Data!BF104="","",Data!BJ104) | M40: =IF(Data!BF105="","",Data!BJ105) | N40: =IF(Data!BF106="","",Data!BJ106) | O40: =IF(Data!BF107="","",Data!BJ107) | P40: =IF(Data!BF108="","",Data!BJ108) | Q40: =IF(Data!BF109="","",Data!BJ109) | R40: =IF(Data!BF110="","",Data!BJ110) | S40: =IF(Data!BF111="","",Data!BJ111) | T40: =IF(Data!BF112="","",Data!BJ112) | U40: =IF(Data!BF113="","",Data!BJ113) | V40: =IF(Data!BF114="","",Data!BJ114) | W40: =IF(Data!BF115="","",Data!BJ115) | X40: =IF(Data!BF116="","",Data!BJ116) | Y40: =IF(Data!BF117="","",Data!BJ117) | Z40: =IF(Data!BF118="","",Data!BJ118) | AA40: =IF(Data!BF119="","",Data!BJ119) | AB40: =IF(Data!BF120="","",Data!BJ120) | AC40: =IF(Data!BF121="","",Data!BJ121) | AD40: =IF(Data!BF122="","",Data!BJ122) | AE40: =IF(Data!BF123="","",Data!BJ123) | AF40: =IF(Data!BF124="","",Data!BJ124) | AG40: =IF(Data!BF125="","",Data!BJ125) | AH40: =IF(Data!BF126="","",Data!BJ126) | AI40: =IF(Data!BF127="","",Data!BJ127)
B42: DAILY FOUNDATION SCORE | AK42: WEEKLY AVERAGE
B43: One number for the day, built from 9 things: Sleep · Movement · Protein · Water · Steps · Prayer · Top 3 (work days) · Fiancée · Read/learn M days are scored on the Minimum Viable Day. S days are paused — no score, no guilt. ◆ = part of the Minimum Viable Day
AK44: Week 1 | AM44: =IF(ISNUMBER(AN44),REPT("█",ROUND(MAX(0,MIN(1,AN44))*10,0))&REPT("░",10-ROUND(MAX(0,MIN(1,AN44))*10,0)),"") | AN44: =IFERROR(AVERAGE(E39:K39),"")
AK46: Week 2 | AM46: =IF(ISNUMBER(AN46),REPT("█",ROUND(MAX(0,MIN(1,AN46))*10,0))&REPT("░",10-ROUND(MAX(0,MIN(1,AN46))*10,0)),"") | AN46: =IFERROR(AVERAGE(L39:R39),"")
AK48: Week 3 | AM48: =IF(ISNUMBER(AN48),REPT("█",ROUND(MAX(0,MIN(1,AN48))*10,0))&REPT("░",10-ROUND(MAX(0,MIN(1,AN48))*10,0)),"") | AN48: =IFERROR(AVERAGE(S39:Y39),"")
AK50: Week 4 | AM50: =IF(ISNUMBER(AN50),REPT("█",ROUND(MAX(0,MIN(1,AN50))*10,0))&REPT("░",10-ROUND(MAX(0,MIN(1,AN50))*10,0)),"") | AN50: =IFERROR(AVERAGE(Z39:AF39),"")
AK52: Week 5 | AM52: =IF(ISNUMBER(AN52),REPT("█",ROUND(MAX(0,MIN(1,AN52))*10,0))&REPT("░",10-ROUND(MAX(0,MIN(1,AN52))*10,0)),"") | AN52: =IFERROR(AVERAGE(AG39:AI39),"")
B56: BODY & MIND | E56: Week 1 | L56: Week 2 | S56: Week 3 | Z56: Week 4 | AG56: Week 5 | AK56: ANALYSIS
B57: Log the numbers you have. Blank is fine. | E57: =E6 | F57: =F6 | G57: =G6 | H57: =H6 | I57: =I6 | J57: =J6 | K57: =K6 | L57: =L6 | ... AI57: =AI6 | AK57: Avg | AL57: Target | AM57: Progress | AN57: Hit %
B58: Metric | C58: Unit | D58: Target | E58: =E7 | F58: =F7 | G58: =G7 | H58: =H7 | I58: =I7 | J58: =J7 | K58: =K7 | L58: =L7 | ... AI58: =AI7 | AK58: hit % = days on target ÷ days logged
B59: ⚖️ Weight | C59: kg | D59: AM, 7-day avg | AK59: =IF($AP$11=0,"",INDEX(Data!$BI$4:$BI$375,MATCH($AP$11,Data!$A$4:$A$375,0))) | AL59: 7d avg | AM59: =IF($AP$11=0,"",IFERROR("Δ month "&TEXT(AK59-INDEX(Data!$BI$4:$BI$375,MATCH($AP$12,Data!$A$4:$A$375,0)),"+0.0;-0.0")&" kg",""))
B60: 👣 Steps | C60: steps | D60: adaptive | AK60: =IFERROR(AVERAGE(E60:AI60),"") | AL60: =IFERROR(MAX(E69:AI69)*1000,"") | AM60: =IF(AND(ISNUMBER(AK60),ISNUMBER(AL60)),IF(ISNUMBER(AK60/AL60),REPT("█",ROUND(MAX(0,MIN(1,AK60/AL60))*10,0))&REPT("░",10-ROUND(MAX(0,MIN(1,AK60/AL60))*10,0)),""),"") | AN60: =IFERROR(SUMIFS(Data!$AY$4:$AY$375,Data!$B$4:$B$375,4)/COUNTIFS(Data!$B$4:$B$375,4,Data!$AG$4:$AG$375,">0"),"")
B61: 🍗 Protein | C61: g | D61: 150 g | AK61: =IFERROR(AVERAGE(E61:AI61),"") | AL61: =ProtTarget | AM61: =IF(AND(ISNUMBER(AK61),ISNUMBER(AL61)),IF(ISNUMBER(AK61/AL61),REPT("█",ROUND(MAX(0,MIN(1,AK61/AL61))*10,0))&REPT("░",10-ROUND(MAX(0,MIN(1,AK61/AL61))*10,0)),""),"") | AN61: =IFERROR(SUMIFS(Data!$AW$4:$AW$375,Data!$B$4:$B$375,4)/COUNTIFS(Data!$B$4:$B$375,4,Data!$AH$4:$AH$375,">0"),"")
B62: 💧 Water | C62: L | D62: 2.5–3 L | AK62: =IFERROR(AVERAGE(E62:AI62),"") | AL62: =WaterHit | AM62: =IF(AND(ISNUMBER(AK62),ISNUMBER(AL62)),IF(ISNUMBER(AK62/AL62),REPT("█",ROUND(MAX(0,MIN(1,AK62/AL62))*10,0))&REPT("░",10-ROUND(MAX(0,MIN(1,AK62/AL62))*10,0)),""),"") | AN62: =IFERROR(SUMIFS(Data!$AX$4:$AX$375,Data!$B$4:$B$375,4)/COUNTIFS(Data!$B$4:$B$375,4,Data!$AI$4:$AI$375,">0"),"")
B63: 🔥 Calories | C63: kcal | D63: 1.8–2k | AK63: =IFERROR(AVERAGE(E63:AI63),"") | AL63: =TEXT(KcalMin,"#,##0")&"–"&TEXT(KcalMax,"#,##0") | AM63: =IF(ISNUMBER(AN63),REPT("█",ROUND(MAX(0,MIN(1,AN63))*10,0))&REPT("░",10-ROUND(MAX(0,MIN(1,AN63))*10,0)),"") | AN63: =IFERROR(COUNTIFS(E63:AI63,">="&$AP$7,E63:AI63,"<="&$AP$8)/COUNT(E63:AI63),"")
B64: 🛌 Sleep | C64: hours | D64: 7.5–8.5 h | AK64: =IFERROR(AVERAGE(E64:AI64),"") | AL64: =SleepTarget | AM64: =IF(AND(ISNUMBER(AK64),ISNUMBER(AL64)),IF(ISNUMBER(AK64/AL64),REPT("█",ROUND(MAX(0,MIN(1,AK64/AL64))*10,0))&REPT("░",10-ROUND(MAX(0,MIN(1,AK64/AL64))*10,0)),""),"") | AN64: =IFERROR(COUNTIF(E64:AI64,">="&$AP$4)/COUNT(E64:AI64),"")
B65: ⚡ Energy | C65: 1–10 | D65: 1–10 | AK65: =IFERROR(AVERAGE(E65:AI65),"") | AL65: / 10 | AM65: =IF(ISNUMBER(AK65),IF(ISNUMBER(AK65/10),REPT("█",ROUND(MAX(0,MIN(1,AK65/10))*10,0))&REPT("░",10-ROUND(MAX(0,MIN(1,AK65/10))*10,0)),""),"")
B66: 🌡️ Stress | C66: 1–10 | D66: 1–10 | AK66: =IFERROR(AVERAGE(E66:AI66),"") | AL66: / 10 | AM66: =IF(ISNUMBER(AK66),IF(ISNUMBER(AK66/10),REPT("█",ROUND(MAX(0,MIN(1,AK66/10))*10,0))&REPT("░",10-ROUND(MAX(0,MIN(1,AK66/10))*10,0)),""),"")
B67: 🙂 Mood | C67: 1–10 | D67: 1–10 | AK67: =IFERROR(AVERAGE(E67:AI67),"") | AL67: / 10 | AM67: =IF(ISNUMBER(AK67),IF(ISNUMBER(AK67/10),REPT("█",ROUND(MAX(0,MIN(1,AK67/10))*10,0))&REPT("░",10-ROUND(MAX(0,MIN(1,AK67/10))*10,0)),""),"")
B68: ↳ Weight · 7-day average | C68: decide on this | E68: =Data!BI97 | F68: =Data!BI98 | G68: =Data!BI99 | H68: =Data!BI100 | I68: =Data!BI101 | J68: =Data!BI102 | K68: =Data!BI103 | L68: =Data!BI104 | M68: =Data!BI105 | N68: =Data!BI106 | O68: =Data!BI107 | P68: =Data!BI108 | Q68: =Data!BI109 | R68: =Data!BI110 | S68: =Data!BI111 | T68: =Data!BI112 | U68: =Data!BI113 | V68: =Data!BI114 | W68: =Data!BI115 | X68: =Data!BI116 | Y68: =Data!BI117 | Z68: =Data!BI118 | AA68: =Data!BI119 | AB68: =Data!BI120 | AC68: =Data!BI121 | AD68: =Data!BI122 | AE68: =Data!BI123 | AF68: =Data!BI124 | AG68: =Data!BI125 | AH68: =Data!BI126 | AI68: =Data!BI127
B69: ↳ Steps target (adaptive) | C69: 7k → 8k → 9k | E69: =IF(Data!A97="","",Data!AR97/1000) | F69: =IF(Data!A98="","",Data!AR98/1000) | G69: =IF(Data!A99="","",Data!AR99/1000) | H69: =IF(Data!A100="","",Data!AR100/1000) | I69: =IF(Data!A101="","",Data!AR101/1000) | J69: =IF(Data!A102="","",Data!AR102/1000) | K69: =IF(Data!A103="","",Data!AR103/1000) | L69: =IF(Data!A104="","",Data!AR104/1000) | M69: =IF(Data!A105="","",Data!AR105/1000) | N69: =IF(Data!A106="","",Data!AR106/1000) | O69: =IF(Data!A107="","",Data!AR107/1000) | P69: =IF(Data!A108="","",Data!AR108/1000) | Q69: =IF(Data!A109="","",Data!AR109/1000) | R69: =IF(Data!A110="","",Data!AR110/1000) | S69: =IF(Data!A111="","",Data!AR111/1000) | T69: =IF(Data!A112="","",Data!AR112/1000) | U69: =IF(Data!A113="","",Data!AR113/1000) | V69: =IF(Data!A114="","",Data!AR114/1000) | W69: =IF(Data!A115="","",Data!AR115/1000) | X69: =IF(Data!A116="","",Data!AR116/1000) | Y69: =IF(Data!A117="","",Data!AR117/1000) | Z69: =IF(Data!A118="","",Data!AR118/1000) | AA69: =IF(Data!A119="","",Data!AR119/1000) | AB69: =IF(Data!A120="","",Data!AR120/1000) | AC69: =IF(Data!A121="","",Data!AR121/1000) | AD69: =IF(Data!A122="","",Data!AR122/1000) | AE69: =IF(Data!A123="","",Data!AR123/1000) | AF69: =IF(Data!A124="","",Data!AR124/1000) | AG69: =IF(Data!A125="","",Data!AR125/1000) | AH69: =IF(Data!A126="","",Data!AR126/1000) | AI69: =IF(Data!A127="","",Data!AR127/1000)
B71: TRENDS | E71: MIND & RECOVERY · energy · stress · mood | U71: WEIGHT · daily vs 7-day average
B72: Energy, stress and mood show how the month feels, not just what got done. Weight: the dots jump around with water and salt. The 7-day average is the only line that decides anything. Target pace: −0.4 to −0.8 kg a week.

Sheet Feb 2027
AP1: =DATE(2027,2,1)
B2: =UPPER(TEXT($AP$1,"mmmm")) | E2: HABITS | L2: CHECK-INS | S2: FOUNDATION · MONTH | AC2: ROLLING 7-DAY | AK2: ROLLING 30-DAY | AP2: =ProtHit
B3: ="— Life OS · Habit Tracker · "&YEAR($AP$1)&" —" | E3: =COUNTA(B10:B18,B20:B32,B34:B37) | L3: =COUNTIF(E10:AI18,TRUE)+COUNTIF(E10:AI18,"x")+COUNTIF(E20:AI32,TRUE)+COUNTIF(E20:AI32,"x")+COUNTIF(E34:AI37,TRUE)+COUNTIF(E34:AI37,"x") | S3: =IF(ISNUMBER(AK39),TEXT(AK39,"0%")&" "&IF(ISNUMBER(AK39),REPT("█",ROUND(MAX(0,MIN(1,AK39))*12,0))&REPT("░",12-ROUND(MAX(0,MIN(1,AK39))*12,0)),""),"—") | AC3: =IF(ISNUMBER(IFERROR(INDEX(Data!$BG$4:$BG$375,MATCH($AP$13,Data!$A$4:$A$375,0)),"")),TEXT(IFERROR(INDEX(Data!$BG$4:$BG$375,MATCH($AP$13,Data!$A$4:$A$375,0)),""),"0%")&" · "&IF(NOT(ISNUMBER(IFERROR(INDEX(Data!$BG$4:$BG$375,MATCH($AP$13,Data!$A$4:$A$375,0)),""))),"—",IF(IFERROR(INDEX(Data!$BG$4:$BG$375,MATCH($AP$13,Data!$A$4:$A$375,0)),"")>=Band1,"GREEN",IF(IFERROR(INDEX(Data!$BG$4:$BG$375,MATCH($AP$13,Data!$A$4:$A$375,0)),"")>=Band2,"GOOD",IF(IFERROR(INDEX(Data!$BG$4:$BG$375,MATCH($AP$13,Data!$A$4:$A$375,0)),"")>=Band3,"NEEDS ATTENTION","RESET")))),"—") | AK3: =IF(ISNUMBER(IFERROR(INDEX(Data!$BH$4:$BH$375,MATCH($AP$13,Data!$A$4:$A$375,0)),"")),TEXT(IFERROR(INDEX(Data!$BH$4:$BH$375,MATCH($AP$13,Data!$A$4:$A$375,0)),""),"0%")&" · "&IF(NOT(ISNUMBER(IFERROR(INDEX(Data!$BH$4:$BH$375,MATCH($AP$13,Data!$A$4:$A$375,0)),""))),"—",IF(IFERROR(INDEX(Data!$BH$4:$BH$375,MATCH($AP$13,Data!$A$4:$A$375,0)),"")>=Band1,"GREEN",IF(IFERROR(INDEX(Data!$BH$4:$BH$375,MATCH($AP$13,Data!$A$4:$A$375,0)),"")>=Band2,"GOOD",IF(IFERROR(INDEX(Data!$BH$4:$BH$375,MATCH($AP$13,Data!$A$4:$A$375,0)),"")>=Band3,"NEEDS ATTENTION","RESET")))),"—") | AP3: =WaterHit
AP4: =SleepMin
B5: MY HABITS | E5: Week 1 | L5: Week 2 | S5: Week 3 | Z5: Week 4 | AG5: Week 5 | AK5: ANALYSIS | AP5: =SleepLow
B6: Tick what you did. Missed is data, not failure. | E6: =IF(E7="","",LEFT(TEXT(E7,"ddd"),2)) | F6: =IF(F7="","",LEFT(TEXT(F7,"ddd"),2)) | G6: =IF(G7="","",LEFT(TEXT(G7,"ddd"),2)) | H6: =IF(H7="","",LEFT(TEXT(H7,"ddd"),2)) | I6: =IF(I7="","",LEFT(TEXT(I7,"ddd"),2)) | J6: =IF(J7="","",LEFT(TEXT(J7,"ddd"),2)) | K6: =IF(K7="","",LEFT(TEXT(K7,"ddd"),2)) | L6: =IF(L7="","",LEFT(TEXT(L7,"ddd"),2)) | ... AI6: =IF(AI7="","",LEFT(TEXT(AI7,"ddd"),2)) | AK6: Done | AL6: Goal | AM6: Progress | AN6: % | AP6: =TODAY()
B7: Habit | C7: Pillar | D7: Target | E7: =IF(1<=DAY(EOMONTH($AP$1,0)),$AP$1+0,"") | F7: =IF(2<=DAY(EOMONTH($AP$1,0)),$AP$1+1,"") | G7: =IF(3<=DAY(EOMONTH($AP$1,0)),$AP$1+2,"") | H7: =IF(4<=DAY(EOMONTH($AP$1,0)),$AP$1+3,"") | I7: =IF(5<=DAY(EOMONTH($AP$1,0)),$AP$1+4,"") | J7: =IF(6<=DAY(EOMONTH($AP$1,0)),$AP$1+5,"") | K7: =IF(7<=DAY(EOMONTH($AP$1,0)),$AP$1+6,"") | L7: =IF(8<=DAY(EOMONTH($AP$1,0)),$AP$1+7,"") | M7: =IF(9<=DAY(EOMONTH($AP$1,0)),$AP$1+8,"") | N7: =IF(10<=DAY(EOMONTH($AP$1,0)),$AP$1+9,"") | O7: =IF(11<=DAY(EOMONTH($AP$1,0)),$AP$1+10,"") | P7: =IF(12<=DAY(EOMONTH($AP$1,0)),$AP$1+11,"") | Q7: =IF(13<=DAY(EOMONTH($AP$1,0)),$AP$1+12,"") | R7: =IF(14<=DAY(EOMONTH($AP$1,0)),$AP$1+13,"") | S7: =IF(15<=DAY(EOMONTH($AP$1,0)),$AP$1+14,"") | T7: =IF(16<=DAY(EOMONTH($AP$1,0)),$AP$1+15,"") | U7: =IF(17<=DAY(EOMONTH($AP$1,0)),$AP$1+16,"") | V7: =IF(18<=DAY(EOMONTH($AP$1,0)),$AP$1+17,"") | W7: =IF(19<=DAY(EOMONTH($AP$1,0)),$AP$1+18,"") | X7: =IF(20<=DAY(EOMONTH($AP$1,0)),$AP$1+19,"") | Y7: =IF(21<=DAY(EOMONTH($AP$1,0)),$AP$1+20,"") | Z7: =IF(22<=DAY(EOMONTH($AP$1,0)),$AP$1+21,"") | AA7: =IF(23<=DAY(EOMONTH($AP$1,0)),$AP$1+22,"") | AB7: =IF(24<=DAY(EOMONTH($AP$1,0)),$AP$1+23,"") | AC7: =IF(25<=DAY(EOMONTH($AP$1,0)),$AP$1+24,"") | AD7: =IF(26<=DAY(EOMONTH($AP$1,0)),$AP$1+25,"") | AE7: =IF(27<=DAY(EOMONTH($AP$1,0)),$AP$1+26,"") | AF7: =IF(28<=DAY(EOMONTH($AP$1,0)),$AP$1+27,"") | AG7: =IF(29<=DAY(EOMONTH($AP$1,0)),$AP$1+28,"") | AH7: =IF(30<=DAY(EOMONTH($AP$1,0)),$AP$1+29,"") | AI7: =IF(31<=DAY(EOMONTH($AP$1,0)),$AP$1+30,"") | AK7: goal = weekly target × days tracked | AP7: =KcalMin
B8: Day mode | C8: M = minimum · S = sick · R = rest | AK8: =COUNTIF(E8:AI8,"M")&" min · "&COUNTIF(E8:AI8,"S")&" sick · "&COUNTIF(E8:AI8,"R")&" rest" | AP8: =KcalMax
B9: LEVEL 1 · NON-NEGOTIABLES | AK9: the daily foundation | AP9: =COUNTIFS(Data!$B$4:$B$375,5,Data!$AO$4:$AO$375,1,Data!$E$4:$E$375,"<>S")
B10: 🌅 Morning reset | C10: HEALTH | D10: Daily | AK10: =COUNTIF(E10:AI10,TRUE)+COUNTIF(E10:AI10,"x") | AL10: =ROUND($AP$9*7/7,0) | AM10: =IF(ISNUMBER(AN10),REPT("█",ROUND(MAX(0,MIN(1,AN10))*10,0))&REPT("░",10-ROUND(MAX(0,MIN(1,AN10))*10,0)),"") | AN10: =IF(N(AL10)=0,"",MIN(1,AK10/AL10)) | AP10: =COUNTIFS(Data!$B$4:$B$375,5,Data!$AO$4:$AO$375,1,Data!$E$4:$E$375,"<>S",Data!$AS$4:$AS$375,1)
B11: 🙏 Prayer + Scripture ◆ | C11: SPIRIT | D11: Daily | AK11: =COUNTIF(E11:AI11,TRUE)+COUNTIF(E11:AI11,"x") | AL11: =ROUND($AP$9*7/7,0) | AM11: =IF(ISNUMBER(AN11),REPT("█",ROUND(MAX(0,MIN(1,AN11))*10,0))&REPT("░",10-ROUND(MAX(0,MIN(1,AN11))*10,0)),"") | AN11: =IF(N(AL11)=0,"",MIN(1,AK11/AL11)) | AP11: =_xlfn.MAXIFS(Data!$A$4:$A$375,Data!$B$4:$B$375,5,Data!$AF$4:$AF$375,">0")
B12: 🧘 Mobility & posture ◆ | C12: POSTURE | D12: Daily | AK12: =COUNTIF(E12:AI12,TRUE)+COUNTIF(E12:AI12,"x") | AL12: =ROUND($AP$9*7/7,0) | AM12: =IF(ISNUMBER(AN12),REPT("█",ROUND(MAX(0,MIN(1,AN12))*10,0))&REPT("░",10-ROUND(MAX(0,MIN(1,AN12))*10,0)),"") | AN12: =IF(N(AL12)=0,"",MIN(1,AK12/AL12)) | AP12: =_xlfn.MINIFS(Data!$A$4:$A$375,Data!$B$4:$B$375,5,Data!$AF$4:$AF$375,">0")
B13: 💪 Training / movement ◆ | C13: BODY | D13: Daily | AK13: =COUNTIF(E13:AI13,TRUE)+COUNTIF(E13:AI13,"x") | AL13: =ROUND($AP$9*7/7,0) | AM13: =IF(ISNUMBER(AN13),REPT("█",ROUND(MAX(0,MIN(1,AN13))*10,0))&REPT("░",10-ROUND(MAX(0,MIN(1,AN13))*10,0)),"") | AN13: =IF(N(AL13)=0,"",MIN(1,AK13/AL13)) | AP13: =MIN(AP6,EOMONTH(AP1,0))
B14: 🎯 Top 3 priorities | C14: WORK | D14: 5× / wk | AK14: =COUNTIF(E14:AI14,TRUE)+COUNTIF(E14:AI14,"x") | AL14: =$AP$10 | AM14: =IF(ISNUMBER(AN14),REPT("█",ROUND(MAX(0,MIN(1,AN14))*10,0))&REPT("░",10-ROUND(MAX(0,MIN(1,AN14))*10,0)),"") | AN14: =IF(N(AL14)=0,"",MIN(1,AK14/AL14))
B15: ❤️ Fiancée time ◆ | C15: RELATIONSHIPS | D15: Daily | AK15: =COUNTIF(E15:AI15,TRUE)+COUNTIF(E15:AI15,"x") | AL15: =ROUND($AP$9*7/7,0) | AM15: =IF(ISNUMBER(AN15),REPT("█",ROUND(MAX(0,MIN(1,AN15))*10,0))&REPT("░",10-ROUND(MAX(0,MIN(1,AN15))*10,0)),"") | AN15: =IF(N(AL15)=0,"",MIN(1,AK15/AL15))
B16: 📖 Read / learn | C16: MIND | D16: Daily | AK16: =COUNTIF(E16:AI16,TRUE)+COUNTIF(E16:AI16,"x") | AL16: =ROUND($AP$9*7/7,0) | AM16: =IF(ISNUMBER(AN16),REPT("█",ROUND(MAX(0,MIN(1,AN16))*10,0))&REPT("░",10-ROUND(MAX(0,MIN(1,AN16))*10,0)),"") | AN16: =IF(N(AL16)=0,"",MIN(1,AK16/AL16))
B17: 🌙 Evening shutdown | C17: WORK | D17: Daily | AK17: =COUNTIF(E17:AI17,TRUE)+COUNTIF(E17:AI17,"x") | AL17: =ROUND($AP$9*7/7,0) | AM17: =IF(ISNUMBER(AN17),REPT("█",ROUND(MAX(0,MIN(1,AN17))*10,0))&REPT("░",10-ROUND(MAX(0,MIN(1,AN17))*10,0)),"") | AN17: =IF(N(AL17)=0,"",MIN(1,AK17/AL17))
B18: 😴 Lights out 22:00 ◆ | C18: HEALTH | D18: Daily | AK18: =COUNTIF(E18:AI18,TRUE)+COUNTIF(E18:AI18,"x") | AL18: =ROUND($AP$9*7/7,0) | AM18: =IF(ISNUMBER(AN18),REPT("█",ROUND(MAX(0,MIN(1,AN18))*10,0))&REPT("░",10-ROUND(MAX(0,MIN(1,AN18))*10,0)),"") | AN18: =IF(N(AL18)=0,"",MIN(1,AK18/AL18))
B19: LEVEL 2 · HIGH VALUE | AK19: weekly targets
B20: 🏋️ Strength session | C20: BODY | D20: 4× / wk | AK20: =COUNTIF(E20:AI20,TRUE)+COUNTIF(E20:AI20,"x") | AL20: =ROUND($AP$9*4/7,0) | AM20: =IF(ISNUMBER(AN20),REPT("█",ROUND(MAX(0,MIN(1,AN20))*10,0))&REPT("░",10-ROUND(MAX(0,MIN(1,AN20))*10,0)),"") | AN20: =IF(N(AL20)=0,"",MIN(1,AK20/AL20))
B21: 📈 Progression achieved | C21: BODY | D21: 4× / wk | AK21: =COUNTIF(E21:AI21,TRUE)+COUNTIF(E21:AI21,"x") | AL21: =ROUND($AP$9*4/7,0) | AM21: =IF(ISNUMBER(AN21),REPT("█",ROUND(MAX(0,MIN(1,AN21))*10,0))&REPT("░",10-ROUND(MAX(0,MIN(1,AN21))*10,0)),"") | AN21: =IF(N(AL21)=0,"",MIN(1,AK21/AL21))
B22: 🧱 Core | C22: BODY | D22: 3× / wk | AK22: =COUNTIF(E22:AI22,TRUE)+COUNTIF(E22:AI22,"x") | AL22: =ROUND($AP$9*3/7,0) | AM22: =IF(ISNUMBER(AN22),REPT("█",ROUND(MAX(0,MIN(1,AN22))*10,0))&REPT("░",10-ROUND(MAX(0,MIN(1,AN22))*10,0)),"") | AN22: =IF(N(AL22)=0,"",MIN(1,AK22/AL22))
B23: 🦵 Calves | C23: BODY | D23: 3× / wk | AK23: =COUNTIF(E23:AI23,TRUE)+COUNTIF(E23:AI23,"x") | AL23: =ROUND($AP$9*3/7,0) | AM23: =IF(ISNUMBER(AN23),REPT("█",ROUND(MAX(0,MIN(1,AN23))*10,0))&REPT("░",10-ROUND(MAX(0,MIN(1,AN23))*10,0)),"") | AN23: =IF(N(AL23)=0,"",MIN(1,AK23/AL23))
B24: 🚶 Cardio | C24: BODY | D24: 2× / wk | AK24: =COUNTIF(E24:AI24,TRUE)+COUNTIF(E24:AI24,"x") | AL24: =ROUND($AP$9*2/7,0) | AM24: =IF(ISNUMBER(AN24),REPT("█",ROUND(MAX(0,MIN(1,AN24))*10,0))&REPT("░",10-ROUND(MAX(0,MIN(1,AN24))*10,0)),"") | AN24: =IF(N(AL24)=0,"",MIN(1,AK24/AL24))
B25: 🧠 Deep work 2+ blocks | C25: WORK | D25: 5× / wk | AK25: =COUNTIF(E25:AI25,TRUE)+COUNTIF(E25:AI25,"x") | AL25: =ROUND($AP$9*5/7,0) | AM25: =IF(ISNUMBER(AN25),REPT("█",ROUND(MAX(0,MIN(1,AN25))*10,0))&REPT("░",10-ROUND(MAX(0,MIN(1,AN25))*10,0)),"") | AN25: =IF(N(AL25)=0,"",MIN(1,AK25/AL25))
B26: 👀 Posture & eye breaks | C26: POSTURE | D26: 5× / wk | AK26: =COUNTIF(E26:AI26,TRUE)+COUNTIF(E26:AI26,"x") | AL26: =ROUND($AP$9*5/7,0) | AM26: =IF(ISNUMBER(AN26),REPT("█",ROUND(MAX(0,MIN(1,AN26))*10,0))&REPT("░",10-ROUND(MAX(0,MIN(1,AN26))*10,0)),"") | AN26: =IF(N(AL26)=0,"",MIN(1,AK26/AL26))
B27: 🧹 Home reset | C27: LIFE ADMIN | D27: 5× / wk | AK27: =COUNTIF(E27:AI27,TRUE)+COUNTIF(E27:AI27,"x") | AL27: =ROUND($AP$9*5/7,0) | AM27: =IF(ISNUMBER(AN27),REPT("█",ROUND(MAX(0,MIN(1,AN27))*10,0))&REPT("░",10-ROUND(MAX(0,MIN(1,AN27))*10,0)),"") | AN27: =IF(N(AL27)=0,"",MIN(1,AK27/AL27))
B28: 👦 Father–son time | C28: RELATIONSHIPS | D28: 1× / wk | AK28: =COUNTIF(E28:AI28,TRUE)+COUNTIF(E28:AI28,"x") | AL28: =ROUND($AP$9*1/7,0) | AM28: =IF(ISNUMBER(AN28),REPT("█",ROUND(MAX(0,MIN(1,AN28))*10,0))&REPT("░",10-ROUND(MAX(0,MIN(1,AN28))*10,0)),"") | AN28: =IF(N(AL28)=0,"",MIN(1,AK28/AL28))
B29: 🥂 Couple time / date | C29: RELATIONSHIPS | D29: 1× / wk | AK29: =COUNTIF(E29:AI29,TRUE)+COUNTIF(E29:AI29,"x") | AL29: =ROUND($AP$9*1/7,0) | AM29: =IF(ISNUMBER(AN29),REPT("█",ROUND(MAX(0,MIN(1,AN29))*10,0))&REPT("░",10-ROUND(MAX(0,MIN(1,AN29))*10,0)),"") | AN29: =IF(N(AL29)=0,"",MIN(1,AK29/AL29))
B30: 📞 Family check-in | C30: RELATIONSHIPS | D30: 1× / wk | AK30: =COUNTIF(E30:AI30,TRUE)+COUNTIF(E30:AI30,"x") | AL30: =ROUND($AP$9*1/7,0) | AM30: =IF(ISNUMBER(AN30),REPT("█",ROUND(MAX(0,MIN(1,AN30))*10,0))&REPT("░",10-ROUND(MAX(0,MIN(1,AN30))*10,0)),"") | AN30: =IF(N(AL30)=0,"",MIN(1,AK30/AL30))
B31: ⛪ Church / worship | C31: SPIRIT | D31: 1× / wk | AK31: =COUNTIF(E31:AI31,TRUE)+COUNTIF(E31:AI31,"x") | AL31: =ROUND($AP$9*1/7,0) | AM31: =IF(ISNUMBER(AN31),REPT("█",ROUND(MAX(0,MIN(1,AN31))*10,0))&REPT("░",10-ROUND(MAX(0,MIN(1,AN31))*10,0)),"") | AN31: =IF(N(AL31)=0,"",MIN(1,AK31/AL31))
B32: 🍱 Meal prep | C32: LIFE ADMIN | D32: 1× / wk | AK32: =COUNTIF(E32:AI32,TRUE)+COUNTIF(E32:AI32,"x") | AL32: =ROUND($AP$9*1/7,0) | AM32: =IF(ISNUMBER(AN32),REPT("█",ROUND(MAX(0,MIN(1,AN32))*10,0))&REPT("░",10-ROUND(MAX(0,MIN(1,AN32))*10,0)),"") | AN32: =IF(N(AL32)=0,"",MIN(1,AK32/AL32))
B33: LEVEL 3 · OPTIONAL | AK33: bonus, never guilt
B34: 🕊️ Meditation / journal | C34: MIND | D34: Optional | AK34: =COUNTIF(E34:AI34,TRUE)+COUNTIF(E34:AI34,"x") | AL34: — | AM34: =IF(AK34=0,"",AK34&" × bonus")
B35: ➕ Extra walk / cardio | C35: BODY | D35: Optional | AK35: =COUNTIF(E35:AI35,TRUE)+COUNTIF(E35:AI35,"x") | AL35: — | AM35: =IF(AK35=0,"",AK35&" × bonus")
B36: ➕ Extra mobility | C36: POSTURE | D36: Optional | AK36: =COUNTIF(E36:AI36,TRUE)+COUNTIF(E36:AI36,"x") | AL36: — | AM36: =IF(AK36=0,"",AK36&" × bonus")
B37: ➕ Extra reading | C37: MIND | D37: Optional | AK37: =COUNTIF(E37:AI37,TRUE)+COUNTIF(E37:AI37,"x") | AL37: — | AM37: =IF(AK37=0,"",AK37&" × bonus")
B39: Foundation score | C39: auto · 9 pillars of the day | E39: =Data!BF128 | F39: =Data!BF129 | G39: =Data!BF130 | H39: =Data!BF131 | I39: =Data!BF132 | J39: =Data!BF133 | K39: =Data!BF134 | L39: =Data!BF135 | M39: =Data!BF136 | N39: =Data!BF137 | O39: =Data!BF138 | P39: =Data!BF139 | Q39: =Data!BF140 | R39: =Data!BF141 | S39: =Data!BF142 | T39: =Data!BF143 | U39: =Data!BF144 | V39: =Data!BF145 | W39: =Data!BF146 | X39: =Data!BF147 | Y39: =Data!BF148 | Z39: =Data!BF149 | AA39: =Data!BF150 | AB39: =Data!BF151 | AC39: =Data!BF152 | AD39: =Data!BF153 | AE39: =Data!BF154 | AF39: =Data!BF155 | AG39: =Data!BF156 | AH39: =Data!BF157 | AI39: =Data!BF158 | AK39: =IFERROR(AVERAGE(E39:AI39),"") | AL39: avg | AM39: =IF(ISNUMBER(AN39),REPT("█",ROUND(MAX(0,MIN(1,AN39))*10,0))&REPT("░",10-ROUND(MAX(0,MIN(1,AN39))*10,0)),"") | AN39: =AK39
B40: Non-negotiables done | C40: of 9 (8 on non-work days) | E40: =IF(Data!BF128="","",Data!BJ128) | F40: =IF(Data!BF129="","",Data!BJ129) | G40: =IF(Data!BF130="","",Data!BJ130) | H40: =IF(Data!BF131="","",Data!BJ131) | I40: =IF(Data!BF132="","",Data!BJ132) | J40: =IF(Data!BF133="","",Data!BJ133) | K40: =IF(Data!BF134="","",Data!BJ134) | L40: =IF(Data!BF135="","",Data!BJ135) | M40: =IF(Data!BF136="","",Data!BJ136) | N40: =IF(Data!BF137="","",Data!BJ137) | O40: =IF(Data!BF138="","",Data!BJ138) | P40: =IF(Data!BF139="","",Data!BJ139) | Q40: =IF(Data!BF140="","",Data!BJ140) | R40: =IF(Data!BF141="","",Data!BJ141) | S40: =IF(Data!BF142="","",Data!BJ142) | T40: =IF(Data!BF143="","",Data!BJ143) | U40: =IF(Data!BF144="","",Data!BJ144) | V40: =IF(Data!BF145="","",Data!BJ145) | W40: =IF(Data!BF146="","",Data!BJ146) | X40: =IF(Data!BF147="","",Data!BJ147) | Y40: =IF(Data!BF148="","",Data!BJ148) | Z40: =IF(Data!BF149="","",Data!BJ149) | AA40: =IF(Data!BF150="","",Data!BJ150) | AB40: =IF(Data!BF151="","",Data!BJ151) | AC40: =IF(Data!BF152="","",Data!BJ152) | AD40: =IF(Data!BF153="","",Data!BJ153) | AE40: =IF(Data!BF154="","",Data!BJ154) | AF40: =IF(Data!BF155="","",Data!BJ155) | AG40: =IF(Data!BF156="","",Data!BJ156) | AH40: =IF(Data!BF157="","",Data!BJ157) | AI40: =IF(Data!BF158="","",Data!BJ158)
B42: DAILY FOUNDATION SCORE | AK42: WEEKLY AVERAGE
B43: One number for the day, built from 9 things: Sleep · Movement · Protein · Water · Steps · Prayer · Top 3 (work days) · Fiancée · Read/learn M days are scored on the Minimum Viable Day. S days are paused — no score, no guilt. ◆ = part of the Minimum Viable Day
AK44: Week 1 | AM44: =IF(ISNUMBER(AN44),REPT("█",ROUND(MAX(0,MIN(1,AN44))*10,0))&REPT("░",10-ROUND(MAX(0,MIN(1,AN44))*10,0)),"") | AN44: =IFERROR(AVERAGE(E39:K39),"")
AK46: Week 2 | AM46: =IF(ISNUMBER(AN46),REPT("█",ROUND(MAX(0,MIN(1,AN46))*10,0))&REPT("░",10-ROUND(MAX(0,MIN(1,AN46))*10,0)),"") | AN46: =IFERROR(AVERAGE(L39:R39),"")
AK48: Week 3 | AM48: =IF(ISNUMBER(AN48),REPT("█",ROUND(MAX(0,MIN(1,AN48))*10,0))&REPT("░",10-ROUND(MAX(0,MIN(1,AN48))*10,0)),"") | AN48: =IFERROR(AVERAGE(S39:Y39),"")
AK50: Week 4 | AM50: =IF(ISNUMBER(AN50),REPT("█",ROUND(MAX(0,MIN(1,AN50))*10,0))&REPT("░",10-ROUND(MAX(0,MIN(1,AN50))*10,0)),"") | AN50: =IFERROR(AVERAGE(Z39:AF39),"")
AK52: Week 5 | AM52: =IF(ISNUMBER(AN52),REPT("█",ROUND(MAX(0,MIN(1,AN52))*10,0))&REPT("░",10-ROUND(MAX(0,MIN(1,AN52))*10,0)),"") | AN52: =IFERROR(AVERAGE(AG39:AI39),"")
B56: BODY & MIND | E56: Week 1 | L56: Week 2 | S56: Week 3 | Z56: Week 4 | AG56: Week 5 | AK56: ANALYSIS
B57: Log the numbers you have. Blank is fine. | E57: =E6 | F57: =F6 | G57: =G6 | H57: =H6 | I57: =I6 | J57: =J6 | K57: =K6 | L57: =L6 | ... AI57: =AI6 | AK57: Avg | AL57: Target | AM57: Progress | AN57: Hit %
B58: Metric | C58: Unit | D58: Target | E58: =E7 | F58: =F7 | G58: =G7 | H58: =H7 | I58: =I7 | J58: =J7 | K58: =K7 | L58: =L7 | ... AI58: =AI7 | AK58: hit % = days on target ÷ days logged
B59: ⚖️ Weight | C59: kg | D59: AM, 7-day avg | AK59: =IF($AP$11=0,"",INDEX(Data!$BI$4:$BI$375,MATCH($AP$11,Data!$A$4:$A$375,0))) | AL59: 7d avg | AM59: =IF($AP$11=0,"",IFERROR("Δ month "&TEXT(AK59-INDEX(Data!$BI$4:$BI$375,MATCH($AP$12,Data!$A$4:$A$375,0)),"+0.0;-0.0")&" kg",""))
B60: 👣 Steps | C60: steps | D60: adaptive | AK60: =IFERROR(AVERAGE(E60:AI60),"") | AL60: =IFERROR(MAX(E69:AI69)*1000,"") | AM60: =IF(AND(ISNUMBER(AK60),ISNUMBER(AL60)),IF(ISNUMBER(AK60/AL60),REPT("█",ROUND(MAX(0,MIN(1,AK60/AL60))*10,0))&REPT("░",10-ROUND(MAX(0,MIN(1,AK60/AL60))*10,0)),""),"") | AN60: =IFERROR(SUMIFS(Data!$AY$4:$AY$375,Data!$B$4:$B$375,5)/COUNTIFS(Data!$B$4:$B$375,5,Data!$AG$4:$AG$375,">0"),"")
B61: 🍗 Protein | C61: g | D61: 150 g | AK61: =IFERROR(AVERAGE(E61:AI61),"") | AL61: =ProtTarget | AM61: =IF(AND(ISNUMBER(AK61),ISNUMBER(AL61)),IF(ISNUMBER(AK61/AL61),REPT("█",ROUND(MAX(0,MIN(1,AK61/AL61))*10,0))&REPT("░",10-ROUND(MAX(0,MIN(1,AK61/AL61))*10,0)),""),"") | AN61: =IFERROR(SUMIFS(Data!$AW$4:$AW$375,Data!$B$4:$B$375,5)/COUNTIFS(Data!$B$4:$B$375,5,Data!$AH$4:$AH$375,">0"),"")
B62: 💧 Water | C62: L | D62: 2.5–3 L | AK62: =IFERROR(AVERAGE(E62:AI62),"") | AL62: =WaterHit | AM62: =IF(AND(ISNUMBER(AK62),ISNUMBER(AL62)),IF(ISNUMBER(AK62/AL62),REPT("█",ROUND(MAX(0,MIN(1,AK62/AL62))*10,0))&REPT("░",10-ROUND(MAX(0,MIN(1,AK62/AL62))*10,0)),""),"") | AN62: =IFERROR(SUMIFS(Data!$AX$4:$AX$375,Data!$B$4:$B$375,5)/COUNTIFS(Data!$B$4:$B$375,5,Data!$AI$4:$AI$375,">0"),"")
B63: 🔥 Calories | C63: kcal | D63: 1.8–2k | AK63: =IFERROR(AVERAGE(E63:AI63),"") | AL63: =TEXT(KcalMin,"#,##0")&"–"&TEXT(KcalMax,"#,##0") | AM63: =IF(ISNUMBER(AN63),REPT("█",ROUND(MAX(0,MIN(1,AN63))*10,0))&REPT("░",10-ROUND(MAX(0,MIN(1,AN63))*10,0)),"") | AN63: =IFERROR(COUNTIFS(E63:AI63,">="&$AP$7,E63:AI63,"<="&$AP$8)/COUNT(E63:AI63),"")
B64: 🛌 Sleep | C64: hours | D64: 7.5–8.5 h | AK64: =IFERROR(AVERAGE(E64:AI64),"") | AL64: =SleepTarget | AM64: =IF(AND(ISNUMBER(AK64),ISNUMBER(AL64)),IF(ISNUMBER(AK64/AL64),REPT("█",ROUND(MAX(0,MIN(1,AK64/AL64))*10,0))&REPT("░",10-ROUND(MAX(0,MIN(1,AK64/AL64))*10,0)),""),"") | AN64: =IFERROR(COUNTIF(E64:AI64,">="&$AP$4)/COUNT(E64:AI64),"")
B65: ⚡ Energy | C65: 1–10 | D65: 1–10 | AK65: =IFERROR(AVERAGE(E65:AI65),"") | AL65: / 10 | AM65: =IF(ISNUMBER(AK65),IF(ISNUMBER(AK65/10),REPT("█",ROUND(MAX(0,MIN(1,AK65/10))*10,0))&REPT("░",10-ROUND(MAX(0,MIN(1,AK65/10))*10,0)),""),"")
B66: 🌡️ Stress | C66: 1–10 | D66: 1–10 | AK66: =IFERROR(AVERAGE(E66:AI66),"") | AL66: / 10 | AM66: =IF(ISNUMBER(AK66),IF(ISNUMBER(AK66/10),REPT("█",ROUND(MAX(0,MIN(1,AK66/10))*10,0))&REPT("░",10-ROUND(MAX(0,MIN(1,AK66/10))*10,0)),""),"")
B67: 🙂 Mood | C67: 1–10 | D67: 1–10 | AK67: =IFERROR(AVERAGE(E67:AI67),"") | AL67: / 10 | AM67: =IF(ISNUMBER(AK67),IF(ISNUMBER(AK67/10),REPT("█",ROUND(MAX(0,MIN(1,AK67/10))*10,0))&REPT("░",10-ROUND(MAX(0,MIN(1,AK67/10))*10,0)),""),"")
B68: ↳ Weight · 7-day average | C68: decide on this | E68: =Data!BI128 | F68: =Data!BI129 | G68: =Data!BI130 | H68: =Data!BI131 | I68: =Data!BI132 | J68: =Data!BI133 | K68: =Data!BI134 | L68: =Data!BI135 | M68: =Data!BI136 | N68: =Data!BI137 | O68: =Data!BI138 | P68: =Data!BI139 | Q68: =Data!BI140 | R68: =Data!BI141 | S68: =Data!BI142 | T68: =Data!BI143 | U68: =Data!BI144 | V68: =Data!BI145 | W68: =Data!BI146 | X68: =Data!BI147 | Y68: =Data!BI148 | Z68: =Data!BI149 | AA68: =Data!BI150 | AB68: =Data!BI151 | AC68: =Data!BI152 | AD68: =Data!BI153 | AE68: =Data!BI154 | AF68: =Data!BI155 | AG68: =Data!BI156 | AH68: =Data!BI157 | AI68: =Data!BI158
B69: ↳ Steps target (adaptive) | C69: 7k → 8k → 9k | E69: =IF(Data!A128="","",Data!AR128/1000) | F69: =IF(Data!A129="","",Data!AR129/1000) | G69: =IF(Data!A130="","",Data!AR130/1000) | H69: =IF(Data!A131="","",Data!AR131/1000) | I69: =IF(Data!A132="","",Data!AR132/1000) | J69: =IF(Data!A133="","",Data!AR133/1000) | K69: =IF(Data!A134="","",Data!AR134/1000) | L69: =IF(Data!A135="","",Data!AR135/1000) | M69: =IF(Data!A136="","",Data!AR136/1000) | N69: =IF(Data!A137="","",Data!AR137/1000) | O69: =IF(Data!A138="","",Data!AR138/1000) | P69: =IF(Data!A139="","",Data!AR139/1000) | Q69: =IF(Data!A140="","",Data!AR140/1000) | R69: =IF(Data!A141="","",Data!AR141/1000) | S69: =IF(Data!A142="","",Data!AR142/1000) | T69: =IF(Data!A143="","",Data!AR143/1000) | U69: =IF(Data!A144="","",Data!AR144/1000) | V69: =IF(Data!A145="","",Data!AR145/1000) | W69: =IF(Data!A146="","",Data!AR146/1000) | X69: =IF(Data!A147="","",Data!AR147/1000) | Y69: =IF(Data!A148="","",Data!AR148/1000) | Z69: =IF(Data!A149="","",Data!AR149/1000) | AA69: =IF(Data!A150="","",Data!AR150/1000) | AB69: =IF(Data!A151="","",Data!AR151/1000) | AC69: =IF(Data!A152="","",Data!AR152/1000) | AD69: =IF(Data!A153="","",Data!AR153/1000) | AE69: =IF(Data!A154="","",Data!AR154/1000) | AF69: =IF(Data!A155="","",Data!AR155/1000) | AG69: =IF(Data!A156="","",Data!AR156/1000) | AH69: =IF(Data!A157="","",Data!AR157/1000) | AI69: =IF(Data!A158="","",Data!AR158/1000)
B71: TRENDS | E71: MIND & RECOVERY · energy · stress · mood | U71: WEIGHT · daily vs 7-day average
B72: Energy, stress and mood show how the month feels, not just what got done. Weight: the dots jump around with water and salt. The 7-day average is the only line that decides anything. Target pace: −0.4 to −0.8 kg a week.

Sheet Mar 2027
AP1: =DATE(2027,3,1)
B2: =UPPER(TEXT($AP$1,"mmmm")) | E2: HABITS | L2: CHECK-INS | S2: FOUNDATION · MONTH | AC2: ROLLING 7-DAY | AK2: ROLLING 30-DAY | AP2: =ProtHit
B3: ="— Life OS · Habit Tracker · "&YEAR($AP$1)&" —" | E3: =COUNTA(B10:B18,B20:B32,B34:B37) | L3: =COUNTIF(E10:AI18,TRUE)+COUNTIF(E10:AI18,"x")+COUNTIF(E20:AI32,TRUE)+COUNTIF(E20:AI32,"x")+COUNTIF(E34:AI37,TRUE)+COUNTIF(E34:AI37,"x") | S3: =IF(ISNUMBER(AK39),TEXT(AK39,"0%")&" "&IF(ISNUMBER(AK39),REPT("█",ROUND(MAX(0,MIN(1,AK39))*12,0))&REPT("░",12-ROUND(MAX(0,MIN(1,AK39))*12,0)),""),"—") | AC3: =IF(ISNUMBER(IFERROR(INDEX(Data!$BG$4:$BG$375,MATCH($AP$13,Data!$A$4:$A$375,0)),"")),TEXT(IFERROR(INDEX(Data!$BG$4:$BG$375,MATCH($AP$13,Data!$A$4:$A$375,0)),""),"0%")&" · "&IF(NOT(ISNUMBER(IFERROR(INDEX(Data!$BG$4:$BG$375,MATCH($AP$13,Data!$A$4:$A$375,0)),""))),"—",IF(IFERROR(INDEX(Data!$BG$4:$BG$375,MATCH($AP$13,Data!$A$4:$A$375,0)),"")>=Band1,"GREEN",IF(IFERROR(INDEX(Data!$BG$4:$BG$375,MATCH($AP$13,Data!$A$4:$A$375,0)),"")>=Band2,"GOOD",IF(IFERROR(INDEX(Data!$BG$4:$BG$375,MATCH($AP$13,Data!$A$4:$A$375,0)),"")>=Band3,"NEEDS ATTENTION","RESET")))),"—") | AK3: =IF(ISNUMBER(IFERROR(INDEX(Data!$BH$4:$BH$375,MATCH($AP$13,Data!$A$4:$A$375,0)),"")),TEXT(IFERROR(INDEX(Data!$BH$4:$BH$375,MATCH($AP$13,Data!$A$4:$A$375,0)),""),"0%")&" · "&IF(NOT(ISNUMBER(IFERROR(INDEX(Data!$BH$4:$BH$375,MATCH($AP$13,Data!$A$4:$A$375,0)),""))),"—",IF(IFERROR(INDEX(Data!$BH$4:$BH$375,MATCH($AP$13,Data!$A$4:$A$375,0)),"")>=Band1,"GREEN",IF(IFERROR(INDEX(Data!$BH$4:$BH$375,MATCH($AP$13,Data!$A$4:$A$375,0)),"")>=Band2,"GOOD",IF(IFERROR(INDEX(Data!$BH$4:$BH$375,MATCH($AP$13,Data!$A$4:$A$375,0)),"")>=Band3,"NEEDS ATTENTION","RESET")))),"—") | AP3: =WaterHit
AP4: =SleepMin
B5: MY HABITS | E5: Week 1 | L5: Week 2 | S5: Week 3 | Z5: Week 4 | AG5: Week 5 | AK5: ANALYSIS | AP5: =SleepLow
B6: Tick what you did. Missed is data, not failure. | E6: =IF(E7="","",LEFT(TEXT(E7,"ddd"),2)) | F6: =IF(F7="","",LEFT(TEXT(F7,"ddd"),2)) | G6: =IF(G7="","",LEFT(TEXT(G7,"ddd"),2)) | H6: =IF(H7="","",LEFT(TEXT(H7,"ddd"),2)) | I6: =IF(I7="","",LEFT(TEXT(I7,"ddd"),2)) | J6: =IF(J7="","",LEFT(TEXT(J7,"ddd"),2)) | K6: =IF(K7="","",LEFT(TEXT(K7,"ddd"),2)) | L6: =IF(L7="","",LEFT(TEXT(L7,"ddd"),2)) | ... AI6: =IF(AI7="","",LEFT(TEXT(AI7,"ddd"),2)) | AK6: Done | AL6: Goal | AM6: Progress | AN6: % | AP6: =TODAY()
B7: Habit | C7: Pillar | D7: Target | E7: =IF(1<=DAY(EOMONTH($AP$1,0)),$AP$1+0,"") | F7: =IF(2<=DAY(EOMONTH($AP$1,0)),$AP$1+1,"") | G7: =IF(3<=DAY(EOMONTH($AP$1,0)),$AP$1+2,"") | H7: =IF(4<=DAY(EOMONTH($AP$1,0)),$AP$1+3,"") | I7: =IF(5<=DAY(EOMONTH($AP$1,0)),$AP$1+4,"") | J7: =IF(6<=DAY(EOMONTH($AP$1,0)),$AP$1+5,"") | K7: =IF(7<=DAY(EOMONTH($AP$1,0)),$AP$1+6,"") | L7: =IF(8<=DAY(EOMONTH($AP$1,0)),$AP$1+7,"") | M7: =IF(9<=DAY(EOMONTH($AP$1,0)),$AP$1+8,"") | N7: =IF(10<=DAY(EOMONTH($AP$1,0)),$AP$1+9,"") | O7: =IF(11<=DAY(EOMONTH($AP$1,0)),$AP$1+10,"") | P7: =IF(12<=DAY(EOMONTH($AP$1,0)),$AP$1+11,"") | Q7: =IF(13<=DAY(EOMONTH($AP$1,0)),$AP$1+12,"") | R7: =IF(14<=DAY(EOMONTH($AP$1,0)),$AP$1+13,"") | S7: =IF(15<=DAY(EOMONTH($AP$1,0)),$AP$1+14,"") | T7: =IF(16<=DAY(EOMONTH($AP$1,0)),$AP$1+15,"") | U7: =IF(17<=DAY(EOMONTH($AP$1,0)),$AP$1+16,"") | V7: =IF(18<=DAY(EOMONTH($AP$1,0)),$AP$1+17,"") | W7: =IF(19<=DAY(EOMONTH($AP$1,0)),$AP$1+18,"") | X7: =IF(20<=DAY(EOMONTH($AP$1,0)),$AP$1+19,"") | Y7: =IF(21<=DAY(EOMONTH($AP$1,0)),$AP$1+20,"") | Z7: =IF(22<=DAY(EOMONTH($AP$1,0)),$AP$1+21,"") | AA7: =IF(23<=DAY(EOMONTH($AP$1,0)),$AP$1+22,"") | AB7: =IF(24<=DAY(EOMONTH($AP$1,0)),$AP$1+23,"") | AC7: =IF(25<=DAY(EOMONTH($AP$1,0)),$AP$1+24,"") | AD7: =IF(26<=DAY(EOMONTH($AP$1,0)),$AP$1+25,"") | AE7: =IF(27<=DAY(EOMONTH($AP$1,0)),$AP$1+26,"") | AF7: =IF(28<=DAY(EOMONTH($AP$1,0)),$AP$1+27,"") | AG7: =IF(29<=DAY(EOMONTH($AP$1,0)),$AP$1+28,"") | AH7: =IF(30<=DAY(EOMONTH($AP$1,0)),$AP$1+29,"") | AI7: =IF(31<=DAY(EOMONTH($AP$1,0)),$AP$1+30,"") | AK7: goal = weekly target × days tracked | AP7: =KcalMin
B8: Day mode | C8: M = minimum · S = sick · R = rest | AK8: =COUNTIF(E8:AI8,"M")&" min · "&COUNTIF(E8:AI8,"S")&" sick · "&COUNTIF(E8:AI8,"R")&" rest" | AP8: =KcalMax
B9: LEVEL 1 · NON-NEGOTIABLES | AK9: the daily foundation | AP9: =COUNTIFS(Data!$B$4:$B$375,6,Data!$AO$4:$AO$375,1,Data!$E$4:$E$375,"<>S")
B10: 🌅 Morning reset | C10: HEALTH | D10: Daily | AK10: =COUNTIF(E10:AI10,TRUE)+COUNTIF(E10:AI10,"x") | AL10: =ROUND($AP$9*7/7,0) | AM10: =IF(ISNUMBER(AN10),REPT("█",ROUND(MAX(0,MIN(1,AN10))*10,0))&REPT("░",10-ROUND(MAX(0,MIN(1,AN10))*10,0)),"") | AN10: =IF(N(AL10)=0,"",MIN(1,AK10/AL10)) | AP10: =COUNTIFS(Data!$B$4:$B$375,6,Data!$AO$4:$AO$375,1,Data!$E$4:$E$375,"<>S",Data!$AS$4:$AS$375,1)
B11: 🙏 Prayer + Scripture ◆ | C11: SPIRIT | D11: Daily | AK11: =COUNTIF(E11:AI11,TRUE)+COUNTIF(E11:AI11,"x") | AL11: =ROUND($AP$9*7/7,0) | AM11: =IF(ISNUMBER(AN11),REPT("█",ROUND(MAX(0,MIN(1,AN11))*10,0))&REPT("░",10-ROUND(MAX(0,MIN(1,AN11))*10,0)),"") | AN11: =IF(N(AL11)=0,"",MIN(1,AK11/AL11)) | AP11: =_xlfn.MAXIFS(Data!$A$4:$A$375,Data!$B$4:$B$375,6,Data!$AF$4:$AF$375,">0")
B12: 🧘 Mobility & posture ◆ | C12: POSTURE | D12: Daily | AK12: =COUNTIF(E12:AI12,TRUE)+COUNTIF(E12:AI12,"x") | AL12: =ROUND($AP$9*7/7,0) | AM12: =IF(ISNUMBER(AN12),REPT("█",ROUND(MAX(0,MIN(1,AN12))*10,0))&REPT("░",10-ROUND(MAX(0,MIN(1,AN12))*10,0)),"") | AN12: =IF(N(AL12)=0,"",MIN(1,AK12/AL12)) | AP12: =_xlfn.MINIFS(Data!$A$4:$A$375,Data!$B$4:$B$375,6,Data!$AF$4:$AF$375,">0")
B13: 💪 Training / movement ◆ | C13: BODY | D13: Daily | AK13: =COUNTIF(E13:AI13,TRUE)+COUNTIF(E13:AI13,"x") | AL13: =ROUND($AP$9*7/7,0) | AM13: =IF(ISNUMBER(AN13),REPT("█",ROUND(MAX(0,MIN(1,AN13))*10,0))&REPT("░",10-ROUND(MAX(0,MIN(1,AN13))*10,0)),"") | AN13: =IF(N(AL13)=0,"",MIN(1,AK13/AL13)) | AP13: =MIN(AP6,EOMONTH(AP1,0))
B14: 🎯 Top 3 priorities | C14: WORK | D14: 5× / wk | AK14: =COUNTIF(E14:AI14,TRUE)+COUNTIF(E14:AI14,"x") | AL14: =$AP$10 | AM14: =IF(ISNUMBER(AN14),REPT("█",ROUND(MAX(0,MIN(1,AN14))*10,0))&REPT("░",10-ROUND(MAX(0,MIN(1,AN14))*10,0)),"") | AN14: =IF(N(AL14)=0,"",MIN(1,AK14/AL14))
B15: ❤️ Fiancée time ◆ | C15: RELATIONSHIPS | D15: Daily | AK15: =COUNTIF(E15:AI15,TRUE)+COUNTIF(E15:AI15,"x") | AL15: =ROUND($AP$9*7/7,0) | AM15: =IF(ISNUMBER(AN15),REPT("█",ROUND(MAX(0,MIN(1,AN15))*10,0))&REPT("░",10-ROUND(MAX(0,MIN(1,AN15))*10,0)),"") | AN15: =IF(N(AL15)=0,"",MIN(1,AK15/AL15))
B16: 📖 Read / learn | C16: MIND | D16: Daily | AK16: =COUNTIF(E16:AI16,TRUE)+COUNTIF(E16:AI16,"x") | AL16: =ROUND($AP$9*7/7,0) | AM16: =IF(ISNUMBER(AN16),REPT("█",ROUND(MAX(0,MIN(1,AN16))*10,0))&REPT("░",10-ROUND(MAX(0,MIN(1,AN16))*10,0)),"") | AN16: =IF(N(AL16)=0,"",MIN(1,AK16/AL16))
B17: 🌙 Evening shutdown | C17: WORK | D17: Daily | AK17: =COUNTIF(E17:AI17,TRUE)+COUNTIF(E17:AI17,"x") | AL17: =ROUND($AP$9*7/7,0) | AM17: =IF(ISNUMBER(AN17),REPT("█",ROUND(MAX(0,MIN(1,AN17))*10,0))&REPT("░",10-ROUND(MAX(0,MIN(1,AN17))*10,0)),"") | AN17: =IF(N(AL17)=0,"",MIN(1,AK17/AL17))
B18: 😴 Lights out 22:00 ◆ | C18: HEALTH | D18: Daily | AK18: =COUNTIF(E18:AI18,TRUE)+COUNTIF(E18:AI18,"x") | AL18: =ROUND($AP$9*7/7,0) | AM18: =IF(ISNUMBER(AN18),REPT("█",ROUND(MAX(0,MIN(1,AN18))*10,0))&REPT("░",10-ROUND(MAX(0,MIN(1,AN18))*10,0)),"") | AN18: =IF(N(AL18)=0,"",MIN(1,AK18/AL18))
B19: LEVEL 2 · HIGH VALUE | AK19: weekly targets
B20: 🏋️ Strength session | C20: BODY | D20: 4× / wk | AK20: =COUNTIF(E20:AI20,TRUE)+COUNTIF(E20:AI20,"x") | AL20: =ROUND($AP$9*4/7,0) | AM20: =IF(ISNUMBER(AN20),REPT("█",ROUND(MAX(0,MIN(1,AN20))*10,0))&REPT("░",10-ROUND(MAX(0,MIN(1,AN20))*10,0)),"") | AN20: =IF(N(AL20)=0,"",MIN(1,AK20/AL20))
B21: 📈 Progression achieved | C21: BODY | D21: 4× / wk | AK21: =COUNTIF(E21:AI21,TRUE)+COUNTIF(E21:AI21,"x") | AL21: =ROUND($AP$9*4/7,0) | AM21: =IF(ISNUMBER(AN21),REPT("█",ROUND(MAX(0,MIN(1,AN21))*10,0))&REPT("░",10-ROUND(MAX(0,MIN(1,AN21))*10,0)),"") | AN21: =IF(N(AL21)=0,"",MIN(1,AK21/AL21))
B22: 🧱 Core | C22: BODY | D22: 3× / wk | AK22: =COUNTIF(E22:AI22,TRUE)+COUNTIF(E22:AI22,"x") | AL22: =ROUND($AP$9*3/7,0) | AM22: =IF(ISNUMBER(AN22),REPT("█",ROUND(MAX(0,MIN(1,AN22))*10,0))&REPT("░",10-ROUND(MAX(0,MIN(1,AN22))*10,0)),"") | AN22: =IF(N(AL22)=0,"",MIN(1,AK22/AL22))
B23: 🦵 Calves | C23: BODY | D23: 3× / wk | AK23: =COUNTIF(E23:AI23,TRUE)+COUNTIF(E23:AI23,"x") | AL23: =ROUND($AP$9*3/7,0) | AM23: =IF(ISNUMBER(AN23),REPT("█",ROUND(MAX(0,MIN(1,AN23))*10,0))&REPT("░",10-ROUND(MAX(0,MIN(1,AN23))*10,0)),"") | AN23: =IF(N(AL23)=0,"",MIN(1,AK23/AL23))
B24: 🚶 Cardio | C24: BODY | D24: 2× / wk | AK24: =COUNTIF(E24:AI24,TRUE)+COUNTIF(E24:AI24,"x") | AL24: =ROUND($AP$9*2/7,0) | AM24: =IF(ISNUMBER(AN24),REPT("█",ROUND(MAX(0,MIN(1,AN24))*10,0))&REPT("░",10-ROUND(MAX(0,MIN(1,AN24))*10,0)),"") | AN24: =IF(N(AL24)=0,"",MIN(1,AK24/AL24))
B25: 🧠 Deep work 2+ blocks | C25: WORK | D25: 5× / wk | AK25: =COUNTIF(E25:AI25,TRUE)+COUNTIF(E25:AI25,"x") | AL25: =ROUND($AP$9*5/7,0) | AM25: =IF(ISNUMBER(AN25),REPT("█",ROUND(MAX(0,MIN(1,AN25))*10,0))&REPT("░",10-ROUND(MAX(0,MIN(1,AN25))*10,0)),"") | AN25: =IF(N(AL25)=0,"",MIN(1,AK25/AL25))
B26: 👀 Posture & eye breaks | C26: POSTURE | D26: 5× / wk | AK26: =COUNTIF(E26:AI26,TRUE)+COUNTIF(E26:AI26,"x") | AL26: =ROUND($AP$9*5/7,0) | AM26: =IF(ISNUMBER(AN26),REPT("█",ROUND(MAX(0,MIN(1,AN26))*10,0))&REPT("░",10-ROUND(MAX(0,MIN(1,AN26))*10,0)),"") | AN26: =IF(N(AL26)=0,"",MIN(1,AK26/AL26))
B27: 🧹 Home reset | C27: LIFE ADMIN | D27: 5× / wk | AK27: =COUNTIF(E27:AI27,TRUE)+COUNTIF(E27:AI27,"x") | AL27: =ROUND($AP$9*5/7,0) | AM27: =IF(ISNUMBER(AN27),REPT("█",ROUND(MAX(0,MIN(1,AN27))*10,0))&REPT("░",10-ROUND(MAX(0,MIN(1,AN27))*10,0)),"") | AN27: =IF(N(AL27)=0,"",MIN(1,AK27/AL27))
B28: 👦 Father–son time | C28: RELATIONSHIPS | D28: 1× / wk | AK28: =COUNTIF(E28:AI28,TRUE)+COUNTIF(E28:AI28,"x") | AL28: =ROUND($AP$9*1/7,0) | AM28: =IF(ISNUMBER(AN28),REPT("█",ROUND(MAX(0,MIN(1,AN28))*10,0))&REPT("░",10-ROUND(MAX(0,MIN(1,AN28))*10,0)),"") | AN28: =IF(N(AL28)=0,"",MIN(1,AK28/AL28))
B29: 🥂 Couple time / date | C29: RELATIONSHIPS | D29: 1× / wk | AK29: =COUNTIF(E29:AI29,TRUE)+COUNTIF(E29:AI29,"x") | AL29: =ROUND($AP$9*1/7,0) | AM29: =IF(ISNUMBER(AN29),REPT("█",ROUND(MAX(0,MIN(1,AN29))*10,0))&REPT("░",10-ROUND(MAX(0,MIN(1,AN29))*10,0)),"") | AN29: =IF(N(AL29)=0,"",MIN(1,AK29/AL29))
B30: 📞 Family check-in | C30: RELATIONSHIPS | D30: 1× / wk | AK30: =COUNTIF(E30:AI30,TRUE)+COUNTIF(E30:AI30,"x") | AL30: =ROUND($AP$9*1/7,0) | AM30: =IF(ISNUMBER(AN30),REPT("█",ROUND(MAX(0,MIN(1,AN30))*10,0))&REPT("░",10-ROUND(MAX(0,MIN(1,AN30))*10,0)),"") | AN30: =IF(N(AL30)=0,"",MIN(1,AK30/AL30))
B31: ⛪ Church / worship | C31: SPIRIT | D31: 1× / wk | AK31: =COUNTIF(E31:AI31,TRUE)+COUNTIF(E31:AI31,"x") | AL31: =ROUND($AP$9*1/7,0) | AM31: =IF(ISNUMBER(AN31),REPT("█",ROUND(MAX(0,MIN(1,AN31))*10,0))&REPT("░",10-ROUND(MAX(0,MIN(1,AN31))*10,0)),"") | AN31: =IF(N(AL31)=0,"",MIN(1,AK31/AL31))
B32: 🍱 Meal prep | C32: LIFE ADMIN | D32: 1× / wk | AK32: =COUNTIF(E32:AI32,TRUE)+COUNTIF(E32:AI32,"x") | AL32: =ROUND($AP$9*1/7,0) | AM32: =IF(ISNUMBER(AN32),REPT("█",ROUND(MAX(0,MIN(1,AN32))*10,0))&REPT("░",10-ROUND(MAX(0,MIN(1,AN32))*10,0)),"") | AN32: =IF(N(AL32)=0,"",MIN(1,AK32/AL32))
B33: LEVEL 3 · OPTIONAL | AK33: bonus, never guilt
B34: 🕊️ Meditation / journal | C34: MIND | D34: Optional | AK34: =COUNTIF(E34:AI34,TRUE)+COUNTIF(E34:AI34,"x") | AL34: — | AM34: =IF(AK34=0,"",AK34&" × bonus")
B35: ➕ Extra walk / cardio | C35: BODY | D35: Optional | AK35: =COUNTIF(E35:AI35,TRUE)+COUNTIF(E35:AI35,"x") | AL35: — | AM35: =IF(AK35=0,"",AK35&" × bonus")
B36: ➕ Extra mobility | C36: POSTURE | D36: Optional | AK36: =COUNTIF(E36:AI36,TRUE)+COUNTIF(E36:AI36,"x") | AL36: — | AM36: =IF(AK36=0,"",AK36&" × bonus")
B37: ➕ Extra reading | C37: MIND | D37: Optional | AK37: =COUNTIF(E37:AI37,TRUE)+COUNTIF(E37:AI37,"x") | AL37: — | AM37: =IF(AK37=0,"",AK37&" × bonus")
B39: Foundation score | C39: auto · 9 pillars of the day | E39: =Data!BF159 | F39: =Data!BF160 | G39: =Data!BF161 | H39: =Data!BF162 | I39: =Data!BF163 | J39: =Data!BF164 | K39: =Data!BF165 | L39: =Data!BF166 | M39: =Data!BF167 | N39: =Data!BF168 | O39: =Data!BF169 | P39: =Data!BF170 | Q39: =Data!BF171 | R39: =Data!BF172 | S39: =Data!BF173 | T39: =Data!BF174 | U39: =Data!BF175 | V39: =Data!BF176 | W39: =Data!BF177 | X39: =Data!BF178 | Y39: =Data!BF179 | Z39: =Data!BF180 | AA39: =Data!BF181 | AB39: =Data!BF182 | AC39: =Data!BF183 | AD39: =Data!BF184 | AE39: =Data!BF185 | AF39: =Data!BF186 | AG39: =Data!BF187 | AH39: =Data!BF188 | AI39: =Data!BF189 | AK39: =IFERROR(AVERAGE(E39:AI39),"") | AL39: avg | AM39: =IF(ISNUMBER(AN39),REPT("█",ROUND(MAX(0,MIN(1,AN39))*10,0))&REPT("░",10-ROUND(MAX(0,MIN(1,AN39))*10,0)),"") | AN39: =AK39
B40: Non-negotiables done | C40: of 9 (8 on non-work days) | E40: =IF(Data!BF159="","",Data!BJ159) | F40: =IF(Data!BF160="","",Data!BJ160) | G40: =IF(Data!BF161="","",Data!BJ161) | H40: =IF(Data!BF162="","",Data!BJ162) | I40: =IF(Data!BF163="","",Data!BJ163) | J40: =IF(Data!BF164="","",Data!BJ164) | K40: =IF(Data!BF165="","",Data!BJ165) | L40: =IF(Data!BF166="","",Data!BJ166) | M40: =IF(Data!BF167="","",Data!BJ167) | N40: =IF(Data!BF168="","",Data!BJ168) | O40: =IF(Data!BF169="","",Data!BJ169) | P40: =IF(Data!BF170="","",Data!BJ170) | Q40: =IF(Data!BF171="","",Data!BJ171) | R40: =IF(Data!BF172="","",Data!BJ172) | S40: =IF(Data!BF173="","",Data!BJ173) | T40: =IF(Data!BF174="","",Data!BJ174) | U40: =IF(Data!BF175="","",Data!BJ175) | V40: =IF(Data!BF176="","",Data!BJ176) | W40: =IF(Data!BF177="","",Data!BJ177) | X40: =IF(Data!BF178="","",Data!BJ178) | Y40: =IF(Data!BF179="","",Data!BJ179) | Z40: =IF(Data!BF180="","",Data!BJ180) | AA40: =IF(Data!BF181="","",Data!BJ181) | AB40: =IF(Data!BF182="","",Data!BJ182) | AC40: =IF(Data!BF183="","",Data!BJ183) | AD40: =IF(Data!BF184="","",Data!BJ184) | AE40: =IF(Data!BF185="","",Data!BJ185) | AF40: =IF(Data!BF186="","",Data!BJ186) | AG40: =IF(Data!BF187="","",Data!BJ187) | AH40: =IF(Data!BF188="","",Data!BJ188) | AI40: =IF(Data!BF189="","",Data!BJ189)
B42: DAILY FOUNDATION SCORE | AK42: WEEKLY AVERAGE
B43: One number for the day, built from 9 things: Sleep · Movement · Protein · Water · Steps · Prayer · Top 3 (work days) · Fiancée · Read/learn M days are scored on the Minimum Viable Day. S days are paused — no score, no guilt. ◆ = part of the Minimum Viable Day
AK44: Week 1 | AM44: =IF(ISNUMBER(AN44),REPT("█",ROUND(MAX(0,MIN(1,AN44))*10,0))&REPT("░",10-ROUND(MAX(0,MIN(1,AN44))*10,0)),"") | AN44: =IFERROR(AVERAGE(E39:K39),"")
AK46: Week 2 | AM46: =IF(ISNUMBER(AN46),REPT("█",ROUND(MAX(0,MIN(1,AN46))*10,0))&REPT("░",10-ROUND(MAX(0,MIN(1,AN46))*10,0)),"") | AN46: =IFERROR(AVERAGE(L39:R39),"")
AK48: Week 3 | AM48: =IF(ISNUMBER(AN48),REPT("█",ROUND(MAX(0,MIN(1,AN48))*10,0))&REPT("░",10-ROUND(MAX(0,MIN(1,AN48))*10,0)),"") | AN48: =IFERROR(AVERAGE(S39:Y39),"")
AK50: Week 4 | AM50: =IF(ISNUMBER(AN50),REPT("█",ROUND(MAX(0,MIN(1,AN50))*10,0))&REPT("░",10-ROUND(MAX(0,MIN(1,AN50))*10,0)),"") | AN50: =IFERROR(AVERAGE(Z39:AF39),"")
AK52: Week 5 | AM52: =IF(ISNUMBER(AN52),REPT("█",ROUND(MAX(0,MIN(1,AN52))*10,0))&REPT("░",10-ROUND(MAX(0,MIN(1,AN52))*10,0)),"") | AN52: =IFERROR(AVERAGE(AG39:AI39),"")
B56: BODY & MIND | E56: Week 1 | L56: Week 2 | S56: Week 3 | Z56: Week 4 | AG56: Week 5 | AK56: ANALYSIS
B57: Log the numbers you have. Blank is fine. | E57: =E6 | F57: =F6 | G57: =G6 | H57: =H6 | I57: =I6 | J57: =J6 | K57: =K6 | L57: =L6 | ... AI57: =AI6 | AK57: Avg | AL57: Target | AM57: Progress | AN57: Hit %
B58: Metric | C58: Unit | D58: Target | E58: =E7 | F58: =F7 | G58: =G7 | H58: =H7 | I58: =I7 | J58: =J7 | K58: =K7 | L58: =L7 | ... AI58: =AI7 | AK58: hit % = days on target ÷ days logged
B59: ⚖️ Weight | C59: kg | D59: AM, 7-day avg | AK59: =IF($AP$11=0,"",INDEX(Data!$BI$4:$BI$375,MATCH($AP$11,Data!$A$4:$A$375,0))) | AL59: 7d avg | AM59: =IF($AP$11=0,"",IFERROR("Δ month "&TEXT(AK59-INDEX(Data!$BI$4:$BI$375,MATCH($AP$12,Data!$A$4:$A$375,0)),"+0.0;-0.0")&" kg",""))
B60: 👣 Steps | C60: steps | D60: adaptive | AK60: =IFERROR(AVERAGE(E60:AI60),"") | AL60: =IFERROR(MAX(E69:AI69)*1000,"") | AM60: =IF(AND(ISNUMBER(AK60),ISNUMBER(AL60)),IF(ISNUMBER(AK60/AL60),REPT("█",ROUND(MAX(0,MIN(1,AK60/AL60))*10,0))&REPT("░",10-ROUND(MAX(0,MIN(1,AK60/AL60))*10,0)),""),"") | AN60: =IFERROR(SUMIFS(Data!$AY$4:$AY$375,Data!$B$4:$B$375,6)/COUNTIFS(Data!$B$4:$B$375,6,Data!$AG$4:$AG$375,">0"),"")
B61: 🍗 Protein | C61: g | D61: 150 g | AK61: =IFERROR(AVERAGE(E61:AI61),"") | AL61: =ProtTarget | AM61: =IF(AND(ISNUMBER(AK61),ISNUMBER(AL61)),IF(ISNUMBER(AK61/AL61),REPT("█",ROUND(MAX(0,MIN(1,AK61/AL61))*10,0))&REPT("░",10-ROUND(MAX(0,MIN(1,AK61/AL61))*10,0)),""),"") | AN61: =IFERROR(SUMIFS(Data!$AW$4:$AW$375,Data!$B$4:$B$375,6)/COUNTIFS(Data!$B$4:$B$375,6,Data!$AH$4:$AH$375,">0"),"")
B62: 💧 Water | C62: L | D62: 2.5–3 L | AK62: =IFERROR(AVERAGE(E62:AI62),"") | AL62: =WaterHit | AM62: =IF(AND(ISNUMBER(AK62),ISNUMBER(AL62)),IF(ISNUMBER(AK62/AL62),REPT("█",ROUND(MAX(0,MIN(1,AK62/AL62))*10,0))&REPT("░",10-ROUND(MAX(0,MIN(1,AK62/AL62))*10,0)),""),"") | AN62: =IFERROR(SUMIFS(Data!$AX$4:$AX$375,Data!$B$4:$B$375,6)/COUNTIFS(Data!$B$4:$B$375,6,Data!$AI$4:$AI$375,">0"),"")
B63: 🔥 Calories | C63: kcal | D63: 1.8–2k | AK63: =IFERROR(AVERAGE(E63:AI63),"") | AL63: =TEXT(KcalMin,"#,##0")&"–"&TEXT(KcalMax,"#,##0") | AM63: =IF(ISNUMBER(AN63),REPT("█",ROUND(MAX(0,MIN(1,AN63))*10,0))&REPT("░",10-ROUND(MAX(0,MIN(1,AN63))*10,0)),"") | AN63: =IFERROR(COUNTIFS(E63:AI63,">="&$AP$7,E63:AI63,"<="&$AP$8)/COUNT(E63:AI63),"")
B64: 🛌 Sleep | C64: hours | D64: 7.5–8.5 h | AK64: =IFERROR(AVERAGE(E64:AI64),"") | AL64: =SleepTarget | AM64: =IF(AND(ISNUMBER(AK64),ISNUMBER(AL64)),IF(ISNUMBER(AK64/AL64),REPT("█",ROUND(MAX(0,MIN(1,AK64/AL64))*10,0))&REPT("░",10-ROUND(MAX(0,MIN(1,AK64/AL64))*10,0)),""),"") | AN64: =IFERROR(COUNTIF(E64:AI64,">="&$AP$4)/COUNT(E64:AI64),"")
B65: ⚡ Energy | C65: 1–10 | D65: 1–10 | AK65: =IFERROR(AVERAGE(E65:AI65),"") | AL65: / 10 | AM65: =IF(ISNUMBER(AK65),IF(ISNUMBER(AK65/10),REPT("█",ROUND(MAX(0,MIN(1,AK65/10))*10,0))&REPT("░",10-ROUND(MAX(0,MIN(1,AK65/10))*10,0)),""),"")
B66: 🌡️ Stress | C66: 1–10 | D66: 1–10 | AK66: =IFERROR(AVERAGE(E66:AI66),"") | AL66: / 10 | AM66: =IF(ISNUMBER(AK66),IF(ISNUMBER(AK66/10),REPT("█",ROUND(MAX(0,MIN(1,AK66/10))*10,0))&REPT("░",10-ROUND(MAX(0,MIN(1,AK66/10))*10,0)),""),"")
B67: 🙂 Mood | C67: 1–10 | D67: 1–10 | AK67: =IFERROR(AVERAGE(E67:AI67),"") | AL67: / 10 | AM67: =IF(ISNUMBER(AK67),IF(ISNUMBER(AK67/10),REPT("█",ROUND(MAX(0,MIN(1,AK67/10))*10,0))&REPT("░",10-ROUND(MAX(0,MIN(1,AK67/10))*10,0)),""),"")
B68: ↳ Weight · 7-day average | C68: decide on this | E68: =Data!BI159 | F68: =Data!BI160 | G68: =Data!BI161 | H68: =Data!BI162 | I68: =Data!BI163 | J68: =Data!BI164 | K68: =Data!BI165 | L68: =Data!BI166 | M68: =Data!BI167 | N68: =Data!BI168 | O68: =Data!BI169 | P68: =Data!BI170 | Q68: =Data!BI171 | R68: =Data!BI172 | S68: =Data!BI173 | T68: =Data!BI174 | U68: =Data!BI175 | V68: =Data!BI176 | W68: =Data!BI177 | X68: =Data!BI178 | Y68: =Data!BI179 | Z68: =Data!BI180 | AA68: =Data!BI181 | AB68: =Data!BI182 | AC68: =Data!BI183 | AD68: =Data!BI184 | AE68: =Data!BI185 | AF68: =Data!BI186 | AG68: =Data!BI187 | AH68: =Data!BI188 | AI68: =Data!BI189
B69: ↳ Steps target (adaptive) | C69: 7k → 8k → 9k | E69: =IF(Data!A159="","",Data!AR159/1000) | F69: =IF(Data!A160="","",Data!AR160/1000) | G69: =IF(Data!A161="","",Data!AR161/1000) | H69: =IF(Data!A162="","",Data!AR162/1000) | I69: =IF(Data!A163="","",Data!AR163/1000) | J69: =IF(Data!A164="","",Data!AR164/1000) | K69: =IF(Data!A165="","",Data!AR165/1000) | L69: =IF(Data!A166="","",Data!AR166/1000) | M69: =IF(Data!A167="","",Data!AR167/1000) | N69: =IF(Data!A168="","",Data!AR168/1000) | O69: =IF(Data!A169="","",Data!AR169/1000) | P69: =IF(Data!A170="","",Data!AR170/1000) | Q69: =IF(Data!A171="","",Data!AR171/1000) | R69: =IF(Data!A172="","",Data!AR172/1000) | S69: =IF(Data!A173="","",Data!AR173/1000) | T69: =IF(Data!A174="","",Data!AR174/1000) | U69: =IF(Data!A175="","",Data!AR175/1000) | V69: =IF(Data!A176="","",Data!AR176/1000) | W69: =IF(Data!A177="","",Data!AR177/1000) | X69: =IF(Data!A178="","",Data!AR178/1000) | Y69: =IF(Data!A179="","",Data!AR179/1000) | Z69: =IF(Data!A180="","",Data!AR180/1000) | AA69: =IF(Data!A181="","",Data!AR181/1000) | AB69: =IF(Data!A182="","",Data!AR182/1000) | AC69: =IF(Data!A183="","",Data!AR183/1000) | AD69: =IF(Data!A184="","",Data!AR184/1000) | AE69: =IF(Data!A185="","",Data!AR185/1000) | AF69: =IF(Data!A186="","",Data!AR186/1000) | AG69: =IF(Data!A187="","",Data!AR187/1000) | AH69: =IF(Data!A188="","",Data!AR188/1000) | AI69: =IF(Data!A189="","",Data!AR189/1000)
B71: TRENDS | E71: MIND & RECOVERY · energy · stress · mood | U71: WEIGHT · daily vs 7-day average
B72: Energy, stress and mood show how the month feels, not just what got done. Weight: the dots jump around with water and salt. The 7-day average is the only line that decides anything. Target pace: −0.4 to −0.8 kg a week.

Sheet Apr 2027
AP1: =DATE(2027,4,1)
B2: =UPPER(TEXT($AP$1,"mmmm")) | E2: HABITS | L2: CHECK-INS | S2: FOUNDATION · MONTH | AC2: ROLLING 7-DAY | AK2: ROLLING 30-DAY | AP2: =ProtHit
B3: ="— Life OS · Habit Tracker · "&YEAR($AP$1)&" —" | E3: =COUNTA(B10:B18,B20:B32,B34:B37) | L3: =COUNTIF(E10:AI18,TRUE)+COUNTIF(E10:AI18,"x")+COUNTIF(E20:AI32,TRUE)+COUNTIF(E20:AI32,"x")+COUNTIF(E34:AI37,TRUE)+COUNTIF(E34:AI37,"x") | S3: =IF(ISNUMBER(AK39),TEXT(AK39,"0%")&" "&IF(ISNUMBER(AK39),REPT("█",ROUND(MAX(0,MIN(1,AK39))*12,0))&REPT("░",12-ROUND(MAX(0,MIN(1,AK39))*12,0)),""),"—") | AC3: =IF(ISNUMBER(IFERROR(INDEX(Data!$BG$4:$BG$375,MATCH($AP$13,Data!$A$4:$A$375,0)),"")),TEXT(IFERROR(INDEX(Data!$BG$4:$BG$375,MATCH($AP$13,Data!$A$4:$A$375,0)),""),"0%")&" · "&IF(NOT(ISNUMBER(IFERROR(INDEX(Data!$BG$4:$BG$375,MATCH($AP$13,Data!$A$4:$A$375,0)),""))),"—",IF(IFERROR(INDEX(Data!$BG$4:$BG$375,MATCH($AP$13,Data!$A$4:$A$375,0)),"")>=Band1,"GREEN",IF(IFERROR(INDEX(Data!$BG$4:$BG$375,MATCH($AP$13,Data!$A$4:$A$375,0)),"")>=Band2,"GOOD",IF(IFERROR(INDEX(Data!$BG$4:$BG$375,MATCH($AP$13,Data!$A$4:$A$375,0)),"")>=Band3,"NEEDS ATTENTION","RESET")))),"—") | AK3: =IF(ISNUMBER(IFERROR(INDEX(Data!$BH$4:$BH$375,MATCH($AP$13,Data!$A$4:$A$375,0)),"")),TEXT(IFERROR(INDEX(Data!$BH$4:$BH$375,MATCH($AP$13,Data!$A$4:$A$375,0)),""),"0%")&" · "&IF(NOT(ISNUMBER(IFERROR(INDEX(Data!$BH$4:$BH$375,MATCH($AP$13,Data!$A$4:$A$375,0)),""))),"—",IF(IFERROR(INDEX(Data!$BH$4:$BH$375,MATCH($AP$13,Data!$A$4:$A$375,0)),"")>=Band1,"GREEN",IF(IFERROR(INDEX(Data!$BH$4:$BH$375,MATCH($AP$13,Data!$A$4:$A$375,0)),"")>=Band2,"GOOD",IF(IFERROR(INDEX(Data!$BH$4:$BH$375,MATCH($AP$13,Data!$A$4:$A$375,0)),"")>=Band3,"NEEDS ATTENTION","RESET")))),"—") | AP3: =WaterHit
AP4: =SleepMin
B5: MY HABITS | E5: Week 1 | L5: Week 2 | S5: Week 3 | Z5: Week 4 | AG5: Week 5 | AK5: ANALYSIS | AP5: =SleepLow
B6: Tick what you did. Missed is data, not failure. | E6: =IF(E7="","",LEFT(TEXT(E7,"ddd"),2)) | F6: =IF(F7="","",LEFT(TEXT(F7,"ddd"),2)) | G6: =IF(G7="","",LEFT(TEXT(G7,"ddd"),2)) | H6: =IF(H7="","",LEFT(TEXT(H7,"ddd"),2)) | I6: =IF(I7="","",LEFT(TEXT(I7,"ddd"),2)) | J6: =IF(J7="","",LEFT(TEXT(J7,"ddd"),2)) | K6: =IF(K7="","",LEFT(TEXT(K7,"ddd"),2)) | L6: =IF(L7="","",LEFT(TEXT(L7,"ddd"),2)) | ... AI6: =IF(AI7="","",LEFT(TEXT(AI7,"ddd"),2)) | AK6: Done | AL6: Goal | AM6: Progress | AN6: % | AP6: =TODAY()
B7: Habit | C7: Pillar | D7: Target | E7: =IF(1<=DAY(EOMONTH($AP$1,0)),$AP$1+0,"") | F7: =IF(2<=DAY(EOMONTH($AP$1,0)),$AP$1+1,"") | G7: =IF(3<=DAY(EOMONTH($AP$1,0)),$AP$1+2,"") | H7: =IF(4<=DAY(EOMONTH($AP$1,0)),$AP$1+3,"") | I7: =IF(5<=DAY(EOMONTH($AP$1,0)),$AP$1+4,"") | J7: =IF(6<=DAY(EOMONTH($AP$1,0)),$AP$1+5,"") | K7: =IF(7<=DAY(EOMONTH($AP$1,0)),$AP$1+6,"") | L7: =IF(8<=DAY(EOMONTH($AP$1,0)),$AP$1+7,"") | M7: =IF(9<=DAY(EOMONTH($AP$1,0)),$AP$1+8,"") | N7: =IF(10<=DAY(EOMONTH($AP$1,0)),$AP$1+9,"") | O7: =IF(11<=DAY(EOMONTH($AP$1,0)),$AP$1+10,"") | P7: =IF(12<=DAY(EOMONTH($AP$1,0)),$AP$1+11,"") | Q7: =IF(13<=DAY(EOMONTH($AP$1,0)),$AP$1+12,"") | R7: =IF(14<=DAY(EOMONTH($AP$1,0)),$AP$1+13,"") | S7: =IF(15<=DAY(EOMONTH($AP$1,0)),$AP$1+14,"") | T7: =IF(16<=DAY(EOMONTH($AP$1,0)),$AP$1+15,"") | U7: =IF(17<=DAY(EOMONTH($AP$1,0)),$AP$1+16,"") | V7: =IF(18<=DAY(EOMONTH($AP$1,0)),$AP$1+17,"") | W7: =IF(19<=DAY(EOMONTH($AP$1,0)),$AP$1+18,"") | X7: =IF(20<=DAY(EOMONTH($AP$1,0)),$AP$1+19,"") | Y7: =IF(21<=DAY(EOMONTH($AP$1,0)),$AP$1+20,"") | Z7: =IF(22<=DAY(EOMONTH($AP$1,0)),$AP$1+21,"") | AA7: =IF(23<=DAY(EOMONTH($AP$1,0)),$AP$1+22,"") | AB7: =IF(24<=DAY(EOMONTH($AP$1,0)),$AP$1+23,"") | AC7: =IF(25<=DAY(EOMONTH($AP$1,0)),$AP$1+24,"") | AD7: =IF(26<=DAY(EOMONTH($AP$1,0)),$AP$1+25,"") | AE7: =IF(27<=DAY(EOMONTH($AP$1,0)),$AP$1+26,"") | AF7: =IF(28<=DAY(EOMONTH($AP$1,0)),$AP$1+27,"") | AG7: =IF(29<=DAY(EOMONTH($AP$1,0)),$AP$1+28,"") | AH7: =IF(30<=DAY(EOMONTH($AP$1,0)),$AP$1+29,"") | AI7: =IF(31<=DAY(EOMONTH($AP$1,0)),$AP$1+30,"") | AK7: goal = weekly target × days tracked | AP7: =KcalMin
B8: Day mode | C8: M = minimum · S = sick · R = rest | AK8: =COUNTIF(E8:AI8,"M")&" min · "&COUNTIF(E8:AI8,"S")&" sick · "&COUNTIF(E8:AI8,"R")&" rest" | AP8: =KcalMax
B9: LEVEL 1 · NON-NEGOTIABLES | AK9: the daily foundation | AP9: =COUNTIFS(Data!$B$4:$B$375,7,Data!$AO$4:$AO$375,1,Data!$E$4:$E$375,"<>S")
B10: 🌅 Morning reset | C10: HEALTH | D10: Daily | AK10: =COUNTIF(E10:AI10,TRUE)+COUNTIF(E10:AI10,"x") | AL10: =ROUND($AP$9*7/7,0) | AM10: =IF(ISNUMBER(AN10),REPT("█",ROUND(MAX(0,MIN(1,AN10))*10,0))&REPT("░",10-ROUND(MAX(0,MIN(1,AN10))*10,0)),"") | AN10: =IF(N(AL10)=0,"",MIN(1,AK10/AL10)) | AP10: =COUNTIFS(Data!$B$4:$B$375,7,Data!$AO$4:$AO$375,1,Data!$E$4:$E$375,"<>S",Data!$AS$4:$AS$375,1)
B11: 🙏 Prayer + Scripture ◆ | C11: SPIRIT | D11: Daily | AK11: =COUNTIF(E11:AI11,TRUE)+COUNTIF(E11:AI11,"x") | AL11: =ROUND($AP$9*7/7,0) | AM11: =IF(ISNUMBER(AN11),REPT("█",ROUND(MAX(0,MIN(1,AN11))*10,0))&REPT("░",10-ROUND(MAX(0,MIN(1,AN11))*10,0)),"") | AN11: =IF(N(AL11)=0,"",MIN(1,AK11/AL11)) | AP11: =_xlfn.MAXIFS(Data!$A$4:$A$375,Data!$B$4:$B$375,7,Data!$AF$4:$AF$375,">0")
B12: 🧘 Mobility & posture ◆ | C12: POSTURE | D12: Daily | AK12: =COUNTIF(E12:AI12,TRUE)+COUNTIF(E12:AI12,"x") | AL12: =ROUND($AP$9*7/7,0) | AM12: =IF(ISNUMBER(AN12),REPT("█",ROUND(MAX(0,MIN(1,AN12))*10,0))&REPT("░",10-ROUND(MAX(0,MIN(1,AN12))*10,0)),"") | AN12: =IF(N(AL12)=0,"",MIN(1,AK12/AL12)) | AP12: =_xlfn.MINIFS(Data!$A$4:$A$375,Data!$B$4:$B$375,7,Data!$AF$4:$AF$375,">0")
B13: 💪 Training / movement ◆ | C13: BODY | D13: Daily | AK13: =COUNTIF(E13:AI13,TRUE)+COUNTIF(E13:AI13,"x") | AL13: =ROUND($AP$9*7/7,0) | AM13: =IF(ISNUMBER(AN13),REPT("█",ROUND(MAX(0,MIN(1,AN13))*10,0))&REPT("░",10-ROUND(MAX(0,MIN(1,AN13))*10,0)),"") | AN13: =IF(N(AL13)=0,"",MIN(1,AK13/AL13)) | AP13: =MIN(AP6,EOMONTH(AP1,0))
B14: 🎯 Top 3 priorities | C14: WORK | D14: 5× / wk | AK14: =COUNTIF(E14:AI14,TRUE)+COUNTIF(E14:AI14,"x") | AL14: =$AP$10 | AM14: =IF(ISNUMBER(AN14),REPT("█",ROUND(MAX(0,MIN(1,AN14))*10,0))&REPT("░",10-ROUND(MAX(0,MIN(1,AN14))*10,0)),"") | AN14: =IF(N(AL14)=0,"",MIN(1,AK14/AL14))
B15: ❤️ Fiancée time ◆ | C15: RELATIONSHIPS | D15: Daily | AK15: =COUNTIF(E15:AI15,TRUE)+COUNTIF(E15:AI15,"x") | AL15: =ROUND($AP$9*7/7,0) | AM15: =IF(ISNUMBER(AN15),REPT("█",ROUND(MAX(0,MIN(1,AN15))*10,0))&REPT("░",10-ROUND(MAX(0,MIN(1,AN15))*10,0)),"") | AN15: =IF(N(AL15)=0,"",MIN(1,AK15/AL15))
B16: 📖 Read / learn | C16: MIND | D16: Daily | AK16: =COUNTIF(E16:AI16,TRUE)+COUNTIF(E16:AI16,"x") | AL16: =ROUND($AP$9*7/7,0) | AM16: =IF(ISNUMBER(AN16),REPT("█",ROUND(MAX(0,MIN(1,AN16))*10,0))&REPT("░",10-ROUND(MAX(0,MIN(1,AN16))*10,0)),"") | AN16: =IF(N(AL16)=0,"",MIN(1,AK16/AL16))
B17: 🌙 Evening shutdown | C17: WORK | D17: Daily | AK17: =COUNTIF(E17:AI17,TRUE)+COUNTIF(E17:AI17,"x") | AL17: =ROUND($AP$9*7/7,0) | AM17: =IF(ISNUMBER(AN17),REPT("█",ROUND(MAX(0,MIN(1,AN17))*10,0))&REPT("░",10-ROUND(MAX(0,MIN(1,AN17))*10,0)),"") | AN17: =IF(N(AL17)=0,"",MIN(1,AK17/AL17))
B18: 😴 Lights out 22:00 ◆ | C18: HEALTH | D18: Daily | AK18: =COUNTIF(E18:AI18,TRUE)+COUNTIF(E18:AI18,"x") | AL18: =ROUND($AP$9*7/7,0) | AM18: =IF(ISNUMBER(AN18),REPT("█",ROUND(MAX(0,MIN(1,AN18))*10,0))&REPT("░",10-ROUND(MAX(0,MIN(1,AN18))*10,0)),"") | AN18: =IF(N(AL18)=0,"",MIN(1,AK18/AL18))
B19: LEVEL 2 · HIGH VALUE | AK19: weekly targets
B20: 🏋️ Strength session | C20: BODY | D20: 4× / wk | AK20: =COUNTIF(E20:AI20,TRUE)+COUNTIF(E20:AI20,"x") | AL20: =ROUND($AP$9*4/7,0) | AM20: =IF(ISNUMBER(AN20),REPT("█",ROUND(MAX(0,MIN(1,AN20))*10,0))&REPT("░",10-ROUND(MAX(0,MIN(1,AN20))*10,0)),"") | AN20: =IF(N(AL20)=0,"",MIN(1,AK20/AL20))
B21: 📈 Progression achieved | C21: BODY | D21: 4× / wk | AK21: =COUNTIF(E21:AI21,TRUE)+COUNTIF(E21:AI21,"x") | AL21: =ROUND($AP$9*4/7,0) | AM21: =IF(ISNUMBER(AN21),REPT("█",ROUND(MAX(0,MIN(1,AN21))*10,0))&REPT("░",10-ROUND(MAX(0,MIN(1,AN21))*10,0)),"") | AN21: =IF(N(AL21)=0,"",MIN(1,AK21/AL21))
B22: 🧱 Core | C22: BODY | D22: 3× / wk | AK22: =COUNTIF(E22:AI22,TRUE)+COUNTIF(E22:AI22,"x") | AL22: =ROUND($AP$9*3/7,0) | AM22: =IF(ISNUMBER(AN22),REPT("█",ROUND(MAX(0,MIN(1,AN22))*10,0))&REPT("░",10-ROUND(MAX(0,MIN(1,AN22))*10,0)),"") | AN22: =IF(N(AL22)=0,"",MIN(1,AK22/AL22))
B23: 🦵 Calves | C23: BODY | D23: 3× / wk | AK23: =COUNTIF(E23:AI23,TRUE)+COUNTIF(E23:AI23,"x") | AL23: =ROUND($AP$9*3/7,0) | AM23: =IF(ISNUMBER(AN23),REPT("█",ROUND(MAX(0,MIN(1,AN23))*10,0))&REPT("░",10-ROUND(MAX(0,MIN(1,AN23))*10,0)),"") | AN23: =IF(N(AL23)=0,"",MIN(1,AK23/AL23))
B24: 🚶 Cardio | C24: BODY | D24: 2× / wk | AK24: =COUNTIF(E24:AI24,TRUE)+COUNTIF(E24:AI24,"x") | AL24: =ROUND($AP$9*2/7,0) | AM24: =IF(ISNUMBER(AN24),REPT("█",ROUND(MAX(0,MIN(1,AN24))*10,0))&REPT("░",10-ROUND(MAX(0,MIN(1,AN24))*10,0)),"") | AN24: =IF(N(AL24)=0,"",MIN(1,AK24/AL24))
B25: 🧠 Deep work 2+ blocks | C25: WORK | D25: 5× / wk | AK25: =COUNTIF(E25:AI25,TRUE)+COUNTIF(E25:AI25,"x") | AL25: =ROUND($AP$9*5/7,0) | AM25: =IF(ISNUMBER(AN25),REPT("█",ROUND(MAX(0,MIN(1,AN25))*10,0))&REPT("░",10-ROUND(MAX(0,MIN(1,AN25))*10,0)),"") | AN25: =IF(N(AL25)=0,"",MIN(1,AK25/AL25))
B26: 👀 Posture & eye breaks | C26: POSTURE | D26: 5× / wk | AK26: =COUNTIF(E26:AI26,TRUE)+COUNTIF(E26:AI26,"x") | AL26: =ROUND($AP$9*5/7,0) | AM26: =IF(ISNUMBER(AN26),REPT("█",ROUND(MAX(0,MIN(1,AN26))*10,0))&REPT("░",10-ROUND(MAX(0,MIN(1,AN26))*10,0)),"") | AN26: =IF(N(AL26)=0,"",MIN(1,AK26/AL26))
B27: 🧹 Home reset | C27: LIFE ADMIN | D27: 5× / wk | AK27: =COUNTIF(E27:AI27,TRUE)+COUNTIF(E27:AI27,"x") | AL27: =ROUND($AP$9*5/7,0) | AM27: =IF(ISNUMBER(AN27),REPT("█",ROUND(MAX(0,MIN(1,AN27))*10,0))&REPT("░",10-ROUND(MAX(0,MIN(1,AN27))*10,0)),"") | AN27: =IF(N(AL27)=0,"",MIN(1,AK27/AL27))
B28: 👦 Father–son time | C28: RELATIONSHIPS | D28: 1× / wk | AK28: =COUNTIF(E28:AI28,TRUE)+COUNTIF(E28:AI28,"x") | AL28: =ROUND($AP$9*1/7,0) | AM28: =IF(ISNUMBER(AN28),REPT("█",ROUND(MAX(0,MIN(1,AN28))*10,0))&REPT("░",10-ROUND(MAX(0,MIN(1,AN28))*10,0)),"") | AN28: =IF(N(AL28)=0,"",MIN(1,AK28/AL28))
B29: 🥂 Couple time / date | C29: RELATIONSHIPS | D29: 1× / wk | AK29: =COUNTIF(E29:AI29,TRUE)+COUNTIF(E29:AI29,"x") | AL29: =ROUND($AP$9*1/7,0) | AM29: =IF(ISNUMBER(AN29),REPT("█",ROUND(MAX(0,MIN(1,AN29))*10,0))&REPT("░",10-ROUND(MAX(0,MIN(1,AN29))*10,0)),"") | AN29: =IF(N(AL29)=0,"",MIN(1,AK29/AL29))
B30: 📞 Family check-in | C30: RELATIONSHIPS | D30: 1× / wk | AK30: =COUNTIF(E30:AI30,TRUE)+COUNTIF(E30:AI30,"x") | AL30: =ROUND($AP$9*1/7,0) | AM30: =IF(ISNUMBER(AN30),REPT("█",ROUND(MAX(0,MIN(1,AN30))*10,0))&REPT("░",10-ROUND(MAX(0,MIN(1,AN30))*10,0)),"") | AN30: =IF(N(AL30)=0,"",MIN(1,AK30/AL30))
B31: ⛪ Church / worship | C31: SPIRIT | D31: 1× / wk | AK31: =COUNTIF(E31:AI31,TRUE)+COUNTIF(E31:AI31,"x") | AL31: =ROUND($AP$9*1/7,0) | AM31: =IF(ISNUMBER(AN31),REPT("█",ROUND(MAX(0,MIN(1,AN31))*10,0))&REPT("░",10-ROUND(MAX(0,MIN(1,AN31))*10,0)),"") | AN31: =IF(N(AL31)=0,"",MIN(1,AK31/AL31))
B32: 🍱 Meal prep | C32: LIFE ADMIN | D32: 1× / wk | AK32: =COUNTIF(E32:AI32,TRUE)+COUNTIF(E32:AI32,"x") | AL32: =ROUND($AP$9*1/7,0) | AM32: =IF(ISNUMBER(AN32),REPT("█",ROUND(MAX(0,MIN(1,AN32))*10,0))&REPT("░",10-ROUND(MAX(0,MIN(1,AN32))*10,0)),"") | AN32: =IF(N(AL32)=0,"",MIN(1,AK32/AL32))
B33: LEVEL 3 · OPTIONAL | AK33: bonus, never guilt
B34: 🕊️ Meditation / journal | C34: MIND | D34: Optional | AK34: =COUNTIF(E34:AI34,TRUE)+COUNTIF(E34:AI34,"x") | AL34: — | AM34: =IF(AK34=0,"",AK34&" × bonus")
B35: ➕ Extra walk / cardio | C35: BODY | D35: Optional | AK35: =COUNTIF(E35:AI35,TRUE)+COUNTIF(E35:AI35,"x") | AL35: — | AM35: =IF(AK35=0,"",AK35&" × bonus")
B36: ➕ Extra mobility | C36: POSTURE | D36: Optional | AK36: =COUNTIF(E36:AI36,TRUE)+COUNTIF(E36:AI36,"x") | AL36: — | AM36: =IF(AK36=0,"",AK36&" × bonus")
B37: ➕ Extra reading | C37: MIND | D37: Optional | AK37: =COUNTIF(E37:AI37,TRUE)+COUNTIF(E37:AI37,"x") | AL37: — | AM37: =IF(AK37=0,"",AK37&" × bonus")
B39: Foundation score | C39: auto · 9 pillars of the day | E39: =Data!BF190 | F39: =Data!BF191 | G39: =Data!BF192 | H39: =Data!BF193 | I39: =Data!BF194 | J39: =Data!BF195 | K39: =Data!BF196 | L39: =Data!BF197 | M39: =Data!BF198 | N39: =Data!BF199 | O39: =Data!BF200 | P39: =Data!BF201 | Q39: =Data!BF202 | R39: =Data!BF203 | S39: =Data!BF204 | T39: =Data!BF205 | U39: =Data!BF206 | V39: =Data!BF207 | W39: =Data!BF208 | X39: =Data!BF209 | Y39: =Data!BF210 | Z39: =Data!BF211 | AA39: =Data!BF212 | AB39: =Data!BF213 | AC39: =Data!BF214 | AD39: =Data!BF215 | AE39: =Data!BF216 | AF39: =Data!BF217 | AG39: =Data!BF218 | AH39: =Data!BF219 | AI39: =Data!BF220 | AK39: =IFERROR(AVERAGE(E39:AI39),"") | AL39: avg | AM39: =IF(ISNUMBER(AN39),REPT("█",ROUND(MAX(0,MIN(1,AN39))*10,0))&REPT("░",10-ROUND(MAX(0,MIN(1,AN39))*10,0)),"") | AN39: =AK39
B40: Non-negotiables done | C40: of 9 (8 on non-work days) | E40: =IF(Data!BF190="","",Data!BJ190) | F40: =IF(Data!BF191="","",Data!BJ191) | G40: =IF(Data!BF192="","",Data!BJ192) | H40: =IF(Data!BF193="","",Data!BJ193) | I40: =IF(Data!BF194="","",Data!BJ194) | J40: =IF(Data!BF195="","",Data!BJ195) | K40: =IF(Data!BF196="","",Data!BJ196) | L40: =IF(Data!BF197="","",Data!BJ197) | M40: =IF(Data!BF198="","",Data!BJ198) | N40: =IF(Data!BF199="","",Data!BJ199) | O40: =IF(Data!BF200="","",Data!BJ200) | P40: =IF(Data!BF201="","",Data!BJ201) | Q40: =IF(Data!BF202="","",Data!BJ202) | R40: =IF(Data!BF203="","",Data!BJ203) | S40: =IF(Data!BF204="","",Data!BJ204) | T40: =IF(Data!BF205="","",Data!BJ205) | U40: =IF(Data!BF206="","",Data!BJ206) | V40: =IF(Data!BF207="","",Data!BJ207) | W40: =IF(Data!BF208="","",Data!BJ208) | X40: =IF(Data!BF209="","",Data!BJ209) | Y40: =IF(Data!BF210="","",Data!BJ210) | Z40: =IF(Data!BF211="","",Data!BJ211) | AA40: =IF(Data!BF212="","",Data!BJ212) | AB40: =IF(Data!BF213="","",Data!BJ213) | AC40: =IF(Data!BF214="","",Data!BJ214) | AD40: =IF(Data!BF215="","",Data!BJ215) | AE40: =IF(Data!BF216="","",Data!BJ216) | AF40: =IF(Data!BF217="","",Data!BJ217) | AG40: =IF(Data!BF218="","",Data!BJ218) | AH40: =IF(Data!BF219="","",Data!BJ219) | AI40: =IF(Data!BF220="","",Data!BJ220)
B42: DAILY FOUNDATION SCORE | AK42: WEEKLY AVERAGE
B43: One number for the day, built from 9 things: Sleep · Movement · Protein · Water · Steps · Prayer · Top 3 (work days) · Fiancée · Read/learn M days are scored on the Minimum Viable Day. S days are paused — no score, no guilt. ◆ = part of the Minimum Viable Day
AK44: Week 1 | AM44: =IF(ISNUMBER(AN44),REPT("█",ROUND(MAX(0,MIN(1,AN44))*10,0))&REPT("░",10-ROUND(MAX(0,MIN(1,AN44))*10,0)),"") | AN44: =IFERROR(AVERAGE(E39:K39),"")
AK46: Week 2 | AM46: =IF(ISNUMBER(AN46),REPT("█",ROUND(MAX(0,MIN(1,AN46))*10,0))&REPT("░",10-ROUND(MAX(0,MIN(1,AN46))*10,0)),"") | AN46: =IFERROR(AVERAGE(L39:R39),"")
AK48: Week 3 | AM48: =IF(ISNUMBER(AN48),REPT("█",ROUND(MAX(0,MIN(1,AN48))*10,0))&REPT("░",10-ROUND(MAX(0,MIN(1,AN48))*10,0)),"") | AN48: =IFERROR(AVERAGE(S39:Y39),"")
AK50: Week 4 | AM50: =IF(ISNUMBER(AN50),REPT("█",ROUND(MAX(0,MIN(1,AN50))*10,0))&REPT("░",10-ROUND(MAX(0,MIN(1,AN50))*10,0)),"") | AN50: =IFERROR(AVERAGE(Z39:AF39),"")
AK52: Week 5 | AM52: =IF(ISNUMBER(AN52),REPT("█",ROUND(MAX(0,MIN(1,AN52))*10,0))&REPT("░",10-ROUND(MAX(0,MIN(1,AN52))*10,0)),"") | AN52: =IFERROR(AVERAGE(AG39:AI39),"")
B56: BODY & MIND | E56: Week 1 | L56: Week 2 | S56: Week 3 | Z56: Week 4 | AG56: Week 5 | AK56: ANALYSIS
B57: Log the numbers you have. Blank is fine. | E57: =E6 | F57: =F6 | G57: =G6 | H57: =H6 | I57: =I6 | J57: =J6 | K57: =K6 | L57: =L6 | ... AI57: =AI6 | AK57: Avg | AL57: Target | AM57: Progress | AN57: Hit %
B58: Metric | C58: Unit | D58: Target | E58: =E7 | F58: =F7 | G58: =G7 | H58: =H7 | I58: =I7 | J58: =J7 | K58: =K7 | L58: =L7 | ... AI58: =AI7 | AK58: hit % = days on target ÷ days logged
B59: ⚖️ Weight | C59: kg | D59: AM, 7-day avg | AK59: =IF($AP$11=0,"",INDEX(Data!$BI$4:$BI$375,MATCH($AP$11,Data!$A$4:$A$375,0))) | AL59: 7d avg | AM59: =IF($AP$11=0,"",IFERROR("Δ month "&TEXT(AK59-INDEX(Data!$BI$4:$BI$375,MATCH($AP$12,Data!$A$4:$A$375,0)),"+0.0;-0.0")&" kg",""))
B60: 👣 Steps | C60: steps | D60: adaptive | AK60: =IFERROR(AVERAGE(E60:AI60),"") | AL60: =IFERROR(MAX(E69:AI69)*1000,"") | AM60: =IF(AND(ISNUMBER(AK60),ISNUMBER(AL60)),IF(ISNUMBER(AK60/AL60),REPT("█",ROUND(MAX(0,MIN(1,AK60/AL60))*10,0))&REPT("░",10-ROUND(MAX(0,MIN(1,AK60/AL60))*10,0)),""),"") | AN60: =IFERROR(SUMIFS(Data!$AY$4:$AY$375,Data!$B$4:$B$375,7)/COUNTIFS(Data!$B$4:$B$375,7,Data!$AG$4:$AG$375,">0"),"")
B61: 🍗 Protein | C61: g | D61: 150 g | AK61: =IFERROR(AVERAGE(E61:AI61),"") | AL61: =ProtTarget | AM61: =IF(AND(ISNUMBER(AK61),ISNUMBER(AL61)),IF(ISNUMBER(AK61/AL61),REPT("█",ROUND(MAX(0,MIN(1,AK61/AL61))*10,0))&REPT("░",10-ROUND(MAX(0,MIN(1,AK61/AL61))*10,0)),""),"") | AN61: =IFERROR(SUMIFS(Data!$AW$4:$AW$375,Data!$B$4:$B$375,7)/COUNTIFS(Data!$B$4:$B$375,7,Data!$AH$4:$AH$375,">0"),"")
B62: 💧 Water | C62: L | D62: 2.5–3 L | AK62: =IFERROR(AVERAGE(E62:AI62),"") | AL62: =WaterHit | AM62: =IF(AND(ISNUMBER(AK62),ISNUMBER(AL62)),IF(ISNUMBER(AK62/AL62),REPT("█",ROUND(MAX(0,MIN(1,AK62/AL62))*10,0))&REPT("░",10-ROUND(MAX(0,MIN(1,AK62/AL62))*10,0)),""),"") | AN62: =IFERROR(SUMIFS(Data!$AX$4:$AX$375,Data!$B$4:$B$375,7)/COUNTIFS(Data!$B$4:$B$375,7,Data!$AI$4:$AI$375,">0"),"")
B63: 🔥 Calories | C63: kcal | D63: 1.8–2k | AK63: =IFERROR(AVERAGE(E63:AI63),"") | AL63: =TEXT(KcalMin,"#,##0")&"–"&TEXT(KcalMax,"#,##0") | AM63: =IF(ISNUMBER(AN63),REPT("█",ROUND(MAX(0,MIN(1,AN63))*10,0))&REPT("░",10-ROUND(MAX(0,MIN(1,AN63))*10,0)),"") | AN63: =IFERROR(COUNTIFS(E63:AI63,">="&$AP$7,E63:AI63,"<="&$AP$8)/COUNT(E63:AI63),"")
B64: 🛌 Sleep | C64: hours | D64: 7.5–8.5 h | AK64: =IFERROR(AVERAGE(E64:AI64),"") | AL64: =SleepTarget | AM64: =IF(AND(ISNUMBER(AK64),ISNUMBER(AL64)),IF(ISNUMBER(AK64/AL64),REPT("█",ROUND(MAX(0,MIN(1,AK64/AL64))*10,0))&REPT("░",10-ROUND(MAX(0,MIN(1,AK64/AL64))*10,0)),""),"") | AN64: =IFERROR(COUNTIF(E64:AI64,">="&$AP$4)/COUNT(E64:AI64),"")
B65: ⚡ Energy | C65: 1–10 | D65: 1–10 | AK65: =IFERROR(AVERAGE(E65:AI65),"") | AL65: / 10 | AM65: =IF(ISNUMBER(AK65),IF(ISNUMBER(AK65/10),REPT("█",ROUND(MAX(0,MIN(1,AK65/10))*10,0))&REPT("░",10-ROUND(MAX(0,MIN(1,AK65/10))*10,0)),""),"")
B66: 🌡️ Stress | C66: 1–10 | D66: 1–10 | AK66: =IFERROR(AVERAGE(E66:AI66),"") | AL66: / 10 | AM66: =IF(ISNUMBER(AK66),IF(ISNUMBER(AK66/10),REPT("█",ROUND(MAX(0,MIN(1,AK66/10))*10,0))&REPT("░",10-ROUND(MAX(0,MIN(1,AK66/10))*10,0)),""),"")
B67: 🙂 Mood | C67: 1–10 | D67: 1–10 | AK67: =IFERROR(AVERAGE(E67:AI67),"") | AL67: / 10 | AM67: =IF(ISNUMBER(AK67),IF(ISNUMBER(AK67/10),REPT("█",ROUND(MAX(0,MIN(1,AK67/10))*10,0))&REPT("░",10-ROUND(MAX(0,MIN(1,AK67/10))*10,0)),""),"")
B68: ↳ Weight · 7-day average | C68: decide on this | E68: =Data!BI190 | F68: =Data!BI191 | G68: =Data!BI192 | H68: =Data!BI193 | I68: =Data!BI194 | J68: =Data!BI195 | K68: =Data!BI196 | L68: =Data!BI197 | M68: =Data!BI198 | N68: =Data!BI199 | O68: =Data!BI200 | P68: =Data!BI201 | Q68: =Data!BI202 | R68: =Data!BI203 | S68: =Data!BI204 | T68: =Data!BI205 | U68: =Data!BI206 | V68: =Data!BI207 | W68: =Data!BI208 | X68: =Data!BI209 | Y68: =Data!BI210 | Z68: =Data!BI211 | AA68: =Data!BI212 | AB68: =Data!BI213 | AC68: =Data!BI214 | AD68: =Data!BI215 | AE68: =Data!BI216 | AF68: =Data!BI217 | AG68: =Data!BI218 | AH68: =Data!BI219 | AI68: =Data!BI220
B69: ↳ Steps target (adaptive) | C69: 7k → 8k → 9k | E69: =IF(Data!A190="","",Data!AR190/1000) | F69: =IF(Data!A191="","",Data!AR191/1000) | G69: =IF(Data!A192="","",Data!AR192/1000) | H69: =IF(Data!A193="","",Data!AR193/1000) | I69: =IF(Data!A194="","",Data!AR194/1000) | J69: =IF(Data!A195="","",Data!AR195/1000) | K69: =IF(Data!A196="","",Data!AR196/1000) | L69: =IF(Data!A197="","",Data!AR197/1000) | M69: =IF(Data!A198="","",Data!AR198/1000) | N69: =IF(Data!A199="","",Data!AR199/1000) | O69: =IF(Data!A200="","",Data!AR200/1000) | P69: =IF(Data!A201="","",Data!AR201/1000) | Q69: =IF(Data!A202="","",Data!AR202/1000) | R69: =IF(Data!A203="","",Data!AR203/1000) | S69: =IF(Data!A204="","",Data!AR204/1000) | T69: =IF(Data!A205="","",Data!AR205/1000) | U69: =IF(Data!A206="","",Data!AR206/1000) | V69: =IF(Data!A207="","",Data!AR207/1000) | W69: =IF(Data!A208="","",Data!AR208/1000) | X69: =IF(Data!A209="","",Data!AR209/1000) | Y69: =IF(Data!A210="","",Data!AR210/1000) | Z69: =IF(Data!A211="","",Data!AR211/1000) | AA69: =IF(Data!A212="","",Data!AR212/1000) | AB69: =IF(Data!A213="","",Data!AR213/1000) | AC69: =IF(Data!A214="","",Data!AR214/1000) | AD69: =IF(Data!A215="","",Data!AR215/1000) | AE69: =IF(Data!A216="","",Data!AR216/1000) | AF69: =IF(Data!A217="","",Data!AR217/1000) | AG69: =IF(Data!A218="","",Data!AR218/1000) | AH69: =IF(Data!A219="","",Data!AR219/1000) | AI69: =IF(Data!A220="","",Data!AR220/1000)
B71: TRENDS | E71: MIND & RECOVERY · energy · stress · mood | U71: WEIGHT · daily vs 7-day average
B72: Energy, stress and mood show how the month feels, not just what got done. Weight: the dots jump around with water and salt. The 7-day average is the only line that decides anything. Target pace: −0.4 to −0.8 kg a week.

Sheet May 2027
AP1: =DATE(2027,5,1)
B2: =UPPER(TEXT($AP$1,"mmmm")) | E2: HABITS | L2: CHECK-INS | S2: FOUNDATION · MONTH | AC2: ROLLING 7-DAY | AK2: ROLLING 30-DAY | AP2: =ProtHit
B3: ="— Life OS · Habit Tracker · "&YEAR($AP$1)&" —" | E3: =COUNTA(B10:B18,B20:B32,B34:B37) | L3: =COUNTIF(E10:AI18,TRUE)+COUNTIF(E10:AI18,"x")+COUNTIF(E20:AI32,TRUE)+COUNTIF(E20:AI32,"x")+COUNTIF(E34:AI37,TRUE)+COUNTIF(E34:AI37,"x") | S3: =IF(ISNUMBER(AK39),TEXT(AK39,"0%")&" "&IF(ISNUMBER(AK39),REPT("█",ROUND(MAX(0,MIN(1,AK39))*12,0))&REPT("░",12-ROUND(MAX(0,MIN(1,AK39))*12,0)),""),"—") | AC3: =IF(ISNUMBER(IFERROR(INDEX(Data!$BG$4:$BG$375,MATCH($AP$13,Data!$A$4:$A$375,0)),"")),TEXT(IFERROR(INDEX(Data!$BG$4:$BG$375,MATCH($AP$13,Data!$A$4:$A$375,0)),""),"0%")&" · "&IF(NOT(ISNUMBER(IFERROR(INDEX(Data!$BG$4:$BG$375,MATCH($AP$13,Data!$A$4:$A$375,0)),""))),"—",IF(IFERROR(INDEX(Data!$BG$4:$BG$375,MATCH($AP$13,Data!$A$4:$A$375,0)),"")>=Band1,"GREEN",IF(IFERROR(INDEX(Data!$BG$4:$BG$375,MATCH($AP$13,Data!$A$4:$A$375,0)),"")>=Band2,"GOOD",IF(IFERROR(INDEX(Data!$BG$4:$BG$375,MATCH($AP$13,Data!$A$4:$A$375,0)),"")>=Band3,"NEEDS ATTENTION","RESET")))),"—") | AK3: =IF(ISNUMBER(IFERROR(INDEX(Data!$BH$4:$BH$375,MATCH($AP$13,Data!$A$4:$A$375,0)),"")),TEXT(IFERROR(INDEX(Data!$BH$4:$BH$375,MATCH($AP$13,Data!$A$4:$A$375,0)),""),"0%")&" · "&IF(NOT(ISNUMBER(IFERROR(INDEX(Data!$BH$4:$BH$375,MATCH($AP$13,Data!$A$4:$A$375,0)),""))),"—",IF(IFERROR(INDEX(Data!$BH$4:$BH$375,MATCH($AP$13,Data!$A$4:$A$375,0)),"")>=Band1,"GREEN",IF(IFERROR(INDEX(Data!$BH$4:$BH$375,MATCH($AP$13,Data!$A$4:$A$375,0)),"")>=Band2,"GOOD",IF(IFERROR(INDEX(Data!$BH$4:$BH$375,MATCH($AP$13,Data!$A$4:$A$375,0)),"")>=Band3,"NEEDS ATTENTION","RESET")))),"—") | AP3: =WaterHit
AP4: =SleepMin
B5: MY HABITS | E5: Week 1 | L5: Week 2 | S5: Week 3 | Z5: Week 4 | AG5: Week 5 | AK5: ANALYSIS | AP5: =SleepLow
